Workbook

Sheet เปรียบเทียบทุก Solution
A1: ตารางเปรียบเทียบความเป็นไปได้ของทุกข้อเสนอ (Multi-Solution Feasibility Summary)
A2: วิเคราะห์เปรียบเทียบเชิงระบบตามเกณฑ์ TELOS+S (เต็ม 100) และเมทริกซ์ศักยภาพด้านวิศวกรรมหุ่นยนต์ (เต็ม 10 แยกอิสระ)
A4: ลำดับ | B4: รหัสข้อเสนอ (Solution ID) | C4: ชื่อแนวทางแก้ปัญหา (Title / Concept) | D4: คะแนนรวม (เต็ม 100) | E4: T: เทคนิค (/20) | F4: E: เศรษฐศาสตร์ (/20) | G4: L: กฎหมาย (/15) | H4: O: ปฏิบัติการ (/20) | I4: S: แผนงาน (/15) | J4: +S: ยั่งยืน (/10) | K4: ผลการประเมิน (Verdict) | L4: จุดแข็งสำคัญ (Key Strengths) | M4: จุดติดขัดวิกฤต (Critical Bottlenecks) | N4: คำแนะนำเชิงระบบ (Strategic Advice) | O4: Robotics Potential (/10) | P4: เหตุผลความเข้ากันได้ด้านหุ่นยนต์ (Robotics Engineering Rationale)
A5: 1 | B5: Solution-1 | C5: Recession Rate (dh/dt) Predictive Filtering for QRT Dispatch (Ann Arbor Case) | D5: ='Solution-1'!W9 -> 93.433343 | E5: ='Solution-1'!D17 -> 17.6 | F5: ='Solution-1'!D18 -> 18.666 | G5: ='Solution-1'!D19 -> 15 | H5: ='Solution-1'!D20 -> 18.658 | I5: ='Solution-1'!D21 -> 13.5 | J5: ='Solution-1'!D22 -> 10 | K5: ='Solution-1'!W12 -> ผ่านเกณฑ์ระดับสูง (HIGHLY VIABLE) | L5: ใช้สมการอนุพันธ์ชลศาสตร์คำนวณอัตราน้ำลด dh/dt เทียบกับเวลาเดินทาง 20-30 นาที ตัด Empty Cases ได้ 40-50% สมาชิกแบ่งงานชัดเจน ต้นทุนต่ำ (< 3,500 บ.) | M5: ต้องมีหลักฐาน Digital Evidence Card ประกอบการปิดงานบน Traffy Fondue และเซนเซอร์ต้องกรองฟองคลื่นน้ำเพื่อเลี่ยง Derivative Kick | N5: พัฒนาโมดูลคำนวณ dh/dt บน Python/ROS 2 ร่วมกับ Screw Terminal Shield และออกแบบ Median Filter กรองสัญญาณผิวน้ำ | O5: 7.5 | P5: มีความเข้ากันได้สูงในแกนคณิตศาสตร์วิศวกรรม ทฤษฎีระบบควบคุม (Control Theory) และการประมวลผลสัญญาณ (Signal Processing & State Estimation) ของ JK แต่คะแนนอยู่ที่ 7.5 เนื่องจากขาด Physical Actuation และกลไกการเคลื่อนที่
A6: 2 | B6: Solution-2 | C6: PUB Singapore CWOS 2-Factor Authentication Dispatch Filter | D6: ='Solution-2'!W9 -> 91.963196 | E6: ='Solution-2'!D17 -> 16.8 | F6: ='Solution-2'!D18 -> 17.332 | G6: ='Solution-2'!D19 -> 15 | H6: ='Solution-2'!D20 -> 19.322 | I6: ='Solution-2'!D21 -> 13.5 | J6: ='Solution-2'!D22 -> 10 | K6: ='Solution-2'!W12 -> ผ่านเกณฑ์ระดับสูง (HIGHLY VIABLE) | L6: กรองการสั่งการเจ้าหน้าที่หน่วยเคลื่อนที่เร็วด้วยปัจจัยคู่ (Radar Rainfall API + Ultrasonic Water Level) สกัด False Alarms ฝนตกไม่ท่วมได้เด็ดขาด ต้นทุนต่ำมาก | M6: ต้องพึ่งพา Radar Rainfall API ภายนอก หาก API ล่มหรือข้อมูลดีเลย์ 10-15 นาที จะกระทบการตัดสินใจ | N6: ทำระบบ Fallback ไปใช้ค่าจากเซนเซอร์ระดับน้ำหน้างานแบบเดี่ยวหาก API ขาดการเชื่อมต่อ และเชื่อมเข้า LINE Official ของเขต | O6: 5 | P6: มีความเข้ากันได้ในแกนการประมวลผลข้อมูลและสถาปัตยกรรมตรรกะควบคุม (Control & Decision Logic) แต่ขาดแกนกลไก (Mechanics) และ Actuation ของหุ่นยนต์อย่างสิ้นเชิง คะแนนจึงอยู่ที่ 5.0
A7: 3 | B7: Solution-3 | C7: Acoustic Sewer Measurement & Pre-Screening Maintenance (UK/USA SL-RAT Case) | D7: ='Solution-3'!W9 -> 69.634963 | E7: ='Solution-3'!D17 -> 12.8 | F7: ='Solution-3'!D18 -> 14.668 | G7: ='Solution-3'!D19 -> 10.5 | H7: ='Solution-3'!D20 -> 12.66 | I7: ='Solution-3'!D21 -> 9 | J7: ='Solution-3'!D22 -> 10 | K7: ='Solution-3'!W12 -> ผ่านแบบมีเงื่อนไข (CONDITIONALLY VIABLE) | L7: คัดกรองสภาพความสะอาดท่อระบายน้ำด้วยคลื่นเสียงสะท้อน (Acoustic SL-RAT) จัดเทียร์ 3 กลุ่ม (0-3 ล้างทันที, 4-6 จัดคิว, 7-10 ปกติ) ลดงบขุดลอกสุ่มได้มหาศาล | M7: การออกแบบกระบอกสะท้อนเสียงฮอร์น (Acoustic Horn) และการประมวลผลสัญญาณคลื่นเสียง (DSP) มีความซับซ้อนสูง และต้องเปิดฝาท่อริมถนน | N7: ใช้กระบอกสะท้อนเสียงแบบ 3D Printing ร่วมกับโมดูลขยายเสียงสำเร็จรูป และทดสอบเทียบเคียงกับโมเดลท่อ PVC ในห้องปฏิบัติการก่อนลงพื้นที่จริง | O7: 8.5 | P7: มีความเข้ากันได้สูงมากกับศาสตร์วิศวกรรมหุ่นยนต์ในแกน Sensing & Signal Processing ระดับ Transducer และทฤษฎีคลื่นเสียง มีการต่อยอดสู่หุ่นยนต์ตรวจสอบท่อระบายน้ำอัตโนมัติ (Pipe Inspection Robot) ได้โดยตรง คะแนนจึงอยู่ที่ 8.5
A8: 4 | B8: Solution-4 | C8: Underground Flow Telemetry & Predictive Maintenance (Jakarta Case) | D8: ='Solution-4'!W9 -> 66.334633 | E8: ='Solution-4'!D17 -> 12 | F8: ='Solution-4'!D18 -> 13.334 | G8: ='Solution-4'!D19 -> 12 | H8: ='Solution-4'!D20 -> 10.66 | I8: ='Solution-4'!D21 -> 9 | J8: ='Solution-4'!D22 -> 9.334 | K8: ='Solution-4'!W12 -> ผ่านแบบมีเงื่อนไข (CONDITIONALLY VIABLE) | L8: ติดตั้งโครงข่ายเซนเซอร์ใต้ดินส่งสัญญาณ LoRaWAN รายงานอัตราการไหลและเตือนจุดวิกฤตแบบกระจายตัว | M8: สภาพแวดล้อมใต้ท่อระบายน้ำมีความชื้น 100% ก๊าซไข่เน่า (H2S) กัดกร่อน และสัญญาณวิทยุทะลุฝาท่อคอนกรีตขึ้นมาได้ยาก | N8: ใช้เสาอากาศแบบฝังขอบฝาท่อระบายน้ำ (Surface-mount Antenna) เคลือบเรซินกันกรดในกล่อง IP68 และตั้งเวลาส่งสัญญาณเป็นรอบเพื่อประหยัดแบตเตอรี่ | O8: 6.5 | P8: มีความเข้ากันได้ในแกน Distributed Sensor Network, การสื่อสารทางไกล และการประมวลผลข้อมูลโทรมาตร แต่ขาดแกนกลไกและการเคลื่อนที่ของหุ่นยนต์ คะแนนจึงอยู่ที่ 6.5
A9: 5 | B9: Solution-5 | C9: UHI Latent Heat Precision Road Cooling (Micro-dosing 0.2-0.4 mm Evaporative Spraying) | D9: ='Solution-5'!W9 -> 67.938794 | E9: ='Solution-5'!D17 -> 13.6 | F9: ='Solution-5'!D18 -> 13.334 | G9: ='Solution-5'!D19 -> 10.5 | H9: ='Solution-5'!D20 -> 10.664 | I9: ='Solution-5'!D21 -> 10.5 | J9: ='Solution-5'!D22 -> 9.334 | K9: ='Solution-5'!W12 -> ผ่านแบบมีเงื่อนไข (CONDITIONALLY VIABLE) | L9: ระบบพ่นละอองน้ำละเอียด (0.2–0.4 mm) ระบายความร้อนผิวทางเท้าและถนนด้วยความร้อนแฝงการกลายเป็นไอ (Latent Heat) มีศักยภาพด้าน Mechatronics และ Actuation สูงสุด | M9: การพ่นน้ำบนถนนหลวงมีความเสี่ยงต่อกฎหมายจราจร (ผิวทางลื่น) และโครงสร้างบูมฉีดน้ำบนรถเสี่ยงต่อการสั่นสะเทือนและหัวฉีดอุดตันจากตะกรัน | N9: ติดตั้งเซนเซอร์วัดความชื้นผิวถนนแบบเรียลไทม์เพื่อตัดการฉีดพ่นทันที และติดตั้งระบบกรองน้ำ 2 ชั้น (Sediment + Anti-scale) | O9: 9 | P9: มีความเข้ากันได้อย่างสมบูรณ์แบบสูงสุดกับหลักสูตรวิศวกรรมหุ่นยนต์และระบบอัตโนมัติ (FIBO) ครบทั้ง 3 เสาหลัก: Perception (Thermal Imaging), Control (Thermodynamic Closed-loop Control) และ Actuation/Mechatronics (Vehicle-mounted High-pressure Hydraulics & Mechanics) ได้คะแนน 9.0

Sheet Solution-1
A1: เมทริกซ์ประเมินความเป็นไปได้เชิงระบบ TELOS+S: Recession Rate (dh/dt) Predictive Filtering for QRT Dispatch (Ann Arbor Case)
A2: ระบบคะแนนจำนวนเต็มเด็ดขาด: 1, 2, 3, 4, 5 เท่านั้น (ไม่มีจุดทศนิยม / ไม่มี 0.5) | โครงสร้างแบบ Transposed แนวนอน
A4: รหัสคำถาม (Question Code) | B4: T-01 | C4: T-02 | D4: T-03 | E4: T-04 | F4: T-05 | G4: E-01 | H4: E-02 | I4: E-03 | J4: L-01 | K4: L-02 | L4: O-01 | M4: O-02 | N4: O-03 | O4: O-04 | P4: O-05 | Q4: O-06 | R4: S-01 | S4: S-02 | T4: SDG-01 | U4: SDG-02 | V4: SDG-03 | W4: สรุปภาพรวม (SUMMARY)
A5: มิติการประเมิน (TELOS+S Pillar) | B5: ด้านเทคโนโลยีและวิศวกรรม (Technical Feasibility) | C5: ด้านเทคโนโลยีและวิศวกรรม (Technical Feasibility) | D5: ด้านเทคโนโลยีและวิศวกรรม (Technical Feasibility) | E5: ด้านเทคโนโลยีและวิศวกรรม (Technical Feasibility) | F5: ด้านเทคโนโลยีและวิศวกรรม (Technical Feasibility) | G5: ด้านเศรษฐศาสตร์ (Economic Feasibility) | H5: ด้านเศรษฐศาสตร์ (Economic Feasibility) | I5: ด้านเศรษฐศาสตร์ (Economic Feasibility) | J5: ด้านกฎหมายและสถาบัน (Legal & Institutional Feasibility) | K5: ด้านกฎหมายและสถาบัน (Legal & Institutional Feasibility) | L5: ด้านการปฏิบัติการ (Operational Feasibility) | M5: ด้านการปฏิบัติการ (Operational Feasibility) | N5: ด้านการปฏิบัติการ (Operational Feasibility) | O5: ด้านการปฏิบัติการ (Operational Feasibility) | P5: ด้านการปฏิบัติการ (Operational Feasibility) | Q5: ด้านการปฏิบัติการ (Operational Feasibility) | R5: ด้านแผนงานและเวลา (Schedule Feasibility) | S5: ด้านแผนงานและเวลา (Schedule Feasibility) | T5: +S ด้านความยั่งยืน (Sustainable Feasibility) | U5: +S ด้านความยั่งยืน (Sustainable Feasibility) | V5: +S ด้านความยั่งยืน (Sustainable Feasibility) | W5: ผลรวมทุกมิติ (All Pillars)
A6: คำถามทดสอบความเสี่ยงจริง (Stress-Test Question) | B6: Implementation (Build vs. Buy Burden): ระบบต้องพัฒนาขึ้นเองจากศูนย์ (Custom R&D) หรือสามารถประกอบขึ้นจากโมดูลสำเร็จรูป (COTS Assembly)? | C6: Access (Tech Stack & Ecosystem Permissions): สแตกเทคโนโลยีและสิทธิ์การเข้าถึงระบบ (Permissions & Ecosystem) มีความเปิดกว้างเพียงใดในการตรวจสอบ แก้ไข และพัฒนาต่อยอด? | D6: Supply (Component Procurement & Vendor Availability): ชิ้นส่วนและอุปกรณ์หลักมีห่วงโซ่อุปทานและความพร้อมในการจัดหา (Supply & Vendor Availability) จากผู้จำหน่ายในระดับใด? | E6: Base Performance (Technology Readiness Level - TRL): ระดับความพร้อมของเทคโนโลยี (TRL) ของระบบอยู่ในขั้นใดเมื่อเทียบกับสภาวะแวดล้อมการใช้งานจริงหน้างาน? | F6: Team Compatibility (Manpower & Skill Redundancy): ทักษะของสมาชิกในทีมมีความเข้ากันได้และการกระจายความเชี่ยวชาญสำรอง (Bus Factor & Redundancy) มากน้อยเพียงใด? | G6: ROI (Payback Period / Value Horizon): ระยะเวลาคืนทุนและกรอบเวลาการสร้างผลตอบแทนคุ้มค่า (Payback Horizon) ต่อระบบสาธารณะหรือผู้ใช้งานอยู่ในเกณฑ์ใด? | H6: Dependencies of Component (Vendor Lock-in & Service Autonomy): ระบบมีความเป็นอิสระจากการผูกขาดของผู้ผลิต (Vendor Lock-in) มากน้อยเพียงใด และสามารถซ่อมบำรุงด้วยเครื่องมือเปิดได้เองหรือไม่? | I6: Scrap Margin (Safety Allowance for Blown ICs & Iterations): โครงการมีการจัดสรรงบประมาณสำรองสำหรับชิ้นส่วนทดแทนกรณีเสียหาย (Scrap Margin) และการทดลองซ้ำมากน้อยเพียงใด? | J6: Felony and Civil Law (Regulatory & Public Safety Compliance): ระบบและการติดตั้งมีความสอดคล้องต่อข้อบังคับทางกฎหมายอาญา แพ่ง ระเบียบจราจร และการคุ้มครองข้อมูลส่วนบุคคล (PDPA / Public Safety) หรือไม่? | K6: IP and Licensing: ทรัพย์สินทางปัญญา ซอฟต์แวร์ไลบรารี และสิทธิบัตรที่นำมาใช้ มีความเปิดกว้างและปลอดภาระผูกพันทางการค้าหรือการละเมิดลิขสิทธิ์ (Licensing Freedom) มากน้อยเพียงใด? | L6: User — Implementation (Field Deployment / Setup Friction): ขั้นตอนการติดตั้ง ติดตั้งเครื่องมือ ปรับเทียบศูนย์ (Calibration) และเตรียมพร้อมใช้งานหน้างานจริงโดยผู้ปฏิบัติงาน มีความยุ่งยากหรือกินเวลาเพียงใด? | M6: User — Customer / Public Safety & Failsafes: ความปลอดภัยเชิงกลและไฟฟ้าต่อเจ้าหน้าที่ผู้ปฏิบัติงานและประชาชนในพื้นที่ (Intrinsic Safety & Failsafes) มีระบบป้องกันในระดับใด? | N6: User — Behavior & Workflow Disruption: ระบบสร้างความเปลี่ยนแปลงหรือรบกวนต่อขั้นตอนการทำงานปกติ (Standard Operating Procedure - SOP) ของผู้ใช้งานเดิมมากน้อยเพียงใด? | O6: Developer — Task Dependency (Critical Path Architecture): โครงสร้างสถาปัตยกรรมของระบบและการแบ่งส่วนงานระหว่างฮาร์ดแวร์ ซอฟต์แวร์ และกลไก มีการแยกส่วน (Decoupling) เพื่อให้พัฒนาคู่ขนานได้มากน้อยเพียงใด? | P6: Developer — Contribution Dependency (Bureaucratic & Lab Gatekeeping): การเข้าถึงเครื่องมือในห้องปฏิบัติการ การอนุมัติงบประมาณ และกระบวนการทางธุรการ (Lab Access & Purchasing Bureaucracy) มีอุปสรรคขัดขวางความคล่องตัวเพียงใด? | Q6: Developer — Task & Skill Compatibility: ความเข้ากันได้ระหว่างทักษะเดิมของทีมกับเทคโนโลยีสแตกของระบบ (Task & Skill Compatibility: 'Water and Oil' vs. 'Oil and Engine') อยู่ในระดับใด? | R6: Production Time (Engineering Design Maturity by Milestone): ความพร้อมของแบบวิศวกรรม (3D CAD, Schematics, PCB Gerbers, Firmware Architecture, BOM) อยู่ในระดับความสมบูรณ์ใดเทียบกับหมุดหมายการผลิตจริง? | S6: Shipping (Component Procurement Lead Time): ระยะเวลาในการจัดหาและขนส่งชิ้นส่วน อุปกรณ์ และเซนเซอร์ (Procurement Lead Time) อยู่ในกรอบเวลาที่ปลอดภัยต่อกำหนดส่งมอบงานหรือไม่? | T6: Real Public Impact vs. Academic Greenwashing (SDG 11.5 / 13.1): Is this genuinely reducing flood/heat losses for the public, or is it just fluff for a presentation slide? | U6: Environmental Footprint & E-Waste ("Do No Harm" — SDG 6.3 / 12.4): Will this hardware end up as toxic e-waste rotting at the bottom of a canal or washing down the river? | V6: Decision Transparency & Public Fairness (SDG 10.2 / 16.6): Can an officer or citizen verify why the system made its call, or is it an unaccountable black box? | W6: ประเมินคำถามทั้งสิ้น 21 ข้อ
A7: เหตุผลในการถาม & โหมดความล้มเหลวที่เฝ้าระวัง (Rationale) | B7: วัดภาระงานสร้างและการวิจัยพัฒนา (Build vs. Buy Burden) ยิ่งสร้างเองจากศูนย์มาก ยิ่งเสี่ยงต่อความล่าช้าและความล้มเหลว | C7: ตรวจสอบอุปสรรคด้านสิทธิ์การเข้าถึง (Access Barriers) เช่น NDA, Closed-source blobs, หรือข้อจำกัดด้านใบอนุญาตที่ขัดขวางการแก้บั๊ก | D7: ตรวจสอบความเสี่ยงด้านห่วงโซ่อุปทาน (Single-source, EOL, Overseas backlog) ที่อาจทำให้โครงการหยุดชะงักเมื่อชิ้นส่วนขาดตลาด | E7: ประเมินความเสถียรของเทคโนโลยีตามมาตรฐาน TRL จากระดับแล็บทดลอง (Lab model) ไปจนถึงระดับใช้งานจริงในสภาวะวิกฤต (Field-proven) | F7: ป้องกัน Single Point of Failure (SPOF) ด้านบุคคล หากมีสมาชิกคนใดคนหนึ่งไม่สามารถปฏิบัติงานได้ ระบบต้องยังสามารถพัฒนาและแก้ไขต่อได้ | G7: วัดความคุ้มค่าทางเศรษฐศาสตร์และการคืนทุนจากการลดความสูญเสีย ค่าแรง หรือค่าเชื้อเพลิง | H7: ตรวจสอบภาระค่าใช้จ่ายแฝงระยะยาว (Recurring Cloud/Licensing Fees) และการพึ่งพาผู้ผลิตรายเดียว | I7: ตรวจสอบงบสำรองสำหรับชิ้นส่วนเสียหาย (Scrap Budget Rule) ป้องกันงานสะดุดเมื่อเกิดชิปไหม้หรือฮาร์ดแวร์หัก | J7: ตรวจสอบความเสี่ยงทางกฎหมายสาธารณะ (พ.ร.บ. จราจร, PDPA, กฎหมายสิ่งแวดล้อม และระเบียบทางหลวง) | K7: ตรวจสอบข้อจำกัดด้านสิทธิ์ซอฟต์แวร์และฮาร์ดแวร์ ป้องกันการติดไวรัสไลเซนส์ (Copyleft GPLv3) หรือการละเมิดสิทธิบัตร | L7: ประเมินความสะดวกในการติดตั้งหน้างาน (Setup Friction) เพื่อป้องกันไม่ให้อุปกรณ์ถูกละเลยเนื่องจากการตั้งค่ายุ่งยาก | M7: ประเมินมาตรการความปลอดภัยและกลไกป้องกันอันตราย (Hazard Failsafes) เช่น สวิตช์ฉุกเฉิน E-stop, ฟิวส์, และการออกแบบป้องกันแรงดันสูง | N7: ประเมินแรงต้านทานจากผู้ใช้งาน (Workflow Friction) และความราบรื่นในการเชื่อมต่อเข้ากับระบบการทำงานเดิมของเจ้าหน้าที่ | O7: ตรวจสอบคอขวดบนสายงานวิกฤต (Critical Path Bottleneck) ป้องกันไม่ให้ทีมซอฟต์แวร์ต้องหยุดรอแผ่นวงจรพิมพ์หรือกลไกที่ยังไม่เสร็จ | P7: ประเมินอุปสรรคด้านการบริหารและเครื่องมือ (Institutional Gatekeeping) เช่น คิวรอเครื่องจักร การล็อกแล็บ หรือขั้นตอนเบิกจ่ายงบประมาณที่ล่าช้า | Q7: ตรวจสอบความสอดคล้องระหว่างทักษะที่ทีมมีอยู่จริงกับเทคโนโลยีที่เลือกใช้ เพื่อป้องกัน Learning Curve ที่สูงเกินไปจนงานล้มเหลว | R7: ประเมินความพร้อมของพิมพ์เขียวการผลิต (Design Maturity Package) ก่อนเริ่มสั่งผลิตจริง เพื่อป้องกันการรื้อแก้แบบกลางคัน | S7: ตรวจสอบห่วงโซ่อุปทาน (Supply Chain Lead Time) ชิ้นส่วนที่ต้องรอส่งจากต่างประเทศเกิน 3 สัปดาห์ถือเป็นความเสี่ยงต่อวิกฤตสัปดาห์สอบและกำหนดส่งมอบ | T7: Your team's 1 vs. 5 premise: "Pure buzzword bullshit to get a grade vs. Actually moves the needle on city infrastructure." | U7: Your team's 1 vs. 5 premise: "Dumping toxic e-waste into public canals vs. Zero-footprint hardware." | V7: Your team's 1 vs. 5 premise: "Black-box algorithm cutting services to poor areas vs. Open, verifiable math." | W7: สังเคราะห์จาก AI Agents Group 2
A8: เกณฑ์การให้คะแนน (Scoring Rubric Definition: ระดับ 1, 2, 3, 4, 5 ครบทุกระดับ) | B8: 1 — Build from Scratch: 100% custom R&D required (custom mechanism, custom PCB, raw algorithm derivation); no reference designs available. 2 — Heavy Customization: Core components exist, but requires extensive custom adaptation, structural machining, and custom wrapper code. 3 — Hybrid / COTS Integration: Standard COTS modules (e.g., standard dev board + breakout sensors) assembled with custom brackets and intermediate wiring. 4 — Modular COTS Assembly: Pre-engineered building blocks with standard mounting and standard communication buses (e.g., Din-rail modules, I2C/CAN shields); minimal custom fabrication. 5 — Commercial Off-the-Shelf (COTS): Buy and use directly out of the box (Plug-and-Play); zero mechanical or electrical fabrication required. | C8: 1 — Strictly Restricted: Proprietary stack under NDA, blocked enterprise firewalls, or unavailable developer licenses. 2 — Limited Access: Closed binary blobs or third-party proprietary software; black-box firmware with zero internal telemetry or source code. 3 — Request-Based Access: Standard educational/evaluation license or public APIs with strict rate limits; requires account verification or approval delays. 4 — Open Developer Access: Free public SDKs, full documentation, and open developer access, but cannot modify upstream core source code. 5 — Unrestricted Full-Stack Access: Fully open source (permissive license) and open hardware; team has root/admin rights to modify, inspect, and deploy as both user and developer. | D8: 1 — Sole-Source / Obsolete: Single overseas supplier, restricted export control, long backorder, or risk of end-of-life (EOL). 2 — Specialized Vendor: Only 1–2 niche industrial suppliers; requires formal corporate quote/PO process; no consumer retail channels. 3 — Moderate Availability: 2–3 regional distributors (e.g., DigiKey, Mouser, Element14); reliable stock but requires overseas shipping. 4 — Multi-Vendor Local Stock: Readily available from multiple domestic vendors; common industrial or maker components with reliable inventory. 5 — Commodity / Off-the-Shelf: Ubiquitous commodity item sold across multiple local electronics shops and online platforms (delivered in 1–2 days). | E8: 1 — Proof of Concept (TRL 3): Bench breadboard or mathematical model; verified only in simulated/controlled lab conditions. 2 — Functional Breadboard (TRL 4): Integrated components working together in lab; messy wiring, fragile, uncalibrated for harsh environments. 3 — Alpha Prototype (TRL 5–6): Enclosed prototype tested in a relevant simulated environment; occasional crashes, requires human supervisor. 4 — Beta / Field-Proven (TRL 7): Pre-production hardware operating reliably in the actual operating environment under real stress. 5 — Commercial Product (TRL 8–9): Fully certified, production-grade commercial product with documented MTBF and mass field reliability. | F8: 1 — Single Point of Failure (SPOF): Only 1 person has the niche skill (if they get sick, the subsystem halts 100%). 2 — Solo Lead with Minimal Backup: 1 person executes; 1 teammate understands basic concepts but cannot debug code or fix hardware alone. 3 — Primary + Secondary Pair: 1 primary developer and 1 competent secondary backup who can maintain, troubleshoot, and push updates. 4 — Broad Competence: 3+ teammates can actively design, assemble, and debug the subsystem with low ramp-up time. 5 — Full Team Redundancy: All team members are fully proficient; tasks can be swapped across anyone with zero friction or velocity loss. | G8: 1 — Long Payback ($\ge 10\text{ Years}$): High initial CapEx and low recurring savings; economically non-viable for rapid deployment. 2 — Slow Return ($6–9\text{ Years}$): Substantial capital investment with long break-even horizon; requires long-term institutional subsidization. 3 — Moderate Return ($3–5\text{ Years}$): Reasonable public infrastructure payback; offsets costs across multi-year operational cycles. 4 — Fast Return ($2–3\text{ Years}$): Strong operational cost reduction (fuel, labor, scrap); breaks even within normal equipment lifecycle. 5 — Immediate Payback ($\le 1–2\text{ Years}$): Rapid break-even; eliminates major recurring losses within the first operating season. | H8: 1 — Total Vendor Lock-in: Proprietary cloud backend, encrypted telemetry, and proprietary connectors; completely dependent on vendor survival. 2 — High Dependency: Hardware requires vendor-licensed diagnostic tools or annual subscription fees to maintain operation. 3 — Semi-Independent: Core hardware relies on proprietary firmware, but allows open API export and standard electrical interfaces. 4 — High Autonomy: Uses standard open communication protocols (e.g., Modbus, MQTT, CAN); parts can be serviced using generic tools. 5 — Complete Independence: 100% open architecture; hardware is interchangeable with generic substitutes; self-serviceable by any engineer. | I8: 1 — Zero Buffer (0%): Exactly 1x BOM purchased; any fried chip, cracked bracket, or wiring mistake kills the project. 2 — Fragile Buffer (20–30%): Spares only for passive components (resistors, connectors); no backup microcontrollers or expensive sensors. 3 — Moderate Buffer (50%): Spares for all critical passive parts and 1 spare for the primary controller board. 4 — High Buffer (80%): Spares for nearly every active component and sensor; can sustain multiple prototype burn-ins. 5 — Full Redundancy ($\ge 100\%$): Complete 2x BOM budget on hand; can build two complete working units simultaneously. | J8: 1 — Severe Violation / No Privilege: Direct breach of statutory law (e.g., unconsented public surveillance/PDPA, hazardous road blockage, RF jammer). 2 — High Legal Exposure: Ambiguous legal zone; high risk of civic complaints or traffic disruption; requires complex technical waivers. 3 — Conditional / Requires Permit: Allowed under explicit written approval, official agency MoU, or municipal permit (e.g., BMA/Highway dept permit). 4 — Low Legal Friction: Operates within standard public engineering exemptions; simple standard notification/safety compliance needed. 5 — 100% Compliant / Free Domain: Completely exempt from statutory licensing; zero public safety risk, zero personal data (Zero PII), fully unrestricted. | K8: 1 — Closed / Commercial Barrier: Proprietary commercial license; cannot compile, flash, or operate without paying expensive commercial seat licenses. 2 — Ambiguous / Gray IP: Unclear licensing terms or unlicensed GitHub repos; risk of copyright strike or IP dispute upon public demonstration. 3 — Restrictive Open Source (Copyleft): Permitted for educational use, but viral licenses (e.g., GPLv3) force your entire codebase to be made public if distributed. 4 — Permissive Open Source: Open source with minimal conditions (e.g., LGPL, CC-BY); allows proprietary wrapping with simple attribution. 5 — Completely Permissive / Public Domain: Permissive open source (MIT, Apache 2.0, BSD) or Public Domain; unrestricted freedom to commercialize, modify, and contribute. | L8: 1 — Laborious Recalibration: Requires multi-point manual physical zeroing, chemical calibration, or oscilloscope tuning before every run. 2 — Complex Setup: Requires trained technician 20–30 minutes to adjust potentiometers, align brackets, or enter configuration commands. 3 — Moderate Field Setup: Simple 5-minute calibration procedure (e.g., tare button or basic mobile app zeroing) performed by non-engineers. 4 — Minimal Setup: Fast clamp-on mounting with automated self-calibration on power-up; ready in $< 1\text{ minute}$. 5 — True Plug and Go: Pure plug-and-play; zero calibration required, zero buttons; power on and immediately operational. | M8: 1 — Critical Hazard: Failure can directly cause electrocution, fire, traffic crashes, chemical exposure, or confined-space asphyxiation. 2 — High Risk / Manual Oversight: High mechanical/electrical hazard requiring constant operator vigilance and full PPE. 3 — Moderate Safety: Protected by passive mechanical guards, fuses, and warning labels; requires basic safety precautions. 4 — High Safety & Interlocks: Active software limits, hardware thermal shutoffs, and reverse polarity protection; minimal hazard on failure. 5 — Inherently Safe & Redundant: Failsafe by physics (cannot store lethal energy); isolated, dual-rated enclosures, redundant E-stops, zero injury risk. | N8: 1 — Disruptive Overhaul: Forces operators to abandon existing SOPs, adds 5+ extra tedious forms/steps, and faces fierce institutional union/worker resistance. 2 — Significant Friction: Adds notable extra documentation or redundant verification steps; operators will actively look for ways to bypass it. 3 — Moderate Adaptation: Modifies daily routine slightly; requires 1–2 training workshops, but delivers clear convenience trade-offs. 4 — Low Friction: Integrates into existing tools (e.g., sends automated alerts to existing LINE/Telegram or ticketing dashboard); minimal change in habits. 5 — Transparent / Seamless Integration: Zero workflow disruption; runs invisibly in background and automates existing manual paperwork without operator intervention. | O8: 1 — Strictly Sequential (Linear): A depends on B depends on C; if the PCB fab is delayed, software and testing halt 100%. 2 — Bottlenecked Pipelines: Major subsystems are tightly coupled; frequent integration stalls waiting for hardware bench access. 3 — Semi-Decoupled: Hardware and software teams can work independently for 1–2 weeks using rough mockups before needing physical integration. 4 — Modular Parallelism: Clear API/interface boundaries; software builds against mock data/simulators while hardware is routed; integration takes $< 2\text{ days}$. 5 — Fully Parallel Architecture: Microservices/modular nodes with standard contracts; mechanical, electrical, and firmware develop, simulate, and unit-test completely in parallel. | P8: 1 — Heavy Gatekeeping: Blocked by supervisor approvals, locked lab cabinets, NDA signatures, purchasing bureaucracy, and restricted git branches. 2 — Moderate Bureaucracy: Requires departmental request forms, tool booking queues, and waiting 3–5 days for administrative sign-offs. 3 — Standard Campus Access: Workable access during university open hours; minor approval delays for equipment or lab keys. 4 — High Autonomy: Team has full repository write access, open 24/7 lab entry, and pre-approved discretionary debit cards/stipends for rapid purchases. 5 — Frictionless Contribution: Complete autonomy; decentralized cloud CI/CD, local prototyping tools at home/bench, zero administrative blockers. | Q8: 1 — Complete Mismatch ("Water and Oil"): Team has zero foundation in the stack (e.g., pure mechanical students forced to train deep neural nets in C++ from scratch). 2 — Steep Learning Curve: High theoretical knowledge, but zero production hands-on experience; debugging basic syntax/wiring stalls progress. 3 — Adjacent Competence: Strong mastery in related tools (e.g., proficient in Arduino/ESP32 migrating to STM32, or SolidWorks migrating to Fusion360); manageable 1-week curve. 4 — Proven Experience: Team has built similar subsystems in past semester coursework or competition robots; rapid ramp-up. 5 — Perfect Synergy ("Oil and Engine"): Complete domain mastery; team members have built this exact architecture multiple times with verified libraries and muscle memory. | R8: 1 — Concept Only (0% Design): Napkin sketches and verbal concepts; 0% CAD models, 0% schematics, 0% code written. 2 — Rough Drafts (25% Design): Preliminary block diagrams, hand-drawn schematics, unverified parts list, incomplete 3D bounding boxes. 3 — Intermediate Maturity (50% Design): Complete CAD assembly (untested clearances), schematic capture complete, draft firmware architecture mapped out. 4 — Pre-Production (80% Design): Fully detailed 3D CAD ready for 3D print/CNC, routed PCB Gerber files validated with DRC, pinouts locked down. 5 — Fully Engineered Design (100% Production Ready): Complete drawing package: BOM with part numbers, verified manufacturing Gerbers, 2D tolerance drawings, assembly SOP, and flashing scripts ready. | S8: 1 — Extreme Lead Time ($\ge 4\text{ Weeks}$): Custom overseas fabrication, customs clearance delays, or parts with long factory lead times (critical path hazard). 2 — High Lead Time ($3–4\text{ Weeks}$): Standard overseas shipping (e.g., standard AliExpress/international postal surface mail); vulnerable to logistics delays. 3 — Moderate Lead Time ($2\text{ Weeks}$): Express international courier (DHL, FedEx, JLCPCB express) or regional distributors (7–14 days). 4 — Short Lead Time ($1\text{ Week}$): Domestic couriers or express domestic stockists (3–5 business days). 5 — Immediate / Next-Day ($\le 1–2\text{ Days}$): Shelf stock available locally at retail shops or next-day domestic express delivery. | T8: 1 — Pure Buzzword / Academic Greenwashing: Claims to "save the city," but has zero real data, zero measurable effect, and solves a problem nobody in the municipality actually experiences. 2 — Superficial Correlation: Indirect impact; functions only as an isolated school demo with no realistic way to measure if it prevented damage or saved money. 3 — Localized Proof: Delivers a measurable, verified benefit (e.g., cuts response time by 10 minutes or drops pavement temp on a single test strip), but lacks a model to scale. 4 — District-Level Viability: Clear pathway to protect municipal infrastructure or reduce public losses across multiple roads/alleys during extreme weather. 5 — Systemic City Resilience: Backed by concrete empirical data showing significant reduction in public economic losses, vehicle damage, or human hazard during severe rain or heat. | U8: 1 — Toxic Canal Hazard: Cheap plastic enclosure cracks under UV, or unsealed LiPo batteries leak toxic chemicals and detach into the drainage network as marine litter. 2 — Fragile Disposable Tech: Short operational lifespan; sensors foul or corrode within 2–3 weeks and are left behind by crews because retrieving them is too annoying. 3 — Standard Field Footprint: Requires periodic battery replacement and creates standard electronic scrap, but utilizes basic tethering to prevent total hardware loss. 4 — Low-Impact Enclosure: Solar-trickle or long-life low-power architecture; uses recyclable casing and redundant physical tethers (e.g., dual stainless lanyards). 5 — Fully Circular & Zero Footprint: 100% fail-safe retrieval design; uses non-toxic, non-leaching materials, consumes minimal public water/energy, and leaves zero trace in the city. | V8: 1 — Opaque Black Box: Proprietary or unexplained threshold that cancels dispatch trucks or alters services with zero explanation, risking quiet abandonment of vulnerable neighborhoods. 2 — Ambiguous Logic: Decision rules are buried in messy heuristic code; field operators cannot explain to a citizen why an alert was triggered or suppressed. 3 — Documented Internal Rules: Logic is documented on paper for engineers, but has no public audit trail or clear appeal mechanism if the sensor misreads. 4 — Open Empirical Standards: Decisions are driven by transparent physical equations (e.g., verified dh/dt thresholds) applied equally across all city zones. 5 — 100% Auditable & Equitable: Full tamper-evident digital audit trail; open logic accessible to city officials and citizens, guaranteeing equal public protection regardless of district wealth. | W8: เกณฑ์รวม: >=80 ผ่านสูง, >=60 มีเงื่อนไข, <60 เสี่ยงสูง | หากมีข้อใดได้ 1 = VETOED ตกเกณฑ์ทันที
A9: คะแนนที่ได้รับ (ASSIGNED SCORE: 1, 2, 3, 4, 5 STRICT INTEGER) | B9: 4 | C9: 5 | D9: 5 | E9: 4 | F9: 4 | G9: 5 | H9: 4 | I9: 5 | J9: 5 | K9: 5 | L9: 5 | M9: 5 | N9: 4 | O9: 4 | P9: 5 | Q9: 5 | R9: 4 | S9: 5 | T9: 5 | U9: 5 | V9: 5 | W9: =IF(W10>0, (W11/W10)*20, 0) -> 93.433343
A10: ค่าน้ำหนัก (Weight %) | B10: 0.04 | C10: 0.04 | D10: 0.04 | E10: 0.04 | F10: 0.04 | G10: 0.0667 | H10: 0.0667 | I10: 0.0666 | J10: 0.075 | K10: 0.075 | L10: 0.0333 | M10: 0.0333 | N10: 0.0333 | O10: 0.0333 | P10: 0.0333 | Q10: 0.0334 | R10: 0.075 | S10: 0.075 | T10: 0.0333 | U10: 0.0333 | V10: 0.0334 | W10: =SUM(B10:V10) -> 0.9999
A11: คะแนนถ่วงน้ำหนัก (=Score * Weight) | B11: =B9*B10 -> 0.16 | C11: =C9*C10 -> 0.2 | D11: =D9*D10 -> 0.2 | E11: =E9*E10 -> 0.16 | F11: =F9*F10 -> 0.16 | G11: =G9*G10 -> 0.3335 | H11: =H9*H10 -> 0.2668 | I11: =I9*I10 -> 0.333 | ... V11: =V9*V10 -> 0.167 | W11: =SUM(B11:V11) -> 4.6712
A12: คำอธิบาย & หลักฐานอ้างอิงจากไฟล์ Intake (Evidence Citation) | B12: อ้างอิง solution-1.md หน้า 2: ประกอบจากโมดูลสำเร็จรูปมาตรฐาน (ESP32 + เซนเซอร์อัลตราโซนิกกันน้ำ JSN-SR04T) เข้ากับ Screw Terminal Shield และแคลมป์ยึดท่อสำเร็จรูป (Modular COTS Assembly) | C12: สแตกเทคโนโลยีพัฒนาบนโอเพนซอร์สทั้งหมด (Arduino IDE, ESP-IDF, FreeRTOS, MicroPython) ไม่ติด NDA หรือสิทธิ์ซอฟต์แวร์ ทีมงานมีสิทธิ์ระดับ Root/Admin 100% (Unrestricted Full-Stack Access) | D12: ชิ้นส่วนหลัก (ESP32, JSN-SR04T, กล่อง IP67, แคลมป์สแตนเลส) เป็นอุปกรณ์พื้นฐาน มีจำหน่ายในร้านค้าอิเล็กทรอนิกส์ในไทยและแพลตฟอร์มออนไลน์หลายร้าน จัดส่งได้ใน 1-2 วัน (Commodity / Off-the-Shelf) | E12: อ้างอิงงานวิจัยภาคสนาม Ann Arbor (TRL 7): สถาปัตยกรรมผ่านการทดสอบใช้งานจริงในระบบระบายน้ำเมืองมาแล้ว ทีมนำมาสร้างตัวต้นแบบระดับ Field-proven Prototype | F12: อ้างอิง team-skills: สมาชิก 3 คนมีความเชี่ยวชาญเชื่อมโยงกัน (JK เชี่ยวชาญ Control/Derivative, Due เชี่ยวชาญ ESP32/Embedded, Fifa เชี่ยวชาญ CAD/กลไก) สามารถสลับงานซ่อมบำรุงและดีบั๊กได้ (Broad Competence) | G12: ลดการส่งรถ QRT วิ่งเปล่า (Empty Cases) ได้ 40-50% ประหยัดค่าน้ำมันและค่าแรงเจ้าหน้าที่ คืนทุนได้ทันทีในฤดูฝนแรก (< 1-2 ปี) | H12: ใช้มาตรฐานการสื่อสารเปิด (MQTT/HTTP REST API) ซ่อมบำรุงและเปลี่ยนอะไหล่ได้เองโดยวิศวกรทั่วไป ปลอดภาระผูกขาดจากผู้ผลิต (High Autonomy) | I12: ต้นทุนรายการวัสดุ (BOM) ไม่เกิน 1,500 บาท มีงบประมาณเพียงพอจัดซื้อชุดอุปกรณ์สำรองได้มากกว่า 100% (Full Redundancy) | J12: ติดตั้งเหนือผิวน้ำในท่อระบายน้ำสาธารณะ ไม่ล่วงล้ำผิวจราจร ไม่ใช้กล้องถ่ายภาพ ไม่มีการเก็บข้อมูลส่วนบุคคล (Zero PII 100%) ถูกต้องตาม พ.ร.บ. คุ้มครองข้อมูลส่วนบุคคลและระเบียบ กทม. | K12: ซอฟต์แวร์พัฒนาขึ้นเองโดยใช้ไลบรารีสัญญาอนุญาต MIT/Apache 2.0 ไม่มีข้อจำกัดทางการค้าหรือการเผยแพร่โค้ด | L12: ออกแบบเป็นระบบ Plug-and-play ยึดด้วยแคลมป์สำเร็จรูป พร้อมระบบ Calibrate ศูนย์อัตโนมัติเมื่อเปิดเครื่อง (True Plug and Go) | M12: ระบบใช้ไฟกระแสตรงแรงดันต่ำ 5V DC ปลอดภัยตามธรรมชาติทางฟิสิกส์ (Inherently Safe) ไม่มีประกายไฟหรือความร้อนสะสม | N12: ผลการคำนวณ dh/dt ส่งออกเป็น Digital Evidence Card ผ่าน Webhook ตรงเข้า Traffy Fondue และระบบแจ้งเตือนเดิมของ กทม. โดยเจ้าหน้าที่ไม่ต้องกรอกฟอร์มเพิ่ม | O12: แยก API และโครงสร้างข้อมูลระหว่างเฟิร์มแวร์ ESP32 กับอัลกอริทึมคำนวณ dh/dt บน Python ชัดเจน สามารถใช้ข้อมูลจำลองระดับน้ำทดสอบโค้ดขนานไปกับการเดินสายฮาร์ดแวร์ได้ | P12: พัฒนาบนเครื่องคอมพิวเตอร์ส่วนตัวและโต๊ะช่างที่บ้านได้โดยสมบูรณ์ ไม่มีการติดกุญแจห้องแล็บหรือขั้นตอนขออนุมัติจัดซื้อซับซ้อน | Q12: สอดคล้องกับทักษะของทีมอย่างสมบูรณ์แบบ: JK ชำนาญ Dynamic Systems & Control, Due ชำนาญ ESP32 & PCB, Fifa ชำนาญ CAD/กลไก ('Oil and Engine') | R12: แบบจำลอง 3D CAD ของกล่องและแคลมป์ยึดเสร็จสมบูรณ์ วงจรเชื่อมต่อผ่าน Screw Terminal Shield มี DRC ผ่านเกณฑ์ พร้อมเข้าสู่ Pre-production ในสัปดาห์ที่ 9 | S12: ชิ้นส่วนหลักทั้งหมด (ESP32, Ultrasonic Sensor, IP67 Enclosure) มีสต็อกจำหน่ายในประเทศ จัดส่งด่วนถึงภายใน 1-2 วันทำการ | T12: อ้างอิง solution-1.md Requirements a: ตัด False Alarm และ Empty Cases ได้ 40-50% มีตัวชี้วัดจริงในการลดความเสียหายของรถยนต์และพื้นที่เศรษฐกิจ (SDG 11.5/13.1) ผ่านเกณฑ์ระดับ 5 Systemic City Resilience | U12: ฮาร์ดแวร์ติดตั้งเหนือระดับน้ำ ไม่จมแช่ในคลอง ตัวกล่อง IP67 ยึดด้วย Stainless Clamp แน่นหนา มีสายสลิงคล้องนิรภัย (Dual Stainless Lanyards) ป้องกันหลุดร่วงเป็นขยะคลอง แบตเตอรี่และวงจรผ่านมาตรฐาน RoHS ผ่านเกณฑ์ระดับ 5 (Zero Footprint / Non-Leaching) | V12: การตัดสินใจใช้สมการอนุพันธ์ dh/dt ที่โปร่งใส มี Digital Evidence Card แนบส่งตรงเข้า Traffy Fondue บันทึกเวลาและอัตราน้ำลดชัดเจน เจ้าหน้าที่และประชาชนตรวจสอบได้ ไร้ Black-box หรือการละเลยชุมชนเปราะบาง ผ่านเกณฑ์ระดับ 5 (100% Auditable & Equitable) | W12: =IF(MIN(B9:V9)=1, "VETOED / ตกเกณฑ์ข้อบังคับวิกฤต (คะแนนระดับ 1)", IF(W9>=80, "ผ่านเกณฑ์ระดับสูง (HIGHLY VIABLE)", IF(W9>=60, "ผ่านแบบมีเงื่อนไข (CONDITIONALLY VIABLE)", "ความเสี่ยงสูง (HIGH RISK)"))) -> ผ่านเกณฑ์ระดับสูง (HIGHLY VIABLE)
A13: แผนลดขอบเขตงาน & มาตรการลดความเสี่ยง (De-scoping Action) | B13: ใช้กล่องพักสายไฟมาตรฐาน IP67 พร้อมแคลมป์รัดท่อสำเร็จรูป | C13: ใช้เฟิร์มแวร์โอเพนซอร์สมาตรฐาน ESP-IDF และ FreeRTOS | D13: จัดซื้อชิ้นส่วนอิเล็กทรอนิกส์จากร้านค้าสต็อกในประเทศ | E13: ทดสอบฟังก์ชันกรองสัญญาณในถังน้ำจำลองเพื่อยืนยัน TRL 6 ก่อนติดตั้งจริง | F13: จัดทำคู่มือ Pinout และ Interface Contract ให้เพื่อนในทีมร่วมดีบั๊กได้ | G13: ใช้ ESP32 รุ่นมาตรฐานและเซนเซอร์ COTS เพื่อควบคุมต้นทุนไม่ให้เกิน 3,500 บาท | H13: ใช้โปรโตคอล MQTT มาตรฐานเชื่อมต่อกับเซิร์ฟเวอร์เปิด | I13: จัดซื้อบอร์ด ESP32 และเซนเซอร์สำรองอย่างละ 2 ชุดเป็นอะไหล่สำรองในงบ | J13: ติดตั้งป้ายชื่อโครงการวิศวกรรมและหน่วยงานรับผิดชอบบนกล่องอุปกรณ์ | K13: ตรวจสอบลิขสิทธิ์ของไลบรารีทั้งหมดให้เป็น MIT/Apache 2.0 | L13: ออกแบบปุ่มสวิตช์เปิดเครื่องพร้อมไฟ LED แสดงสถานะการ Calibrate สำเร็จ | M13: ติดตั้งฟิวส์ตัดวงจรและไดโอดป้องกันไฟย้อนกลับในวงจรจ่ายไฟ | N13: เชื่อมต่อระบบส่งข้อมูลเข้า LINE Notify หรือ Telegram กลุ่มเจ้าหน้าที่โดยตรง | O13: ทำ Mock Data จำลองค่าระดับน้ำส่งเข้าโมดูล Python สำหรับพัฒนาอัลกอริทึม | P13: จัดเตรียมบอร์ดทดลองส่วนตัวให้สมาชิกแต่ละคนทำงานจากที่พักได้ | Q13: แบ่งงานตามความถนัดเดิมของสมาชิกเพื่อรักษาความเร็วในการพัฒนาสูงสุด | R13: ล็อกสเปกฮาร์ดแวร์และเซนเซอร์ก่อนสัปดาห์ที่ 7 เพื่อทดสอบระบบรวม | S13: สั่งซื้อชิ้นส่วนจากร้านค้าในไทยล่วงหน้า 2 สัปดาห์ก่อนกำหนดประกอบ | T13: เก็บสถิติอัตราการลดเที่ยวรถเปล่าเพื่อรายงานผลสัมฤทธิ์เมือง | U13: ใช้สายสลิงสแตนเลสคู่คล้องยึดตัวเครื่องกับคานท่อ | V13: แสดงสูตรคำนวณ dh/dt บนการ์ดแจ้งเตือน Traffy Fondue | W13: ปฏิบัติตามแผนลดขอบเขตงาน (De-scoping Advisory)
A15: ตารางสรุปคะแนนแยกตามมิติ TELOS+S (Pillar Score Breakdown)
A16: มิติการประเมิน (TELOS+S Pillar) | B16: สัดส่วนน้ำหนัก (Weight %) | C16: คะแนนเต็มมิติ (Max Points) | D16: คะแนนที่ได้รับจริง (Earned Points) | E16: คะแนนเฉลี่ย (Score 1-5) | F16: ระดับความพร้อม (Readiness Level)
A17: T : ด้านเทคโนโลยีและวิศวกรรม (Technical) | B17: 0.2 | C17: 20 | D17: =SUM(B11:F11)*20 -> 17.6 | E17: =IF(C17>0, (D17/C17)*5, 0) -> 4.4 | F17: =IF(D17>=16, "พร้อมระดับสูง (High)", IF(D17>=12, "ปานกลาง (Medium)", "เสี่ยงวิกฤต (Critical)")) -> พร้อมระดับสูง (High)
A18: E : ด้านเศรษฐศาสตร์และความคุ้มค่า (Economic) | B18: 0.2 | C18: 20 | D18: =SUM(G11:I11)*20 -> 18.666 | E18: =IF(C18>0, (D18/C18)*5, 0) -> 4.6665 | F18: =IF(D18>=16, "พร้อมระดับสูง (High)", IF(D18>=12, "ปานกลาง (Medium)", "เสี่ยงวิกฤต (Critical)")) -> พร้อมระดับสูง (High)
A19: L : ด้านกฎหมาย ระเบียบ และภาคประชาชน (Legal & Outreach) | B19: 0.15 | C19: 15 | D19: =SUM(J11:K11)*20 -> 15 | E19: =IF(C19>0, (D19/C19)*5, 0) -> 5 | F19: =IF(D19>=12, "พร้อมระดับสูง (High)", IF(D19>=9, "ปานกลาง (Medium)", "เสี่ยงวิกฤต (Critical)")) -> พร้อมระดับสูง (High)
A20: O : ด้านการปฏิบัติการและหน้างาน (Operational) | B20: 0.2 | C20: 20 | D20: =SUM(L11:Q11)*20 -> 18.658 | E20: =IF(C20>0, (D20/C20)*5, 0) -> 4.6645 | F20: =IF(D20>=16, "พร้อมระดับสูง (High)", IF(D20>=12, "ปานกลาง (Medium)", "เสี่ยงวิกฤต (Critical)")) -> พร้อมระดับสูง (High)
A21: S : ด้านแผนงานและเวลาส่งมอบ (Schedule) | B21: 0.15 | C21: 15 | D21: =SUM(R11:S11)*20 -> 13.5 | E21: =IF(C21>0, (D21/C21)*5, 0) -> 4.5 | F21: =IF(D21>=12, "พร้อมระดับสูง (High)", IF(D21>=9, "ปานกลาง (Medium)", "เสี่ยงวิกฤต (Critical)")) -> พร้อมระดับสูง (High)
A22: +S : ด้านความยั่งยืนและสิ่งแวดล้อม (Sustainability / SDG) | B22: 0.1 | C22: 10 | D22: =SUM(T11:V11)*20 -> 10 | E22: =IF(C22>0, (D22/C22)*5, 0) -> 5 | F22: =IF(D22>=8, "พร้อมระดับสูง (High)", IF(D22>=6, "ปานกลาง (Medium)", "เสี่ยงวิกฤต (Critical)")) -> พร้อมระดับสูง (High)
A23: คะแนนรวมทุกมิติ (Total Feasibility Score) | B23: =SUM(B17:B22) -> 1 | C23: =SUM(C17:C22) -> 100 | D23: =SUM(D17:D22) -> 93.424 | E23: =IF(C23>0, (D23/C23)*5, 0) -> 4.6712 | F23: =IF(D23>=80, "ผ่านเกณฑ์ระดับสูง (HIGHLY VIABLE)", IF(D23>=60, "ผ่านแบบมีเงื่อนไข (CONDITIONALLY VIABLE)", "ความเสี่ยงสูง (HIGH RISK)")) -> ผ่านเกณฑ์ระดับสูง (HIGHLY VIABLE)
A25: เมทริกซ์ประเมินความเข้ากันได้กับองค์ความรู้ด้านวิศวกรรมหุ่นยนต์ (Robotics Knowledge Compatibility)
A26: * หมายเหตุ: การประเมินส่วนนี้วัดศักยภาพในการประยุกต์ใช้องค์ความรู้ด้านวิศวกรรมหุ่นยนต์ (Perception, Control, Actuation, Mechatronics) เต็ม 10 คะแนน | เป็นเอกเทศ ไม่นับรวมในคะแนน TELOS 100 คะแนน
A27: มิติการประเมิน (Robotics Dimension) | B27: คะแนนศักยภาพ (/10) | C27: แกน Perception & Sensing (การรับรู้) | D27: แกน Control & Algorithms (การควบคุม) | E27: แกน Actuation & Mechanisms (กลไก) | F27: บทวิเคราะห์เชิงวิศวกรรมหุ่นยนต์ (FIBO Alignment Rationale)
A28: ศักยภาพการประยุกต์ใช้องค์ความรู้หุ่นยนต์และระบบอัตโนมัติ | B28: 7.5 | C28: เซนเซอร์วัดระดับน้ำอัลตราโซนิก (Ultrasonic Transducer) พร้อมวงจรชดเชยอุณหภูมิ, ตัวกรองสัญญาณรบกวนผิวน้ำ (Wave Filter & Moving Average/Median Filter) และการแปลงค่า Time-of-Flight เป็นระยะขจัด | D28: ทฤษฎีระบบควบคุมและสมการอนุพันธ์ (Dynamic Systems & Control Theory): การคำนวณอนุพันธ์เวลาเชิงดิจิทัล (Discrete Time Derivative dh/dt), การประมาณค่าสถานะ (State Estimation), และอัลกอริทึมทำนายขอบเขตเวลา (Predictive Time Horizon) | E28: ไม่มีระบบขับเคลื่อนกลไก (Lack of Active Mechanical Actuation) มีเฉพาะโครงสร้างยึดจับเชิงกล (Stainless Mounting Bracket, Clamps) และกล่องครอบกันน้ำมาตรฐาน IP67 | F28: มีความเข้ากันได้สูงในแกนคณิตศาสตร์วิศวกรรม ทฤษฎีระบบควบคุม (Control Theory) และการประมวลผลสัญญาณ (Signal Processing & State Estimation) ของ JK แต่คะแนนอยู่ที่ 7.5 เนื่องจากขาด Physical Actuation และกลไกการเคลื่อนที่

Sheet Solution-2
A1: เมทริกซ์ประเมินความเป็นไปได้เชิงระบบ TELOS+S: PUB Singapore CWOS 2-Factor Authentication Dispatch Filter
A2: ระบบคะแนนจำนวนเต็มเด็ดขาด: 1, 2, 3, 4, 5 เท่านั้น (ไม่มีจุดทศนิยม / ไม่มี 0.5) | โครงสร้างแบบ Transposed แนวนอน
A4: รหัสคำถาม (Question Code) | B4: T-01 | C4: T-02 | D4: T-03 | E4: T-04 | F4: T-05 | G4: E-01 | H4: E-02 | I4: E-03 | J4: L-01 | K4: L-02 | L4: O-01 | M4: O-02 | N4: O-03 | O4: O-04 | P4: O-05 | Q4: O-06 | R4: S-01 | S4: S-02 | T4: SDG-01 | U4: SDG-02 | V4: SDG-03 | W4: สรุปภาพรวม (SUMMARY)
A5: มิติการประเมิน (TELOS+S Pillar) | B5: ด้านเทคโนโลยีและวิศวกรรม (Technical Feasibility) | C5: ด้านเทคโนโลยีและวิศวกรรม (Technical Feasibility) | D5: ด้านเทคโนโลยีและวิศวกรรม (Technical Feasibility) | E5: ด้านเทคโนโลยีและวิศวกรรม (Technical Feasibility) | F5: ด้านเทคโนโลยีและวิศวกรรม (Technical Feasibility) | G5: ด้านเศรษฐศาสตร์ (Economic Feasibility) | H5: ด้านเศรษฐศาสตร์ (Economic Feasibility) | I5: ด้านเศรษฐศาสตร์ (Economic Feasibility) | J5: ด้านกฎหมายและสถาบัน (Legal & Institutional Feasibility) | K5: ด้านกฎหมายและสถาบัน (Legal & Institutional Feasibility) | L5: ด้านการปฏิบัติการ (Operational Feasibility) | M5: ด้านการปฏิบัติการ (Operational Feasibility) | N5: ด้านการปฏิบัติการ (Operational Feasibility) | O5: ด้านการปฏิบัติการ (Operational Feasibility) | P5: ด้านการปฏิบัติการ (Operational Feasibility) | Q5: ด้านการปฏิบัติการ (Operational Feasibility) | R5: ด้านแผนงานและเวลา (Schedule Feasibility) | S5: ด้านแผนงานและเวลา (Schedule Feasibility) | T5: +S ด้านความยั่งยืน (Sustainable Feasibility) | U5: +S ด้านความยั่งยืน (Sustainable Feasibility) | V5: +S ด้านความยั่งยืน (Sustainable Feasibility) | W5: ผลรวมทุกมิติ (All Pillars)
A6: คำถามทดสอบความเสี่ยงจริง (Stress-Test Question) | B6: Implementation (Build vs. Buy Burden): ระบบต้องพัฒนาขึ้นเองจากศูนย์ (Custom R&D) หรือสามารถประกอบขึ้นจากโมดูลสำเร็จรูป (COTS Assembly)? | C6: Access (Tech Stack & Ecosystem Permissions): สแตกเทคโนโลยีและสิทธิ์การเข้าถึงระบบ (Permissions & Ecosystem) มีความเปิดกว้างเพียงใดในการตรวจสอบ แก้ไข และพัฒนาต่อยอด? | D6: Supply (Component Procurement & Vendor Availability): ชิ้นส่วนและอุปกรณ์หลักมีห่วงโซ่อุปทานและความพร้อมในการจัดหา (Supply & Vendor Availability) จากผู้จำหน่ายในระดับใด? | E6: Base Performance (Technology Readiness Level - TRL): ระดับความพร้อมของเทคโนโลยี (TRL) ของระบบอยู่ในขั้นใดเมื่อเทียบกับสภาวะแวดล้อมการใช้งานจริงหน้างาน? | F6: Team Compatibility (Manpower & Skill Redundancy): ทักษะของสมาชิกในทีมมีความเข้ากันได้และการกระจายความเชี่ยวชาญสำรอง (Bus Factor & Redundancy) มากน้อยเพียงใด? | G6: ROI (Payback Period / Value Horizon): ระยะเวลาคืนทุนและกรอบเวลาการสร้างผลตอบแทนคุ้มค่า (Payback Horizon) ต่อระบบสาธารณะหรือผู้ใช้งานอยู่ในเกณฑ์ใด? | H6: Dependencies of Component (Vendor Lock-in & Service Autonomy): ระบบมีความเป็นอิสระจากการผูกขาดของผู้ผลิต (Vendor Lock-in) มากน้อยเพียงใด และสามารถซ่อมบำรุงด้วยเครื่องมือเปิดได้เองหรือไม่? | I6: Scrap Margin (Safety Allowance for Blown ICs & Iterations): โครงการมีการจัดสรรงบประมาณสำรองสำหรับชิ้นส่วนทดแทนกรณีเสียหาย (Scrap Margin) และการทดลองซ้ำมากน้อยเพียงใด? | J6: Felony and Civil Law (Regulatory & Public Safety Compliance): ระบบและการติดตั้งมีความสอดคล้องต่อข้อบังคับทางกฎหมายอาญา แพ่ง ระเบียบจราจร และการคุ้มครองข้อมูลส่วนบุคคล (PDPA / Public Safety) หรือไม่? | K6: IP and Licensing: ทรัพย์สินทางปัญญา ซอฟต์แวร์ไลบรารี และสิทธิบัตรที่นำมาใช้ มีความเปิดกว้างและปลอดภาระผูกพันทางการค้าหรือการละเมิดลิขสิทธิ์ (Licensing Freedom) มากน้อยเพียงใด? | L6: User — Implementation (Field Deployment / Setup Friction): ขั้นตอนการติดตั้ง ติดตั้งเครื่องมือ ปรับเทียบศูนย์ (Calibration) และเตรียมพร้อมใช้งานหน้างานจริงโดยผู้ปฏิบัติงาน มีความยุ่งยากหรือกินเวลาเพียงใด? | M6: User — Customer / Public Safety & Failsafes: ความปลอดภัยเชิงกลและไฟฟ้าต่อเจ้าหน้าที่ผู้ปฏิบัติงานและประชาชนในพื้นที่ (Intrinsic Safety & Failsafes) มีระบบป้องกันในระดับใด? | N6: User — Behavior & Workflow Disruption: ระบบสร้างความเปลี่ยนแปลงหรือรบกวนต่อขั้นตอนการทำงานปกติ (Standard Operating Procedure - SOP) ของผู้ใช้งานเดิมมากน้อยเพียงใด? | O6: Developer — Task Dependency (Critical Path Architecture): โครงสร้างสถาปัตยกรรมของระบบและการแบ่งส่วนงานระหว่างฮาร์ดแวร์ ซอฟต์แวร์ และกลไก มีการแยกส่วน (Decoupling) เพื่อให้พัฒนาคู่ขนานได้มากน้อยเพียงใด? | P6: Developer — Contribution Dependency (Bureaucratic & Lab Gatekeeping): การเข้าถึงเครื่องมือในห้องปฏิบัติการ การอนุมัติงบประมาณ และกระบวนการทางธุรการ (Lab Access & Purchasing Bureaucracy) มีอุปสรรคขัดขวางความคล่องตัวเพียงใด? | Q6: Developer — Task & Skill Compatibility: ความเข้ากันได้ระหว่างทักษะเดิมของทีมกับเทคโนโลยีสแตกของระบบ (Task & Skill Compatibility: 'Water and Oil' vs. 'Oil and Engine') อยู่ในระดับใด? | R6: Production Time (Engineering Design Maturity by Milestone): ความพร้อมของแบบวิศวกรรม (3D CAD, Schematics, PCB Gerbers, Firmware Architecture, BOM) อยู่ในระดับความสมบูรณ์ใดเทียบกับหมุดหมายการผลิตจริง? | S6: Shipping (Component Procurement Lead Time): ระยะเวลาในการจัดหาและขนส่งชิ้นส่วน อุปกรณ์ และเซนเซอร์ (Procurement Lead Time) อยู่ในกรอบเวลาที่ปลอดภัยต่อกำหนดส่งมอบงานหรือไม่? | T6: Real Public Impact vs. Academic Greenwashing (SDG 11.5 / 13.1): Is this genuinely reducing flood/heat losses for the public, or is it just fluff for a presentation slide? | U6: Environmental Footprint & E-Waste ("Do No Harm" — SDG 6.3 / 12.4): Will this hardware end up as toxic e-waste rotting at the bottom of a canal or washing down the river? | V6: Decision Transparency & Public Fairness (SDG 10.2 / 16.6): Can an officer or citizen verify why the system made its call, or is it an unaccountable black box? | W6: ประเมินคำถามทั้งสิ้น 21 ข้อ
A7: เหตุผลในการถาม & โหมดความล้มเหลวที่เฝ้าระวัง (Rationale) | B7: วัดภาระงานสร้างและการวิจัยพัฒนา (Build vs. Buy Burden) ยิ่งสร้างเองจากศูนย์มาก ยิ่งเสี่ยงต่อความล่าช้าและความล้มเหลว | C7: ตรวจสอบอุปสรรคด้านสิทธิ์การเข้าถึง (Access Barriers) เช่น NDA, Closed-source blobs, หรือข้อจำกัดด้านใบอนุญาตที่ขัดขวางการแก้บั๊ก | D7: ตรวจสอบความเสี่ยงด้านห่วงโซ่อุปทาน (Single-source, EOL, Overseas backlog) ที่อาจทำให้โครงการหยุดชะงักเมื่อชิ้นส่วนขาดตลาด | E7: ประเมินความเสถียรของเทคโนโลยีตามมาตรฐาน TRL จากระดับแล็บทดลอง (Lab model) ไปจนถึงระดับใช้งานจริงในสภาวะวิกฤต (Field-proven) | F7: ป้องกัน Single Point of Failure (SPOF) ด้านบุคคล หากมีสมาชิกคนใดคนหนึ่งไม่สามารถปฏิบัติงานได้ ระบบต้องยังสามารถพัฒนาและแก้ไขต่อได้ | G7: วัดความคุ้มค่าทางเศรษฐศาสตร์และการคืนทุนจากการลดความสูญเสีย ค่าแรง หรือค่าเชื้อเพลิง | H7: ตรวจสอบภาระค่าใช้จ่ายแฝงระยะยาว (Recurring Cloud/Licensing Fees) และการพึ่งพาผู้ผลิตรายเดียว | I7: ตรวจสอบงบสำรองสำหรับชิ้นส่วนเสียหาย (Scrap Budget Rule) ป้องกันงานสะดุดเมื่อเกิดชิปไหม้หรือฮาร์ดแวร์หัก | J7: ตรวจสอบความเสี่ยงทางกฎหมายสาธารณะ (พ.ร.บ. จราจร, PDPA, กฎหมายสิ่งแวดล้อม และระเบียบทางหลวง) | K7: ตรวจสอบข้อจำกัดด้านสิทธิ์ซอฟต์แวร์และฮาร์ดแวร์ ป้องกันการติดไวรัสไลเซนส์ (Copyleft GPLv3) หรือการละเมิดสิทธิบัตร | L7: ประเมินความสะดวกในการติดตั้งหน้างาน (Setup Friction) เพื่อป้องกันไม่ให้อุปกรณ์ถูกละเลยเนื่องจากการตั้งค่ายุ่งยาก | M7: ประเมินมาตรการความปลอดภัยและกลไกป้องกันอันตราย (Hazard Failsafes) เช่น สวิตช์ฉุกเฉิน E-stop, ฟิวส์, และการออกแบบป้องกันแรงดันสูง | N7: ประเมินแรงต้านทานจากผู้ใช้งาน (Workflow Friction) และความราบรื่นในการเชื่อมต่อเข้ากับระบบการทำงานเดิมของเจ้าหน้าที่ | O7: ตรวจสอบคอขวดบนสายงานวิกฤต (Critical Path Bottleneck) ป้องกันไม่ให้ทีมซอฟต์แวร์ต้องหยุดรอแผ่นวงจรพิมพ์หรือกลไกที่ยังไม่เสร็จ | P7: ประเมินอุปสรรคด้านการบริหารและเครื่องมือ (Institutional Gatekeeping) เช่น คิวรอเครื่องจักร การล็อกแล็บ หรือขั้นตอนเบิกจ่ายงบประมาณที่ล่าช้า | Q7: ตรวจสอบความสอดคล้องระหว่างทักษะที่ทีมมีอยู่จริงกับเทคโนโลยีที่เลือกใช้ เพื่อป้องกัน Learning Curve ที่สูงเกินไปจนงานล้มเหลว | R7: ประเมินความพร้อมของพิมพ์เขียวการผลิต (Design Maturity Package) ก่อนเริ่มสั่งผลิตจริง เพื่อป้องกันการรื้อแก้แบบกลางคัน | S7: ตรวจสอบห่วงโซ่อุปทาน (Supply Chain Lead Time) ชิ้นส่วนที่ต้องรอส่งจากต่างประเทศเกิน 3 สัปดาห์ถือเป็นความเสี่ยงต่อวิกฤตสัปดาห์สอบและกำหนดส่งมอบ | T7: Your team's 1 vs. 5 premise: "Pure buzzword bullshit to get a grade vs. Actually moves the needle on city infrastructure." | U7: Your team's 1 vs. 5 premise: "Dumping toxic e-waste into public canals vs. Zero-footprint hardware." | V7: Your team's 1 vs. 5 premise: "Black-box algorithm cutting services to poor areas vs. Open, verifiable math." | W7: สังเคราะห์จาก AI Agents Group 2
A8: เกณฑ์การให้คะแนน (Scoring Rubric Definition: ระดับ 1, 2, 3, 4, 5 ครบทุกระดับ) | B8: 1 — Build from Scratch: 100% custom R&D required (custom mechanism, custom PCB, raw algorithm derivation); no reference designs available. 2 — Heavy Customization: Core components exist, but requires extensive custom adaptation, structural machining, and custom wrapper code. 3 — Hybrid / COTS Integration: Standard COTS modules (e.g., standard dev board + breakout sensors) assembled with custom brackets and intermediate wiring. 4 — Modular COTS Assembly: Pre-engineered building blocks with standard mounting and standard communication buses (e.g., Din-rail modules, I2C/CAN shields); minimal custom fabrication. 5 — Commercial Off-the-Shelf (COTS): Buy and use directly out of the box (Plug-and-Play); zero mechanical or electrical fabrication required. | C8: 1 — Strictly Restricted: Proprietary stack under NDA, blocked enterprise firewalls, or unavailable developer licenses. 2 — Limited Access: Closed binary blobs or third-party proprietary software; black-box firmware with zero internal telemetry or source code. 3 — Request-Based Access: Standard educational/evaluation license or public APIs with strict rate limits; requires account verification or approval delays. 4 — Open Developer Access: Free public SDKs, full documentation, and open developer access, but cannot modify upstream core source code. 5 — Unrestricted Full-Stack Access: Fully open source (permissive license) and open hardware; team has root/admin rights to modify, inspect, and deploy as both user and developer. | D8: 1 — Sole-Source / Obsolete: Single overseas supplier, restricted export control, long backorder, or risk of end-of-life (EOL). 2 — Specialized Vendor: Only 1–2 niche industrial suppliers; requires formal corporate quote/PO process; no consumer retail channels. 3 — Moderate Availability: 2–3 regional distributors (e.g., DigiKey, Mouser, Element14); reliable stock but requires overseas shipping. 4 — Multi-Vendor Local Stock: Readily available from multiple domestic vendors; common industrial or maker components with reliable inventory. 5 — Commodity / Off-the-Shelf: Ubiquitous commodity item sold across multiple local electronics shops and online platforms (delivered in 1–2 days). | E8: 1 — Proof of Concept (TRL 3): Bench breadboard or mathematical model; verified only in simulated/controlled lab conditions. 2 — Functional Breadboard (TRL 4): Integrated components working together in lab; messy wiring, fragile, uncalibrated for harsh environments. 3 — Alpha Prototype (TRL 5–6): Enclosed prototype tested in a relevant simulated environment; occasional crashes, requires human supervisor. 4 — Beta / Field-Proven (TRL 7): Pre-production hardware operating reliably in the actual operating environment under real stress. 5 — Commercial Product (TRL 8–9): Fully certified, production-grade commercial product with documented MTBF and mass field reliability. | F8: 1 — Single Point of Failure (SPOF): Only 1 person has the niche skill (if they get sick, the subsystem halts 100%). 2 — Solo Lead with Minimal Backup: 1 person executes; 1 teammate understands basic concepts but cannot debug code or fix hardware alone. 3 — Primary + Secondary Pair: 1 primary developer and 1 competent secondary backup who can maintain, troubleshoot, and push updates. 4 — Broad Competence: 3+ teammates can actively design, assemble, and debug the subsystem with low ramp-up time. 5 — Full Team Redundancy: All team members are fully proficient; tasks can be swapped across anyone with zero friction or velocity loss. | G8: 1 — Long Payback ($\ge 10\text{ Years}$): High initial CapEx and low recurring savings; economically non-viable for rapid deployment. 2 — Slow Return ($6–9\text{ Years}$): Substantial capital investment with long break-even horizon; requires long-term institutional subsidization. 3 — Moderate Return ($3–5\text{ Years}$): Reasonable public infrastructure payback; offsets costs across multi-year operational cycles. 4 — Fast Return ($2–3\text{ Years}$): Strong operational cost reduction (fuel, labor, scrap); breaks even within normal equipment lifecycle. 5 — Immediate Payback ($\le 1–2\text{ Years}$): Rapid break-even; eliminates major recurring losses within the first operating season. | H8: 1 — Total Vendor Lock-in: Proprietary cloud backend, encrypted telemetry, and proprietary connectors; completely dependent on vendor survival. 2 — High Dependency: Hardware requires vendor-licensed diagnostic tools or annual subscription fees to maintain operation. 3 — Semi-Independent: Core hardware relies on proprietary firmware, but allows open API export and standard electrical interfaces. 4 — High Autonomy: Uses standard open communication protocols (e.g., Modbus, MQTT, CAN); parts can be serviced using generic tools. 5 — Complete Independence: 100% open architecture; hardware is interchangeable with generic substitutes; self-serviceable by any engineer. | I8: 1 — Zero Buffer (0%): Exactly 1x BOM purchased; any fried chip, cracked bracket, or wiring mistake kills the project. 2 — Fragile Buffer (20–30%): Spares only for passive components (resistors, connectors); no backup microcontrollers or expensive sensors. 3 — Moderate Buffer (50%): Spares for all critical passive parts and 1 spare for the primary controller board. 4 — High Buffer (80%): Spares for nearly every active component and sensor; can sustain multiple prototype burn-ins. 5 — Full Redundancy ($\ge 100\%$): Complete 2x BOM budget on hand; can build two complete working units simultaneously. | J8: 1 — Severe Violation / No Privilege: Direct breach of statutory law (e.g., unconsented public surveillance/PDPA, hazardous road blockage, RF jammer). 2 — High Legal Exposure: Ambiguous legal zone; high risk of civic complaints or traffic disruption; requires complex technical waivers. 3 — Conditional / Requires Permit: Allowed under explicit written approval, official agency MoU, or municipal permit (e.g., BMA/Highway dept permit). 4 — Low Legal Friction: Operates within standard public engineering exemptions; simple standard notification/safety compliance needed. 5 — 100% Compliant / Free Domain: Completely exempt from statutory licensing; zero public safety risk, zero personal data (Zero PII), fully unrestricted. | K8: 1 — Closed / Commercial Barrier: Proprietary commercial license; cannot compile, flash, or operate without paying expensive commercial seat licenses. 2 — Ambiguous / Gray IP: Unclear licensing terms or unlicensed GitHub repos; risk of copyright strike or IP dispute upon public demonstration. 3 — Restrictive Open Source (Copyleft): Permitted for educational use, but viral licenses (e.g., GPLv3) force your entire codebase to be made public if distributed. 4 — Permissive Open Source: Open source with minimal conditions (e.g., LGPL, CC-BY); allows proprietary wrapping with simple attribution. 5 — Completely Permissive / Public Domain: Permissive open source (MIT, Apache 2.0, BSD) or Public Domain; unrestricted freedom to commercialize, modify, and contribute. | L8: 1 — Laborious Recalibration: Requires multi-point manual physical zeroing, chemical calibration, or oscilloscope tuning before every run. 2 — Complex Setup: Requires trained technician 20–30 minutes to adjust potentiometers, align brackets, or enter configuration commands. 3 — Moderate Field Setup: Simple 5-minute calibration procedure (e.g., tare button or basic mobile app zeroing) performed by non-engineers. 4 — Minimal Setup: Fast clamp-on mounting with automated self-calibration on power-up; ready in $< 1\text{ minute}$. 5 — True Plug and Go: Pure plug-and-play; zero calibration required, zero buttons; power on and immediately operational. | M8: 1 — Critical Hazard: Failure can directly cause electrocution, fire, traffic crashes, chemical exposure, or confined-space asphyxiation. 2 — High Risk / Manual Oversight: High mechanical/electrical hazard requiring constant operator vigilance and full PPE. 3 — Moderate Safety: Protected by passive mechanical guards, fuses, and warning labels; requires basic safety precautions. 4 — High Safety & Interlocks: Active software limits, hardware thermal shutoffs, and reverse polarity protection; minimal hazard on failure. 5 — Inherently Safe & Redundant: Failsafe by physics (cannot store lethal energy); isolated, dual-rated enclosures, redundant E-stops, zero injury risk. | N8: 1 — Disruptive Overhaul: Forces operators to abandon existing SOPs, adds 5+ extra tedious forms/steps, and faces fierce institutional union/worker resistance. 2 — Significant Friction: Adds notable extra documentation or redundant verification steps; operators will actively look for ways to bypass it. 3 — Moderate Adaptation: Modifies daily routine slightly; requires 1–2 training workshops, but delivers clear convenience trade-offs. 4 — Low Friction: Integrates into existing tools (e.g., sends automated alerts to existing LINE/Telegram or ticketing dashboard); minimal change in habits. 5 — Transparent / Seamless Integration: Zero workflow disruption; runs invisibly in background and automates existing manual paperwork without operator intervention. | O8: 1 — Strictly Sequential (Linear): A depends on B depends on C; if the PCB fab is delayed, software and testing halt 100%. 2 — Bottlenecked Pipelines: Major subsystems are tightly coupled; frequent integration stalls waiting for hardware bench access. 3 — Semi-Decoupled: Hardware and software teams can work independently for 1–2 weeks using rough mockups before needing physical integration. 4 — Modular Parallelism: Clear API/interface boundaries; software builds against mock data/simulators while hardware is routed; integration takes $< 2\text{ days}$. 5 — Fully Parallel Architecture: Microservices/modular nodes with standard contracts; mechanical, electrical, and firmware develop, simulate, and unit-test completely in parallel. | P8: 1 — Heavy Gatekeeping: Blocked by supervisor approvals, locked lab cabinets, NDA signatures, purchasing bureaucracy, and restricted git branches. 2 — Moderate Bureaucracy: Requires departmental request forms, tool booking queues, and waiting 3–5 days for administrative sign-offs. 3 — Standard Campus Access: Workable access during university open hours; minor approval delays for equipment or lab keys. 4 — High Autonomy: Team has full repository write access, open 24/7 lab entry, and pre-approved discretionary debit cards/stipends for rapid purchases. 5 — Frictionless Contribution: Complete autonomy; decentralized cloud CI/CD, local prototyping tools at home/bench, zero administrative blockers. | Q8: 1 — Complete Mismatch ("Water and Oil"): Team has zero foundation in the stack (e.g., pure mechanical students forced to train deep neural nets in C++ from scratch). 2 — Steep Learning Curve: High theoretical knowledge, but zero production hands-on experience; debugging basic syntax/wiring stalls progress. 3 — Adjacent Competence: Strong mastery in related tools (e.g., proficient in Arduino/ESP32 migrating to STM32, or SolidWorks migrating to Fusion360); manageable 1-week curve. 4 — Proven Experience: Team has built similar subsystems in past semester coursework or competition robots; rapid ramp-up. 5 — Perfect Synergy ("Oil and Engine"): Complete domain mastery; team members have built this exact architecture multiple times with verified libraries and muscle memory. | R8: 1 — Concept Only (0% Design): Napkin sketches and verbal concepts; 0% CAD models, 0% schematics, 0% code written. 2 — Rough Drafts (25% Design): Preliminary block diagrams, hand-drawn schematics, unverified parts list, incomplete 3D bounding boxes. 3 — Intermediate Maturity (50% Design): Complete CAD assembly (untested clearances), schematic capture complete, draft firmware architecture mapped out. 4 — Pre-Production (80% Design): Fully detailed 3D CAD ready for 3D print/CNC, routed PCB Gerber files validated with DRC, pinouts locked down. 5 — Fully Engineered Design (100% Production Ready): Complete drawing package: BOM with part numbers, verified manufacturing Gerbers, 2D tolerance drawings, assembly SOP, and flashing scripts ready. | S8: 1 — Extreme Lead Time ($\ge 4\text{ Weeks}$): Custom overseas fabrication, customs clearance delays, or parts with long factory lead times (critical path hazard). 2 — High Lead Time ($3–4\text{ Weeks}$): Standard overseas shipping (e.g., standard AliExpress/international postal surface mail); vulnerable to logistics delays. 3 — Moderate Lead Time ($2\text{ Weeks}$): Express international courier (DHL, FedEx, JLCPCB express) or regional distributors (7–14 days). 4 — Short Lead Time ($1\text{ Week}$): Domestic couriers or express domestic stockists (3–5 business days). 5 — Immediate / Next-Day ($\le 1–2\text{ Days}$): Shelf stock available locally at retail shops or next-day domestic express delivery. | T8: 1 — Pure Buzzword / Academic Greenwashing: Claims to "save the city," but has zero real data, zero measurable effect, and solves a problem nobody in the municipality actually experiences. 2 — Superficial Correlation: Indirect impact; functions only as an isolated school demo with no realistic way to measure if it prevented damage or saved money. 3 — Localized Proof: Delivers a measurable, verified benefit (e.g., cuts response time by 10 minutes or drops pavement temp on a single test strip), but lacks a model to scale. 4 — District-Level Viability: Clear pathway to protect municipal infrastructure or reduce public losses across multiple roads/alleys during extreme weather. 5 — Systemic City Resilience: Backed by concrete empirical data showing significant reduction in public economic losses, vehicle damage, or human hazard during severe rain or heat. | U8: 1 — Toxic Canal Hazard: Cheap plastic enclosure cracks under UV, or unsealed LiPo batteries leak toxic chemicals and detach into the drainage network as marine litter. 2 — Fragile Disposable Tech: Short operational lifespan; sensors foul or corrode within 2–3 weeks and are left behind by crews because retrieving them is too annoying. 3 — Standard Field Footprint: Requires periodic battery replacement and creates standard electronic scrap, but utilizes basic tethering to prevent total hardware loss. 4 — Low-Impact Enclosure: Solar-trickle or long-life low-power architecture; uses recyclable casing and redundant physical tethers (e.g., dual stainless lanyards). 5 — Fully Circular & Zero Footprint: 100% fail-safe retrieval design; uses non-toxic, non-leaching materials, consumes minimal public water/energy, and leaves zero trace in the city. | V8: 1 — Opaque Black Box: Proprietary or unexplained threshold that cancels dispatch trucks or alters services with zero explanation, risking quiet abandonment of vulnerable neighborhoods. 2 — Ambiguous Logic: Decision rules are buried in messy heuristic code; field operators cannot explain to a citizen why an alert was triggered or suppressed. 3 — Documented Internal Rules: Logic is documented on paper for engineers, but has no public audit trail or clear appeal mechanism if the sensor misreads. 4 — Open Empirical Standards: Decisions are driven by transparent physical equations (e.g., verified dh/dt thresholds) applied equally across all city zones. 5 — 100% Auditable & Equitable: Full tamper-evident digital audit trail; open logic accessible to city officials and citizens, guaranteeing equal public protection regardless of district wealth. | W8: เกณฑ์รวม: >=80 ผ่านสูง, >=60 มีเงื่อนไข, <60 เสี่ยงสูง | หากมีข้อใดได้ 1 = VETOED ตกเกณฑ์ทันที
A9: คะแนนที่ได้รับ (ASSIGNED SCORE: 1, 2, 3, 4, 5 STRICT INTEGER) | B9: 4 | C9: 4 | D9: 5 | E9: 4 | F9: 4 | G9: 4 | H9: 4 | I9: 5 | J9: 5 | K9: 5 | L9: 5 | M9: 5 | N9: 5 | O9: 5 | P9: 5 | Q9: 4 | R9: 4 | S9: 5 | T9: 5 | U9: 5 | V9: 5 | W9: =IF(W10>0, (W11/W10)*20, 0) -> 91.963196
A10: ค่าน้ำหนัก (Weight %) | B10: 0.04 | C10: 0.04 | D10: 0.04 | E10: 0.04 | F10: 0.04 | G10: 0.0667 | H10: 0.0667 | I10: 0.0666 | J10: 0.075 | K10: 0.075 | L10: 0.0333 | M10: 0.0333 | N10: 0.0333 | O10: 0.0333 | P10: 0.0333 | Q10: 0.0334 | R10: 0.075 | S10: 0.075 | T10: 0.0333 | U10: 0.0333 | V10: 0.0334 | W10: =SUM(B10:V10) -> 0.9999
A11: คะแนนถ่วงน้ำหนัก (=Score * Weight) | B11: =B9*B10 -> 0.16 | C11: =C9*C10 -> 0.16 | D11: =D9*D10 -> 0.2 | E11: =E9*E10 -> 0.16 | F11: =F9*F10 -> 0.16 | G11: =G9*G10 -> 0.2668 | H11: =H9*H10 -> 0.2668 | I11: =I9*I10 -> 0.333 | ... V11: =V9*V10 -> 0.167 | W11: =SUM(B11:V11) -> 4.5977
A12: คำอธิบาย & หลักฐานอ้างอิงจากไฟล์ Intake (Evidence Citation) | B12: อ้างอิง solution-2.md: บูรณาการฮาร์ดแวร์ COTS เข้ากับระบบคลาวด์ API (ESP32 + เซนเซอร์ผิวน้ำ + REST API เรดาร์ฝน) | C12: ใช้ Open API ของหน่วยงานรัฐและไลบรารี Python สาธารณะ แต่ขึ้นกับอัตราการจำกัดการเรียกใช้ API (Open Developer Access) | D12: ฮาร์ดแวร์เป็นบอร์ดไมโครคอนโทรลเลอร์และเซนเซอร์วัดระดับน้ำทั่วไป มีจำหน่ายแพร่หลายในประเทศ (Commodity / Off-the-Shelf) | E12: ถอดแบบจากโมเดล CWOS ของ PUB Singapore ซึ่งเป็นระบบที่ใช้งานจริงระดับเทศบาล (Field-Proven / TRL 7) | F12: สมาชิก 3 คนมีความเชี่ยวชาญด้าน Webhook, Python และ IoT Firmware (Kin, Due, JK) สามารถช่วยกันพัฒนาและทดสอบได้ (Broad Competence) | G12: ลดการสิ้นเปลืองทรัพยากรจากการส่งรถตรวจการไปยังจุดที่ฝนตกแต่ไม่มีน้ำท่วมขัง คืนทุนในเวลา 2-3 ปี | H12: พึ่งพาข้อมูล Radar API จากกรมอุตุนิยมวิทยาหรือสำนักระบายน้ำ หาก API ภายนอกปิดปรับปรุงจำเป็นต้องเขียนระบบเชื่อมต่อใหม่ | I12: เน้นงานซอฟต์แวร์และบอร์ด MCU ตัวเดียว งบประมาณโครงการสามารถจัดซื้อบอร์ดสำรองได้เกิน 100% (Full Redundancy) | J12: ไม่ใช้กล้องบันทึกภาพ ไม่เก็บข้อมูลส่วนบุคคล (Zero PII 100%) ใช้งานข้อมูลอุตุนิยมวิทยาเปิดของภาครัฐอย่างถูกต้อง | K12: สถาปัตยกรรมซอฟต์แวร์พัฒนาด้วยโอเพนซอร์สมาตรฐาน (FastAPI, Leaflet, SQLite ภายใต้ MIT License) ปลอดภาระลิขสิทธิ์ | L12: เซนเซอร์หน้างานเชื่อมต่อคลาวด์อัตโนมัติ ติดตั้งด้วยแคลมป์มาตรฐาน ใช้เวลาเปิดเครื่องพร้อมส่งข้อมูล < 1 นาที | M12: ระบบใช้ไฟกระแสตรง 5V ไม่มีความเสี่ยงไฟฟ้าแรงดันสูง ปลอดภัยตามธรรมชาติทางฟิสิกส์ (Inherently Safe) | N12: ส่งการแจ้งเตือนยืนยัน 2-Factor ตรงเข้ากลุ่ม LINE ของเจ้าหน้าที่เขตโดยอัตโนมัติ ไม่ต้องเปลี่ยนหน้าจอทำงานเดิม | O12: ฝั่งดึง Radar API, ฝั่งประมวลผลตรรกะ 2-Factor, และฝั่ง Web Dashboard แยกกันเป็น Microservices อิสระ พัฒนาคู่ขนานได้ 100% | P12: พัฒนาบนระบบคลาวด์และคอมพิวเตอร์ส่วนตัว ไร้การพึ่งพาห้องปฏิบัติการหรือขั้นตอนอนุมัติทางธุรการ | Q12: สมาชิกมีความเชี่ยวชาญสูงด้าน Python, Cloud Webhook และ Data Integration สอดคล้องกับโครงงานแข่งขันเดิม ('Oil and Engine') | R12: ซอฟต์แวร์ Backend API และ Logic Flowchart เสร็จสมบูรณ์ระดับ Pre-production พร้อมทดสอบเชื่อมต่อข้อมูลจริง | S12: บอร์ด MCU และโมดูลสื่อสารจัดซื้อจากตัวแทนจำหน่ายในประเทศ ได้รับของภายใน 1-2 วันทำการ | T12: ตัด Empty Cases ได้เด็ดขาด ช่วยให้รถ QRT เข้าถึงพื้นที่ประสบภัยจริงได้รวดเร็วขึ้น เพิ่มขีดความสามารถการรับมือภัยพิบัติเมือง (SDG 11.5 / 13.1) | U12: ลดการปล่อยก๊าซคาร์บอนไดออกไซด์จากการวิ่งรถเครื่องยนต์ดีเซลเปล่า และประหยัดน้ำมันเชื้อเพลิงของหน่วยงานรัฐ (SDG 13.2 และ SDG 12.4) | V12: สร้างความโปร่งใสในระบบสั่งการของ กทม. ตรวจสอบย้อนหลังได้ว่าจุดใดได้รับการช่วยเหลือตามเกณฑ์วิทยาศาสตร์ (SDG 16.6) | W12: =IF(MIN(B9:V9)=1, "VETOED / ตกเกณฑ์ข้อบังคับวิกฤต (คะแนนระดับ 1)", IF(W9>=80, "ผ่านเกณฑ์ระดับสูง (HIGHLY VIABLE)", IF(W9>=60, "ผ่านแบบมีเงื่อนไข (CONDITIONALLY VIABLE)", "ความเสี่ยงสูง (HIGH RISK)"))) -> ผ่านเกณฑ์ระดับสูง (HIGHLY VIABLE)
A13: แผนลดขอบเขตงาน & มาตรการลดความเสี่ยง (De-scoping Action) | B13: ใช้บอร์ด ESP32 สำเร็จรูปพร้อมเสาอากาศมาตรฐาน | C13: กำหนดโครงสร้าง REST API ให้ชัดเจนเพื่อให้สมาชิกสลับงานกันเขียนโค้ดได้ | D13: จัดซื้อชิ้นส่วน MCU สต็อกในประเทศ | E13: จำลองข้อมูลฝนเพื่อทดสอบความแม่นยำของระบบก่อนต่อ API จริง | F13: แบ่งงานพัฒนาฝั่ง Dashboard และฝั่ง Microcontroller ชัดเจน | G13: ใช้บริการคลาวด์ระดับ Free Tier (เช่น Supabase หรือ Railway) เพื่อลดต้นทุนดำเนินงาน | H13: ทำระบบ Local Fallback รับค่าเฉพาะเซนเซอร์ผิวน้ำหาก Radar API ขัดข้อง | I13: สำรองบอร์ดไมโครคอนโทรลเลอร์ 2 ชุดสำหรับทดสอบและใช้งานจริง | J13: ปฏิบัติตามข้อกำหนดการดึงข้อมูล Open Data ของภาครัฐ | K13: ใช้ไลบรารีโอเพนซอร์สที่มีสัญญาอนุญาต MIT หรือ BSD เท่านั้น | L13: ออกแบบระบบ Auto-provisioning สำหรับเชื่อมต่อ Wi-Fi/Cellular อัตโนมัติ | M13: ใส่เคสกันฝุ่นและกันละอองน้ำมาตรฐาน IP65 ให้กับชุดรับสัญญาณ | N13: จัดรูปแบบข้อความแจ้งเตือนใน LINE ให้กระชับ ระบุพิกัดและระดับน้ำชัดเจน | O13: สร้าง Mock Service จำลองฝนตกเพื่อทดสอบระบบตรรกะโดยไม่ต้องรอฝนตกจริง | P13: ใช้ GitHub Actions รัน Unit Test อัตโนมัติทุกครั้งที่ Pull Request | Q13: ให้ Kin ดูแลฝั่ง Dashboard และ JK ดูแลอัลกอริทึม 2-Factor Logic | R13: ทดสอบระบบรวมกับข้อมูลย้อนหลังของ กทม. ก่อนสัปดาห์ที่ 8 | S13: จัดเตรียมอะไหล่โมดูลสำรองไว้ล่วงหน้าก่อนเริ่มช่วงมิดเทอม | T13: เก็บสถิติชั่วโมงการระบายน้ำที่เร็วขึ้นเพื่อรายงานผลสัมฤทธิ์เมือง | U13: คำนวณปริมาณคาร์บอนที่ลดได้จากการตัดเที่ยวรถเปล่า | V13: เปิดเผย API ให้ภาคประชาชนเข้าถึงข้อมูลสถานะน้ำท่วมได้เสรี | W13: ปฏิบัติตามแผนลดขอบเขตงาน (De-scoping Advisory)
A15: ตารางสรุปคะแนนแยกตามมิติ TELOS+S (Pillar Score Breakdown)
A16: มิติการประเมิน (TELOS+S Pillar) | B16: สัดส่วนน้ำหนัก (Weight %) | C16: คะแนนเต็มมิติ (Max Points) | D16: คะแนนที่ได้รับจริง (Earned Points) | E16: คะแนนเฉลี่ย (Score 1-5) | F16: ระดับความพร้อม (Readiness Level)
A17: T : ด้านเทคโนโลยีและวิศวกรรม (Technical) | B17: 0.2 | C17: 20 | D17: =SUM(B11:F11)*20 -> 16.8 | E17: =IF(C17>0, (D17/C17)*5, 0) -> 4.2 | F17: =IF(D17>=16, "พร้อมระดับสูง (High)", IF(D17>=12, "ปานกลาง (Medium)", "เสี่ยงวิกฤต (Critical)")) -> พร้อมระดับสูง (High)
A18: E : ด้านเศรษฐศาสตร์และความคุ้มค่า (Economic) | B18: 0.2 | C18: 20 | D18: =SUM(G11:I11)*20 -> 17.332 | E18: =IF(C18>0, (D18/C18)*5, 0) -> 4.333 | F18: =IF(D18>=16, "พร้อมระดับสูง (High)", IF(D18>=12, "ปานกลาง (Medium)", "เสี่ยงวิกฤต (Critical)")) -> พร้อมระดับสูง (High)
A19: L : ด้านกฎหมาย ระเบียบ และภาคประชาชน (Legal & Outreach) | B19: 0.15 | C19: 15 | D19: =SUM(J11:K11)*20 -> 15 | E19: =IF(C19>0, (D19/C19)*5, 0) -> 5 | F19: =IF(D19>=12, "พร้อมระดับสูง (High)", IF(D19>=9, "ปานกลาง (Medium)", "เสี่ยงวิกฤต (Critical)")) -> พร้อมระดับสูง (High)
A20: O : ด้านการปฏิบัติการและหน้างาน (Operational) | B20: 0.2 | C20: 20 | D20: =SUM(L11:Q11)*20 -> 19.322 | E20: =IF(C20>0, (D20/C20)*5, 0) -> 4.8305 | F20: =IF(D20>=16, "พร้อมระดับสูง (High)", IF(D20>=12, "ปานกลาง (Medium)", "เสี่ยงวิกฤต (Critical)")) -> พร้อมระดับสูง (High)
A21: S : ด้านแผนงานและเวลาส่งมอบ (Schedule) | B21: 0.15 | C21: 15 | D21: =SUM(R11:S11)*20 -> 13.5 | E21: =IF(C21>0, (D21/C21)*5, 0) -> 4.5 | F21: =IF(D21>=12, "พร้อมระดับสูง (High)", IF(D21>=9, "ปานกลาง (Medium)", "เสี่ยงวิกฤต (Critical)")) -> พร้อมระดับสูง (High)
A22: +S : ด้านความยั่งยืนและสิ่งแวดล้อม (Sustainability / SDG) | B22: 0.1 | C22: 10 | D22: =SUM(T11:V11)*20 -> 10 | E22: =IF(C22>0, (D22/C22)*5, 0) -> 5 | F22: =IF(D22>=8, "พร้อมระดับสูง (High)", IF(D22>=6, "ปานกลาง (Medium)", "เสี่ยงวิกฤต (Critical)")) -> พร้อมระดับสูง (High)
A23: คะแนนรวมทุกมิติ (Total Feasibility Score) | B23: =SUM(B17:B22) -> 1 | C23: =SUM(C17:C22) -> 100 | D23: =SUM(D17:D22) -> 91.954 | E23: =IF(C23>0, (D23/C23)*5, 0) -> 4.5977 | F23: =IF(D23>=80, "ผ่านเกณฑ์ระดับสูง (HIGHLY VIABLE)", IF(D23>=60, "ผ่านแบบมีเงื่อนไข (CONDITIONALLY VIABLE)", "ความเสี่ยงสูง (HIGH RISK)")) -> ผ่านเกณฑ์ระดับสูง (HIGHLY VIABLE)
A25: เมทริกซ์ประเมินความเข้ากันได้กับองค์ความรู้ด้านวิศวกรรมหุ่นยนต์ (Robotics Knowledge Compatibility)
A26: * หมายเหตุ: การประเมินส่วนนี้วัดศักยภาพในการประยุกต์ใช้องค์ความรู้ด้านวิศวกรรมหุ่นยนต์ (Perception, Control, Actuation, Mechatronics) เต็ม 10 คะแนน | เป็นเอกเทศ ไม่นับรวมในคะแนน TELOS 100 คะแนน
A27: มิติการประเมิน (Robotics Dimension) | B27: คะแนนศักยภาพ (/10) | C27: แกน Perception & Sensing (การรับรู้) | D27: แกน Control & Algorithms (การควบคุม) | E27: แกน Actuation & Mechanisms (กลไก) | F27: บทวิเคราะห์เชิงวิศวกรรมหุ่นยนต์ (FIBO Alignment Rationale)
A28: ศักยภาพการประยุกต์ใช้องค์ความรู้หุ่นยนต์และระบบอัตโนมัติ | B28: 5 | C28: การรวมข้อมูลพหุเซนเซอร์ (Multi-Sensor Data Fusion): รวมข้อมูลฝนจากเรดาร์ระยะไกล (Radar Rainfall Reflectivity) เข้ากับเซนเซอร์วัดระดับน้ำผิวดินหน้างานจริง | D28: ตรรกะการตัดสินใจแบบมีเงื่อนไข (Rule-based Decision Logic): 2-Factor Boolean Gate (ฝนตกหนักจริง AND น้ำท่วมขังจริง) สำหรับคัดกรองสัญญาณสั่งการเจ้าหน้าที่ | E28: ไม่มีระบบการทำงานเชิงกลหรือการเคลื่อนที่ของหุ่นยนต์ (Zero Physical Actuation / Pure Software Gateway) | F28: มีความเข้ากันได้ในแกนการประมวลผลข้อมูลและสถาปัตยกรรมตรรกะควบคุม (Control & Decision Logic) แต่ขาดแกนกลไก (Mechanics) และ Actuation ของหุ่นยนต์อย่างสิ้นเชิง คะแนนจึงอยู่ที่ 5.0

Sheet Solution-3
A1: เมทริกซ์ประเมินความเป็นไปได้เชิงระบบ TELOS+S: Acoustic Sewer Measurement & Pre-Screening Maintenance (UK/USA SL-RAT Case)
A2: ระบบคะแนนจำนวนเต็มเด็ดขาด: 1, 2, 3, 4, 5 เท่านั้น (ไม่มีจุดทศนิยม / ไม่มี 0.5) | โครงสร้างแบบ Transposed แนวนอน
A4: รหัสคำถาม (Question Code) | B4: T-01 | C4: T-02 | D4: T-03 | E4: T-04 | F4: T-05 | G4: E-01 | H4: E-02 | I4: E-03 | J4: L-01 | K4: L-02 | L4: O-01 | M4: O-02 | N4: O-03 | O4: O-04 | P4: O-05 | Q4: O-06 | R4: S-01 | S4: S-02 | T4: SDG-01 | U4: SDG-02 | V4: SDG-03 | W4: สรุปภาพรวม (SUMMARY)
A5: มิติการประเมิน (TELOS+S Pillar) | B5: ด้านเทคโนโลยีและวิศวกรรม (Technical Feasibility) | C5: ด้านเทคโนโลยีและวิศวกรรม (Technical Feasibility) | D5: ด้านเทคโนโลยีและวิศวกรรม (Technical Feasibility) | E5: ด้านเทคโนโลยีและวิศวกรรม (Technical Feasibility) | F5: ด้านเทคโนโลยีและวิศวกรรม (Technical Feasibility) | G5: ด้านเศรษฐศาสตร์ (Economic Feasibility) | H5: ด้านเศรษฐศาสตร์ (Economic Feasibility) | I5: ด้านเศรษฐศาสตร์ (Economic Feasibility) | J5: ด้านกฎหมายและสถาบัน (Legal & Institutional Feasibility) | K5: ด้านกฎหมายและสถาบัน (Legal & Institutional Feasibility) | L5: ด้านการปฏิบัติการ (Operational Feasibility) | M5: ด้านการปฏิบัติการ (Operational Feasibility) | N5: ด้านการปฏิบัติการ (Operational Feasibility) | O5: ด้านการปฏิบัติการ (Operational Feasibility) | P5: ด้านการปฏิบัติการ (Operational Feasibility) | Q5: ด้านการปฏิบัติการ (Operational Feasibility) | R5: ด้านแผนงานและเวลา (Schedule Feasibility) | S5: ด้านแผนงานและเวลา (Schedule Feasibility) | T5: +S ด้านความยั่งยืน (Sustainable Feasibility) | U5: +S ด้านความยั่งยืน (Sustainable Feasibility) | V5: +S ด้านความยั่งยืน (Sustainable Feasibility) | W5: ผลรวมทุกมิติ (All Pillars)
A6: คำถามทดสอบความเสี่ยงจริง (Stress-Test Question) | B6: Implementation (Build vs. Buy Burden): ระบบต้องพัฒนาขึ้นเองจากศูนย์ (Custom R&D) หรือสามารถประกอบขึ้นจากโมดูลสำเร็จรูป (COTS Assembly)? | C6: Access (Tech Stack & Ecosystem Permissions): สแตกเทคโนโลยีและสิทธิ์การเข้าถึงระบบ (Permissions & Ecosystem) มีความเปิดกว้างเพียงใดในการตรวจสอบ แก้ไข และพัฒนาต่อยอด? | D6: Supply (Component Procurement & Vendor Availability): ชิ้นส่วนและอุปกรณ์หลักมีห่วงโซ่อุปทานและความพร้อมในการจัดหา (Supply & Vendor Availability) จากผู้จำหน่ายในระดับใด? | E6: Base Performance (Technology Readiness Level - TRL): ระดับความพร้อมของเทคโนโลยี (TRL) ของระบบอยู่ในขั้นใดเมื่อเทียบกับสภาวะแวดล้อมการใช้งานจริงหน้างาน? | F6: Team Compatibility (Manpower & Skill Redundancy): ทักษะของสมาชิกในทีมมีความเข้ากันได้และการกระจายความเชี่ยวชาญสำรอง (Bus Factor & Redundancy) มากน้อยเพียงใด? | G6: ROI (Payback Period / Value Horizon): ระยะเวลาคืนทุนและกรอบเวลาการสร้างผลตอบแทนคุ้มค่า (Payback Horizon) ต่อระบบสาธารณะหรือผู้ใช้งานอยู่ในเกณฑ์ใด? | H6: Dependencies of Component (Vendor Lock-in & Service Autonomy): ระบบมีความเป็นอิสระจากการผูกขาดของผู้ผลิต (Vendor Lock-in) มากน้อยเพียงใด และสามารถซ่อมบำรุงด้วยเครื่องมือเปิดได้เองหรือไม่? | I6: Scrap Margin (Safety Allowance for Blown ICs & Iterations): โครงการมีการจัดสรรงบประมาณสำรองสำหรับชิ้นส่วนทดแทนกรณีเสียหาย (Scrap Margin) และการทดลองซ้ำมากน้อยเพียงใด? | J6: Felony and Civil Law (Regulatory & Public Safety Compliance): ระบบและการติดตั้งมีความสอดคล้องต่อข้อบังคับทางกฎหมายอาญา แพ่ง ระเบียบจราจร และการคุ้มครองข้อมูลส่วนบุคคล (PDPA / Public Safety) หรือไม่? | K6: IP and Licensing: ทรัพย์สินทางปัญญา ซอฟต์แวร์ไลบรารี และสิทธิบัตรที่นำมาใช้ มีความเปิดกว้างและปลอดภาระผูกพันทางการค้าหรือการละเมิดลิขสิทธิ์ (Licensing Freedom) มากน้อยเพียงใด? | L6: User — Implementation (Field Deployment / Setup Friction): ขั้นตอนการติดตั้ง ติดตั้งเครื่องมือ ปรับเทียบศูนย์ (Calibration) และเตรียมพร้อมใช้งานหน้างานจริงโดยผู้ปฏิบัติงาน มีความยุ่งยากหรือกินเวลาเพียงใด? | M6: User — Customer / Public Safety & Failsafes: ความปลอดภัยเชิงกลและไฟฟ้าต่อเจ้าหน้าที่ผู้ปฏิบัติงานและประชาชนในพื้นที่ (Intrinsic Safety & Failsafes) มีระบบป้องกันในระดับใด? | N6: User — Behavior & Workflow Disruption: ระบบสร้างความเปลี่ยนแปลงหรือรบกวนต่อขั้นตอนการทำงานปกติ (Standard Operating Procedure - SOP) ของผู้ใช้งานเดิมมากน้อยเพียงใด? | O6: Developer — Task Dependency (Critical Path Architecture): โครงสร้างสถาปัตยกรรมของระบบและการแบ่งส่วนงานระหว่างฮาร์ดแวร์ ซอฟต์แวร์ และกลไก มีการแยกส่วน (Decoupling) เพื่อให้พัฒนาคู่ขนานได้มากน้อยเพียงใด? | P6: Developer — Contribution Dependency (Bureaucratic & Lab Gatekeeping): การเข้าถึงเครื่องมือในห้องปฏิบัติการ การอนุมัติงบประมาณ และกระบวนการทางธุรการ (Lab Access & Purchasing Bureaucracy) มีอุปสรรคขัดขวางความคล่องตัวเพียงใด? | Q6: Developer — Task & Skill Compatibility: ความเข้ากันได้ระหว่างทักษะเดิมของทีมกับเทคโนโลยีสแตกของระบบ (Task & Skill Compatibility: 'Water and Oil' vs. 'Oil and Engine') อยู่ในระดับใด? | R6: Production Time (Engineering Design Maturity by Milestone): ความพร้อมของแบบวิศวกรรม (3D CAD, Schematics, PCB Gerbers, Firmware Architecture, BOM) อยู่ในระดับความสมบูรณ์ใดเทียบกับหมุดหมายการผลิตจริง? | S6: Shipping (Component Procurement Lead Time): ระยะเวลาในการจัดหาและขนส่งชิ้นส่วน อุปกรณ์ และเซนเซอร์ (Procurement Lead Time) อยู่ในกรอบเวลาที่ปลอดภัยต่อกำหนดส่งมอบงานหรือไม่? | T6: Real Public Impact vs. Academic Greenwashing (SDG 11.5 / 13.1): Is this genuinely reducing flood/heat losses for the public, or is it just fluff for a presentation slide? | U6: Environmental Footprint & E-Waste ("Do No Harm" — SDG 6.3 / 12.4): Will this hardware end up as toxic e-waste rotting at the bottom of a canal or washing down the river? | V6: Decision Transparency & Public Fairness (SDG 10.2 / 16.6): Can an officer or citizen verify why the system made its call, or is it an unaccountable black box? | W6: ประเมินคำถามทั้งสิ้น 21 ข้อ
A7: เหตุผลในการถาม & โหมดความล้มเหลวที่เฝ้าระวัง (Rationale) | B7: วัดภาระงานสร้างและการวิจัยพัฒนา (Build vs. Buy Burden) ยิ่งสร้างเองจากศูนย์มาก ยิ่งเสี่ยงต่อความล่าช้าและความล้มเหลว | C7: ตรวจสอบอุปสรรคด้านสิทธิ์การเข้าถึง (Access Barriers) เช่น NDA, Closed-source blobs, หรือข้อจำกัดด้านใบอนุญาตที่ขัดขวางการแก้บั๊ก | D7: ตรวจสอบความเสี่ยงด้านห่วงโซ่อุปทาน (Single-source, EOL, Overseas backlog) ที่อาจทำให้โครงการหยุดชะงักเมื่อชิ้นส่วนขาดตลาด | E7: ประเมินความเสถียรของเทคโนโลยีตามมาตรฐาน TRL จากระดับแล็บทดลอง (Lab model) ไปจนถึงระดับใช้งานจริงในสภาวะวิกฤต (Field-proven) | F7: ป้องกัน Single Point of Failure (SPOF) ด้านบุคคล หากมีสมาชิกคนใดคนหนึ่งไม่สามารถปฏิบัติงานได้ ระบบต้องยังสามารถพัฒนาและแก้ไขต่อได้ | G7: วัดความคุ้มค่าทางเศรษฐศาสตร์และการคืนทุนจากการลดความสูญเสีย ค่าแรง หรือค่าเชื้อเพลิง | H7: ตรวจสอบภาระค่าใช้จ่ายแฝงระยะยาว (Recurring Cloud/Licensing Fees) และการพึ่งพาผู้ผลิตรายเดียว | I7: ตรวจสอบงบสำรองสำหรับชิ้นส่วนเสียหาย (Scrap Budget Rule) ป้องกันงานสะดุดเมื่อเกิดชิปไหม้หรือฮาร์ดแวร์หัก | J7: ตรวจสอบความเสี่ยงทางกฎหมายสาธารณะ (พ.ร.บ. จราจร, PDPA, กฎหมายสิ่งแวดล้อม และระเบียบทางหลวง) | K7: ตรวจสอบข้อจำกัดด้านสิทธิ์ซอฟต์แวร์และฮาร์ดแวร์ ป้องกันการติดไวรัสไลเซนส์ (Copyleft GPLv3) หรือการละเมิดสิทธิบัตร | L7: ประเมินความสะดวกในการติดตั้งหน้างาน (Setup Friction) เพื่อป้องกันไม่ให้อุปกรณ์ถูกละเลยเนื่องจากการตั้งค่ายุ่งยาก | M7: ประเมินมาตรการความปลอดภัยและกลไกป้องกันอันตราย (Hazard Failsafes) เช่น สวิตช์ฉุกเฉิน E-stop, ฟิวส์, และการออกแบบป้องกันแรงดันสูง | N7: ประเมินแรงต้านทานจากผู้ใช้งาน (Workflow Friction) และความราบรื่นในการเชื่อมต่อเข้ากับระบบการทำงานเดิมของเจ้าหน้าที่ | O7: ตรวจสอบคอขวดบนสายงานวิกฤต (Critical Path Bottleneck) ป้องกันไม่ให้ทีมซอฟต์แวร์ต้องหยุดรอแผ่นวงจรพิมพ์หรือกลไกที่ยังไม่เสร็จ | P7: ประเมินอุปสรรคด้านการบริหารและเครื่องมือ (Institutional Gatekeeping) เช่น คิวรอเครื่องจักร การล็อกแล็บ หรือขั้นตอนเบิกจ่ายงบประมาณที่ล่าช้า | Q7: ตรวจสอบความสอดคล้องระหว่างทักษะที่ทีมมีอยู่จริงกับเทคโนโลยีที่เลือกใช้ เพื่อป้องกัน Learning Curve ที่สูงเกินไปจนงานล้มเหลว | R7: ประเมินความพร้อมของพิมพ์เขียวการผลิต (Design Maturity Package) ก่อนเริ่มสั่งผลิตจริง เพื่อป้องกันการรื้อแก้แบบกลางคัน | S7: ตรวจสอบห่วงโซ่อุปทาน (Supply Chain Lead Time) ชิ้นส่วนที่ต้องรอส่งจากต่างประเทศเกิน 3 สัปดาห์ถือเป็นความเสี่ยงต่อวิกฤตสัปดาห์สอบและกำหนดส่งมอบ | T7: Your team's 1 vs. 5 premise: "Pure buzzword bullshit to get a grade vs. Actually moves the needle on city infrastructure." | U7: Your team's 1 vs. 5 premise: "Dumping toxic e-waste into public canals vs. Zero-footprint hardware." | V7: Your team's 1 vs. 5 premise: "Black-box algorithm cutting services to poor areas vs. Open, verifiable math." | W7: สังเคราะห์จาก AI Agents Group 2
A8: เกณฑ์การให้คะแนน (Scoring Rubric Definition: ระดับ 1, 2, 3, 4, 5 ครบทุกระดับ) | B8: 1 — Build from Scratch: 100% custom R&D required (custom mechanism, custom PCB, raw algorithm derivation); no reference designs available. 2 — Heavy Customization: Core components exist, but requires extensive custom adaptation, structural machining, and custom wrapper code. 3 — Hybrid / COTS Integration: Standard COTS modules (e.g., standard dev board + breakout sensors) assembled with custom brackets and intermediate wiring. 4 — Modular COTS Assembly: Pre-engineered building blocks with standard mounting and standard communication buses (e.g., Din-rail modules, I2C/CAN shields); minimal custom fabrication. 5 — Commercial Off-the-Shelf (COTS): Buy and use directly out of the box (Plug-and-Play); zero mechanical or electrical fabrication required. | C8: 1 — Strictly Restricted: Proprietary stack under NDA, blocked enterprise firewalls, or unavailable developer licenses. 2 — Limited Access: Closed binary blobs or third-party proprietary software; black-box firmware with zero internal telemetry or source code. 3 — Request-Based Access: Standard educational/evaluation license or public APIs with strict rate limits; requires account verification or approval delays. 4 — Open Developer Access: Free public SDKs, full documentation, and open developer access, but cannot modify upstream core source code. 5 — Unrestricted Full-Stack Access: Fully open source (permissive license) and open hardware; team has root/admin rights to modify, inspect, and deploy as both user and developer. | D8: 1 — Sole-Source / Obsolete: Single overseas supplier, restricted export control, long backorder, or risk of end-of-life (EOL). 2 — Specialized Vendor: Only 1–2 niche industrial suppliers; requires formal corporate quote/PO process; no consumer retail channels. 3 — Moderate Availability: 2–3 regional distributors (e.g., DigiKey, Mouser, Element14); reliable stock but requires overseas shipping. 4 — Multi-Vendor Local Stock: Readily available from multiple domestic vendors; common industrial or maker components with reliable inventory. 5 — Commodity / Off-the-Shelf: Ubiquitous commodity item sold across multiple local electronics shops and online platforms (delivered in 1–2 days). | E8: 1 — Proof of Concept (TRL 3): Bench breadboard or mathematical model; verified only in simulated/controlled lab conditions. 2 — Functional Breadboard (TRL 4): Integrated components working together in lab; messy wiring, fragile, uncalibrated for harsh environments. 3 — Alpha Prototype (TRL 5–6): Enclosed prototype tested in a relevant simulated environment; occasional crashes, requires human supervisor. 4 — Beta / Field-Proven (TRL 7): Pre-production hardware operating reliably in the actual operating environment under real stress. 5 — Commercial Product (TRL 8–9): Fully certified, production-grade commercial product with documented MTBF and mass field reliability. | F8: 1 — Single Point of Failure (SPOF): Only 1 person has the niche skill (if they get sick, the subsystem halts 100%). 2 — Solo Lead with Minimal Backup: 1 person executes; 1 teammate understands basic concepts but cannot debug code or fix hardware alone. 3 — Primary + Secondary Pair: 1 primary developer and 1 competent secondary backup who can maintain, troubleshoot, and push updates. 4 — Broad Competence: 3+ teammates can actively design, assemble, and debug the subsystem with low ramp-up time. 5 — Full Team Redundancy: All team members are fully proficient; tasks can be swapped across anyone with zero friction or velocity loss. | G8: 1 — Long Payback ($\ge 10\text{ Years}$): High initial CapEx and low recurring savings; economically non-viable for rapid deployment. 2 — Slow Return ($6–9\text{ Years}$): Substantial capital investment with long break-even horizon; requires long-term institutional subsidization. 3 — Moderate Return ($3–5\text{ Years}$): Reasonable public infrastructure payback; offsets costs across multi-year operational cycles. 4 — Fast Return ($2–3\text{ Years}$): Strong operational cost reduction (fuel, labor, scrap); breaks even within normal equipment lifecycle. 5 — Immediate Payback ($\le 1–2\text{ Years}$): Rapid break-even; eliminates major recurring losses within the first operating season. | H8: 1 — Total Vendor Lock-in: Proprietary cloud backend, encrypted telemetry, and proprietary connectors; completely dependent on vendor survival. 2 — High Dependency: Hardware requires vendor-licensed diagnostic tools or annual subscription fees to maintain operation. 3 — Semi-Independent: Core hardware relies on proprietary firmware, but allows open API export and standard electrical interfaces. 4 — High Autonomy: Uses standard open communication protocols (e.g., Modbus, MQTT, CAN); parts can be serviced using generic tools. 5 — Complete Independence: 100% open architecture; hardware is interchangeable with generic substitutes; self-serviceable by any engineer. | I8: 1 — Zero Buffer (0%): Exactly 1x BOM purchased; any fried chip, cracked bracket, or wiring mistake kills the project. 2 — Fragile Buffer (20–30%): Spares only for passive components (resistors, connectors); no backup microcontrollers or expensive sensors. 3 — Moderate Buffer (50%): Spares for all critical passive parts and 1 spare for the primary controller board. 4 — High Buffer (80%): Spares for nearly every active component and sensor; can sustain multiple prototype burn-ins. 5 — Full Redundancy ($\ge 100\%$): Complete 2x BOM budget on hand; can build two complete working units simultaneously. | J8: 1 — Severe Violation / No Privilege: Direct breach of statutory law (e.g., unconsented public surveillance/PDPA, hazardous road blockage, RF jammer). 2 — High Legal Exposure: Ambiguous legal zone; high risk of civic complaints or traffic disruption; requires complex technical waivers. 3 — Conditional / Requires Permit: Allowed under explicit written approval, official agency MoU, or municipal permit (e.g., BMA/Highway dept permit). 4 — Low Legal Friction: Operates within standard public engineering exemptions; simple standard notification/safety compliance needed. 5 — 100% Compliant / Free Domain: Completely exempt from statutory licensing; zero public safety risk, zero personal data (Zero PII), fully unrestricted. | K8: 1 — Closed / Commercial Barrier: Proprietary commercial license; cannot compile, flash, or operate without paying expensive commercial seat licenses. 2 — Ambiguous / Gray IP: Unclear licensing terms or unlicensed GitHub repos; risk of copyright strike or IP dispute upon public demonstration. 3 — Restrictive Open Source (Copyleft): Permitted for educational use, but viral licenses (e.g., GPLv3) force your entire codebase to be made public if distributed. 4 — Permissive Open Source: Open source with minimal conditions (e.g., LGPL, CC-BY); allows proprietary wrapping with simple attribution. 5 — Completely Permissive / Public Domain: Permissive open source (MIT, Apache 2.0, BSD) or Public Domain; unrestricted freedom to commercialize, modify, and contribute. | L8: 1 — Laborious Recalibration: Requires multi-point manual physical zeroing, chemical calibration, or oscilloscope tuning before every run. 2 — Complex Setup: Requires trained technician 20–30 minutes to adjust potentiometers, align brackets, or enter configuration commands. 3 — Moderate Field Setup: Simple 5-minute calibration procedure (e.g., tare button or basic mobile app zeroing) performed by non-engineers. 4 — Minimal Setup: Fast clamp-on mounting with automated self-calibration on power-up; ready in $< 1\text{ minute}$. 5 — True Plug and Go: Pure plug-and-play; zero calibration required, zero buttons; power on and immediately operational. | M8: 1 — Critical Hazard: Failure can directly cause electrocution, fire, traffic crashes, chemical exposure, or confined-space asphyxiation. 2 — High Risk / Manual Oversight: High mechanical/electrical hazard requiring constant operator vigilance and full PPE. 3 — Moderate Safety: Protected by passive mechanical guards, fuses, and warning labels; requires basic safety precautions. 4 — High Safety & Interlocks: Active software limits, hardware thermal shutoffs, and reverse polarity protection; minimal hazard on failure. 5 — Inherently Safe & Redundant: Failsafe by physics (cannot store lethal energy); isolated, dual-rated enclosures, redundant E-stops, zero injury risk. | N8: 1 — Disruptive Overhaul: Forces operators to abandon existing SOPs, adds 5+ extra tedious forms/steps, and faces fierce institutional union/worker resistance. 2 — Significant Friction: Adds notable extra documentation or redundant verification steps; operators will actively look for ways to bypass it. 3 — Moderate Adaptation: Modifies daily routine slightly; requires 1–2 training workshops, but delivers clear convenience trade-offs. 4 — Low Friction: Integrates into existing tools (e.g., sends automated alerts to existing LINE/Telegram or ticketing dashboard); minimal change in habits. 5 — Transparent / Seamless Integration: Zero workflow disruption; runs invisibly in background and automates existing manual paperwork without operator intervention. | O8: 1 — Strictly Sequential (Linear): A depends on B depends on C; if the PCB fab is delayed, software and testing halt 100%. 2 — Bottlenecked Pipelines: Major subsystems are tightly coupled; frequent integration stalls waiting for hardware bench access. 3 — Semi-Decoupled: Hardware and software teams can work independently for 1–2 weeks using rough mockups before needing physical integration. 4 — Modular Parallelism: Clear API/interface boundaries; software builds against mock data/simulators while hardware is routed; integration takes $< 2\text{ days}$. 5 — Fully Parallel Architecture: Microservices/modular nodes with standard contracts; mechanical, electrical, and firmware develop, simulate, and unit-test completely in parallel. | P8: 1 — Heavy Gatekeeping: Blocked by supervisor approvals, locked lab cabinets, NDA signatures, purchasing bureaucracy, and restricted git branches. 2 — Moderate Bureaucracy: Requires departmental request forms, tool booking queues, and waiting 3–5 days for administrative sign-offs. 3 — Standard Campus Access: Workable access during university open hours; minor approval delays for equipment or lab keys. 4 — High Autonomy: Team has full repository write access, open 24/7 lab entry, and pre-approved discretionary debit cards/stipends for rapid purchases. 5 — Frictionless Contribution: Complete autonomy; decentralized cloud CI/CD, local prototyping tools at home/bench, zero administrative blockers. | Q8: 1 — Complete Mismatch ("Water and Oil"): Team has zero foundation in the stack (e.g., pure mechanical students forced to train deep neural nets in C++ from scratch). 2 — Steep Learning Curve: High theoretical knowledge, but zero production hands-on experience; debugging basic syntax/wiring stalls progress. 3 — Adjacent Competence: Strong mastery in related tools (e.g., proficient in Arduino/ESP32 migrating to STM32, or SolidWorks migrating to Fusion360); manageable 1-week curve. 4 — Proven Experience: Team has built similar subsystems in past semester coursework or competition robots; rapid ramp-up. 5 — Perfect Synergy ("Oil and Engine"): Complete domain mastery; team members have built this exact architecture multiple times with verified libraries and muscle memory. | R8: 1 — Concept Only (0% Design): Napkin sketches and verbal concepts; 0% CAD models, 0% schematics, 0% code written. 2 — Rough Drafts (25% Design): Preliminary block diagrams, hand-drawn schematics, unverified parts list, incomplete 3D bounding boxes. 3 — Intermediate Maturity (50% Design): Complete CAD assembly (untested clearances), schematic capture complete, draft firmware architecture mapped out. 4 — Pre-Production (80% Design): Fully detailed 3D CAD ready for 3D print/CNC, routed PCB Gerber files validated with DRC, pinouts locked down. 5 — Fully Engineered Design (100% Production Ready): Complete drawing package: BOM with part numbers, verified manufacturing Gerbers, 2D tolerance drawings, assembly SOP, and flashing scripts ready. | S8: 1 — Extreme Lead Time ($\ge 4\text{ Weeks}$): Custom overseas fabrication, customs clearance delays, or parts with long factory lead times (critical path hazard). 2 — High Lead Time ($3–4\text{ Weeks}$): Standard overseas shipping (e.g., standard AliExpress/international postal surface mail); vulnerable to logistics delays. 3 — Moderate Lead Time ($2\text{ Weeks}$): Express international courier (DHL, FedEx, JLCPCB express) or regional distributors (7–14 days). 4 — Short Lead Time ($1\text{ Week}$): Domestic couriers or express domestic stockists (3–5 business days). 5 — Immediate / Next-Day ($\le 1–2\text{ Days}$): Shelf stock available locally at retail shops or next-day domestic express delivery. | T8: 1 — Pure Buzzword / Academic Greenwashing: Claims to "save the city," but has zero real data, zero measurable effect, and solves a problem nobody in the municipality actually experiences. 2 — Superficial Correlation: Indirect impact; functions only as an isolated school demo with no realistic way to measure if it prevented damage or saved money. 3 — Localized Proof: Delivers a measurable, verified benefit (e.g., cuts response time by 10 minutes or drops pavement temp on a single test strip), but lacks a model to scale. 4 — District-Level Viability: Clear pathway to protect municipal infrastructure or reduce public losses across multiple roads/alleys during extreme weather. 5 — Systemic City Resilience: Backed by concrete empirical data showing significant reduction in public economic losses, vehicle damage, or human hazard during severe rain or heat. | U8: 1 — Toxic Canal Hazard: Cheap plastic enclosure cracks under UV, or unsealed LiPo batteries leak toxic chemicals and detach into the drainage network as marine litter. 2 — Fragile Disposable Tech: Short operational lifespan; sensors foul or corrode within 2–3 weeks and are left behind by crews because retrieving them is too annoying. 3 — Standard Field Footprint: Requires periodic battery replacement and creates standard electronic scrap, but utilizes basic tethering to prevent total hardware loss. 4 — Low-Impact Enclosure: Solar-trickle or long-life low-power architecture; uses recyclable casing and redundant physical tethers (e.g., dual stainless lanyards). 5 — Fully Circular & Zero Footprint: 100% fail-safe retrieval design; uses non-toxic, non-leaching materials, consumes minimal public water/energy, and leaves zero trace in the city. | V8: 1 — Opaque Black Box: Proprietary or unexplained threshold that cancels dispatch trucks or alters services with zero explanation, risking quiet abandonment of vulnerable neighborhoods. 2 — Ambiguous Logic: Decision rules are buried in messy heuristic code; field operators cannot explain to a citizen why an alert was triggered or suppressed. 3 — Documented Internal Rules: Logic is documented on paper for engineers, but has no public audit trail or clear appeal mechanism if the sensor misreads. 4 — Open Empirical Standards: Decisions are driven by transparent physical equations (e.g., verified dh/dt thresholds) applied equally across all city zones. 5 — 100% Auditable & Equitable: Full tamper-evident digital audit trail; open logic accessible to city officials and citizens, guaranteeing equal public protection regardless of district wealth. | W8: เกณฑ์รวม: >=80 ผ่านสูง, >=60 มีเงื่อนไข, <60 เสี่ยงสูง | หากมีข้อใดได้ 1 = VETOED ตกเกณฑ์ทันที
A9: คะแนนที่ได้รับ (ASSIGNED SCORE: 1, 2, 3, 4, 5 STRICT INTEGER) | B9: 3 | C9: 4 | D9: 3 | E9: 3 | F9: 3 | G9: 4 | H9: 4 | I9: 3 | J9: 3 | K9: 4 | L9: 3 | M9: 3 | N9: 4 | O9: 3 | P9: 3 | Q9: 3 | R9: 3 | S9: 3 | T9: 5 | U9: 5 | V9: 5 | W9: =IF(W10>0, (W11/W10)*20, 0) -> 69.634963
A10: ค่าน้ำหนัก (Weight %) | B10: 0.04 | C10: 0.04 | D10: 0.04 | E10: 0.04 | F10: 0.04 | G10: 0.0667 | H10: 0.0667 | I10: 0.0666 | J10: 0.075 | K10: 0.075 | L10: 0.0333 | M10: 0.0333 | N10: 0.0333 | O10: 0.0333 | P10: 0.0333 | Q10: 0.0334 | R10: 0.075 | S10: 0.075 | T10: 0.0333 | U10: 0.0333 | V10: 0.0334 | W10: =SUM(B10:V10) -> 0.9999
A11: คะแนนถ่วงน้ำหนัก (=Score * Weight) | B11: =B9*B10 -> 0.12 | C11: =C9*C10 -> 0.16 | D11: =D9*D10 -> 0.12 | E11: =E9*E10 -> 0.12 | F11: =F9*F10 -> 0.12 | G11: =G9*G10 -> 0.2668 | H11: =H9*H10 -> 0.2668 | I11: =I9*I10 -> 0.1998 | ... V11: =V9*V10 -> 0.167 | W11: =SUM(B11:V11) -> 3.4814
A12: คำอธิบาย & หลักฐานอ้างอิงจากไฟล์ Intake (Evidence Citation) | B12: อ้างอิง solution-3.md: ต้องออกแบบชุดปากแตรเสียง (Acoustic Horn) สั่งทำพิเศษร่วมกับวงจรปรีแอมป์ขยายสัญญาณและไมโครโฟนความไวสูง (Hybrid / COTS Integration) | C12: ใช้อัลกอริทึม FFT และ Cross-correlation บนโอเพนซอร์ส Python/C++ สามารถตรวจสอบและปรับแก้โค้ดได้เต็มที่ (Open Developer Access) | D12: หัววัดเสียงกันน้ำและทรานสดิวเซอร์เฉพาะทางต้องสั่งซื้อจากตัวแทนจำหน่ายระดับภูมิภาค (Mouser/DigiKey) ใช้เวลาจัดส่งประมาณ 7-14 วัน (Moderate Availability) | E12: อ้างอิงเทคโนโลยี SL-RAT ที่ใช้งานในสหรัฐฯ/อังกฤษ (TRL 8) แต่เวอร์ชันที่ทีมพัฒนาอยู่ในระดับ Alpha Prototype ทดสอบในท่อจำลอง (TRL 5-6) | F12: JK เชี่ยวชาญการประมวลผลสัญญาณและคณิตศาสตร์คลื่นเสียง โดยมี Due เป็นผู้ช่วยพัฒนาฝั่งฮาร์ดแวร์ไมโครโฟน (Primary + Secondary Pair) | G12: ลดค่าใช้จ่ายการขุดลอกท่อระบายน้ำแบบสุ่มของเทศบาล คัดกรองท่อที่ตันจริงได้รวดเร็ว คืนทุนใน 2-3 ปี | H12: ฮาร์ดแวร์ใช้ชิ้นส่วนอิเล็กทรอนิกส์เปิด ซอฟต์แวร์ประมวลผลบนเครื่องคอมพิวเตอร์ทั่วไป ไม่ติดระบบผูกขาด (High Autonomy) | I12: หัวทรานสดิวเซอร์และปรีแอมป์มีราคาสูง สามารถสำรองอะไหล่ได้ประมาณ 50% ของงบประมาณ (Moderate Buffer) | J12: ต้องเปิดฝาท่อระบายน้ำบนถนนสาธารณะ มีความเสี่ยงต่อกฎหมายจราจรและความปลอดภัย ต้องขออนุญาตและมีป้ายเตือน (Conditional / Requires Permit) | K12: สิทธิบัตร SL-RAT คุ้มครองฮาร์ดแวร์เชิงพาณิชย์บางส่วน แต่หลักการคลื่นเสียงสะท้อนในท่อเป็นฟิสิกส์ทั่วไป สามารถพัฒนาอัลกอริทึมเองได้ | L12: เจ้าหน้าที่ต้องนำอุปกรณ์ไปหย่อนลงปากท่อระบายน้ำ 2 จุด ปรับระดับและกดส่งสัญญาณ ใช้เวลาประมาณ 3-5 นาทีต่อบ่อพัก | M12: ปฏิบัติงานใกล้บ่อพักริมถนน เสี่ยงต่ออุบัติเหตุรถเฉี่ยวชนและก๊าซพิษ H2S ต้องมีกรวยจราจรและอุปกรณ์ป้องกันส่วนบุคคล | N12: เจ้าหน้าที่ต้องบันทึกค่าคะแนน 0-10 เพื่อจัดเทียร์คิวล้างท่อ ต้องจัดฝึกอบรมเชิงปฏิบัติการ 1-2 ครั้ง | O12: การปรับจูนอัลกอริทึมคลื่นเสียงจำเป็นต้องทดสอบกับท่อจำลองจริง การพัฒนาซอฟต์แวร์จึงผูกติดกับความพร้อมของแท่นทดสอบฮาร์ดแวร์ | P12: ต้องขออนุญาตใช้พื้นที่ห้องปฏิบัติการเสียงและท่อทดสอบของมหาวิทยาลัยตามเวลาทำการปกติ | Q12: สมาชิกมีพื้นฐานวิชาสัญญาณและระบบ (Signals and Systems) และ Embedded DSP สอดคล้องกับโครงงานที่เคยเรียน | R12: แบบ 3D CAD ของชุดปากแตรและวงจรปรีแอมป์อยู่ในระดับ 50% Design ยังต้องทดสอบ Clearance และการสะท้อนของเสียงจริง | S12: ทรานสดิวเซอร์ความถี่เสียงกันน้ำเฉพาะทางต้องสั่งนำเข้าหรือสั่งจากตัวแทนจำหน่าย ใช้ระยะเวลาขนส่งประมาณ 1-2 สัปดาห์ | T12: เพิ่มประสิทธิภาพการบำรุงรักษาท่อระบายน้ำทั้งระบบ ป้องกันท่อตันก่อนเกิดฝนตกหนัก เสริมความทนทานต่อภัยพิบัติน้ำท่วมเมือง (SDG 11.5) | U12: ลดการใช้น้ำแรงดันสูง (Water Jetting) และสารเคมีล้างท่อแบบสุ่ม ประหยัดทรัพยากรน้ำสะอาดได้มหาศาล (SDG 6.4 และ SDG 12.4) | V12: ข้อมูลผลการตรวจวัดระดับความสะอาดท่อ (เทียร์ 0-10) จัดเก็บเป็น Digital Map เปิดเผยให้ประชาชนติดตามความคืบหน้าการล้างท่อได้ (SDG 16.6) | W12: =IF(MIN(B9:V9)=1, "VETOED / ตกเกณฑ์ข้อบังคับวิกฤต (คะแนนระดับ 1)", IF(W9>=80, "ผ่านเกณฑ์ระดับสูง (HIGHLY VIABLE)", IF(W9>=60, "ผ่านแบบมีเงื่อนไข (CONDITIONALLY VIABLE)", "ความเสี่ยงสูง (HIGH RISK)"))) -> ผ่านแบบมีเงื่อนไข (CONDITIONALLY VIABLE)
A13: แผนลดขอบเขตงาน & มาตรการลดความเสี่ยง (De-scoping Action) | B13: ขึ้นรูปปากแตรด้วย 3D Printing วัสดุ PETG พร้อมซีลยางกันน้ำแทนการหล่อโลหะ | C13: เขียนอัลกอริทึม Cross-correlation และ FFT บน Python ด้วยตนเอง | D13: สั่งซื้อทรานสดิวเซอร์ความถี่เสียงจากร้านค้าออนไลน์ล่วงหน้า | E13: ทดสอบระบบในท่อ PVC จำลองในมหาวิทยาลัยก่อนออกพื้นที่จริง | F13: จัดทำคู่มือสถาปัตยกรรมการประมวลผลสัญญาณและวงจรไฟฟ้าให้ Fifa และ Kin ร่วมทดสอบได้ | G13: นำเสนอรายงานการประหยัดงบประมาณการขุดลอกท่อเพื่อขอรับการสนับสนุนจากหน่วยงานรัฐ | H13: ใช้วงจรขยายเสียงมาตรฐาน Class-D ที่หาอะไหล่ได้ง่ายในท้องตลาด | I13: จัดซื้อหัววัดเสียงและไมโครโฟนสำรองอย่างละ 1 ชุด | J13: ทำหนังสือขออนุญาตทดสอบในพื้นที่ปิดของมหาวิทยาลัยก่อนออกสู่ถนนสาธารณะ | K13: เขียนอัลกอริทึม Cross-correlation และ FFT บน Python ด้วยตนเอง | L13: ออกแบบกลไกขายึดขอบบ่อพักแบบแคลมป์สปริงเพื่อลดเวลาติดตั้งเหลือ 2 นาที | M13: กำหนดระเบียบความปลอดภัยบังคับวางกรวยจราจรรอบจุดทดสอบอย่างน้อย 5 เมตรและสวมเสื้อสะท้อนแสง | N13: ทำแอปพลิเคชันบนมือถือแสดงผลเทียร์ 0-10 พร้อมคำแนะนำการปฏิบัติงานแบบอัตโนมัติ | O13: สร้างชุดท่อ PVC จำลองในห้องทดลองเพื่อใช้ทดสอบอัลกอริทึมล่วงหน้า | P13: ทำเรื่องขอเข้าใช้พื้นที่ทดสอบล่วงหน้ากับหัวหน้าห้องปฏิบัติการ | Q13: จัดเซสชันถ่ายทอดความรู้ด้าน DSP ภายในทีมเพื่อกระจายทักษะ | R13: เร่งสรุปแบบ 3D CAD สำหรับพิมพ์ชิ้นงานภายในสัปดาห์ที่ 6 | S13: สั่งซื้อทรานสดิวเซอร์จากร้านค้าออนไลน์ตั้งแต่สัปดาห์แรกของโครงการ | T13: จัดทำแผนที่ความสะอาดท่อเผยแพร่ในรายงานประจำปีของเขต | U13: คำนวณปริมาตรน้ำสะอาดที่ประหยัดได้จากการลดรอบการฉีดล้างท่อที่ไม่จำเป็น | V13: เชื่อมโยงข้อมูลผลคะแนนเทียร์ท่อเข้าสู่ระบบเปิดของเมือง | W13: ปฏิบัติตามแผนลดขอบเขตงาน (De-scoping Advisory)
A15: ตารางสรุปคะแนนแยกตามมิติ TELOS+S (Pillar Score Breakdown)
A16: มิติการประเมิน (TELOS+S Pillar) | B16: สัดส่วนน้ำหนัก (Weight %) | C16: คะแนนเต็มมิติ (Max Points) | D16: คะแนนที่ได้รับจริง (Earned Points) | E16: คะแนนเฉลี่ย (Score 1-5) | F16: ระดับความพร้อม (Readiness Level)
A17: T : ด้านเทคโนโลยีและวิศวกรรม (Technical) | B17: 0.2 | C17: 20 | D17: =SUM(B11:F11)*20 -> 12.8 | E17: =IF(C17>0, (D17/C17)*5, 0) -> 3.2 | F17: =IF(D17>=16, "พร้อมระดับสูง (High)", IF(D17>=12, "ปานกลาง (Medium)", "เสี่ยงวิกฤต (Critical)")) -> ปานกลาง (Medium)
A18: E : ด้านเศรษฐศาสตร์และความคุ้มค่า (Economic) | B18: 0.2 | C18: 20 | D18: =SUM(G11:I11)*20 -> 14.668 | E18: =IF(C18>0, (D18/C18)*5, 0) -> 3.667 | F18: =IF(D18>=16, "พร้อมระดับสูง (High)", IF(D18>=12, "ปานกลาง (Medium)", "เสี่ยงวิกฤต (Critical)")) -> ปานกลาง (Medium)
A19: L : ด้านกฎหมาย ระเบียบ และภาคประชาชน (Legal & Outreach) | B19: 0.15 | C19: 15 | D19: =SUM(J11:K11)*20 -> 10.5 | E19: =IF(C19>0, (D19/C19)*5, 0) -> 3.5 | F19: =IF(D19>=12, "พร้อมระดับสูง (High)", IF(D19>=9, "ปานกลาง (Medium)", "เสี่ยงวิกฤต (Critical)")) -> ปานกลาง (Medium)
A20: O : ด้านการปฏิบัติการและหน้างาน (Operational) | B20: 0.2 | C20: 20 | D20: =SUM(L11:Q11)*20 -> 12.66 | E20: =IF(C20>0, (D20/C20)*5, 0) -> 3.165 | F20: =IF(D20>=16, "พร้อมระดับสูง (High)", IF(D20>=12, "ปานกลาง (Medium)", "เสี่ยงวิกฤต (Critical)")) -> ปานกลาง (Medium)
A21: S : ด้านแผนงานและเวลาส่งมอบ (Schedule) | B21: 0.15 | C21: 15 | D21: =SUM(R11:S11)*20 -> 9 | E21: =IF(C21>0, (D21/C21)*5, 0) -> 3 | F21: =IF(D21>=12, "พร้อมระดับสูง (High)", IF(D21>=9, "ปานกลาง (Medium)", "เสี่ยงวิกฤต (Critical)")) -> ปานกลาง (Medium)
A22: +S : ด้านความยั่งยืนและสิ่งแวดล้อม (Sustainability / SDG) | B22: 0.1 | C22: 10 | D22: =SUM(T11:V11)*20 -> 10 | E22: =IF(C22>0, (D22/C22)*5, 0) -> 5 | F22: =IF(D22>=8, "พร้อมระดับสูง (High)", IF(D22>=6, "ปานกลาง (Medium)", "เสี่ยงวิกฤต (Critical)")) -> พร้อมระดับสูง (High)
A23: คะแนนรวมทุกมิติ (Total Feasibility Score) | B23: =SUM(B17:B22) -> 1 | C23: =SUM(C17:C22) -> 100 | D23: =SUM(D17:D22) -> 69.628 | E23: =IF(C23>0, (D23/C23)*5, 0) -> 3.4814 | F23: =IF(D23>=80, "ผ่านเกณฑ์ระดับสูง (HIGHLY VIABLE)", IF(D23>=60, "ผ่านแบบมีเงื่อนไข (CONDITIONALLY VIABLE)", "ความเสี่ยงสูง (HIGH RISK)")) -> ผ่านแบบมีเงื่อนไข (CONDITIONALLY VIABLE)
A25: เมทริกซ์ประเมินความเข้ากันได้กับองค์ความรู้ด้านวิศวกรรมหุ่นยนต์ (Robotics Knowledge Compatibility)
A26: * หมายเหตุ: การประเมินส่วนนี้วัดศักยภาพในการประยุกต์ใช้องค์ความรู้ด้านวิศวกรรมหุ่นยนต์ (Perception, Control, Actuation, Mechatronics) เต็ม 10 คะแนน | เป็นเอกเทศ ไม่นับรวมในคะแนน TELOS 100 คะแนน
A27: มิติการประเมิน (Robotics Dimension) | B27: คะแนนศักยภาพ (/10) | C27: แกน Perception & Sensing (การรับรู้) | D27: แกน Control & Algorithms (การควบคุม) | E27: แกน Actuation & Mechanisms (กลไก) | F27: บทวิเคราะห์เชิงวิศวกรรมหุ่นยนต์ (FIBO Alignment Rationale)
A28: ศักยภาพการประยุกต์ใช้องค์ความรู้หุ่นยนต์และระบบอัตโนมัติ | B28: 8.5 | C28: ระบบตรวจวัดคลื่นเสียงเชิงรุก (Active Acoustic Sensing): ทรานสดิวเซอร์ส่งคลื่นเสียงความถี่กวาด (Chirp/Multitone Sound Pulse) และไมโครโฟนรับเสียงสะท้อนเพื่อวิเคราะห์การสูญเสียพลังงาน (Acoustic Attenuation) | D28: การประมวลผลสัญญาณดิจิทัล (Digital Signal Processing - DSP): Fast Fourier Transform (FFT), การคำนวณการตอบสนองความถี่ (Frequency Response Analysis), และการจำแนกรูปแบบการอุดตันด้วย Pattern Matching | E28: กลไกการปรับระยะและการส่งคลื่นเสียง: ปากแตรสะท้อนเสียงแบบปรับมุม (Acoustic Horn), กลไกปรับระดับความลึกหย่อนลงปากท่อ, และโครงสร้างซีลกันเสียงสะท้อนภายนอก | F28: มีความเข้ากันได้สูงมากกับศาสตร์วิศวกรรมหุ่นยนต์ในแกน Sensing & Signal Processing ระดับ Transducer และทฤษฎีคลื่นเสียง มีการต่อยอดสู่หุ่นยนต์ตรวจสอบท่อระบายน้ำอัตโนมัติ (Pipe Inspection Robot) ได้โดยตรง คะแนนจึงอยู่ที่ 8.5

Sheet Solution-4
A1: เมทริกซ์ประเมินความเป็นไปได้เชิงระบบ TELOS+S: Underground Flow Telemetry & Predictive Maintenance (Jakarta Case)
A2: ระบบคะแนนจำนวนเต็มเด็ดขาด: 1, 2, 3, 4, 5 เท่านั้น (ไม่มีจุดทศนิยม / ไม่มี 0.5) | โครงสร้างแบบ Transposed แนวนอน
A4: รหัสคำถาม (Question Code) | B4: T-01 | C4: T-02 | D4: T-03 | E4: T-04 | F4: T-05 | G4: E-01 | H4: E-02 | I4: E-03 | J4: L-01 | K4: L-02 | L4: O-01 | M4: O-02 | N4: O-03 | O4: O-04 | P4: O-05 | Q4: O-06 | R4: S-01 | S4: S-02 | T4: SDG-01 | U4: SDG-02 | V4: SDG-03 | W4: สรุปภาพรวม (SUMMARY)
A5: มิติการประเมิน (TELOS+S Pillar) | B5: ด้านเทคโนโลยีและวิศวกรรม (Technical Feasibility) | C5: ด้านเทคโนโลยีและวิศวกรรม (Technical Feasibility) | D5: ด้านเทคโนโลยีและวิศวกรรม (Technical Feasibility) | E5: ด้านเทคโนโลยีและวิศวกรรม (Technical Feasibility) | F5: ด้านเทคโนโลยีและวิศวกรรม (Technical Feasibility) | G5: ด้านเศรษฐศาสตร์ (Economic Feasibility) | H5: ด้านเศรษฐศาสตร์ (Economic Feasibility) | I5: ด้านเศรษฐศาสตร์ (Economic Feasibility) | J5: ด้านกฎหมายและสถาบัน (Legal & Institutional Feasibility) | K5: ด้านกฎหมายและสถาบัน (Legal & Institutional Feasibility) | L5: ด้านการปฏิบัติการ (Operational Feasibility) | M5: ด้านการปฏิบัติการ (Operational Feasibility) | N5: ด้านการปฏิบัติการ (Operational Feasibility) | O5: ด้านการปฏิบัติการ (Operational Feasibility) | P5: ด้านการปฏิบัติการ (Operational Feasibility) | Q5: ด้านการปฏิบัติการ (Operational Feasibility) | R5: ด้านแผนงานและเวลา (Schedule Feasibility) | S5: ด้านแผนงานและเวลา (Schedule Feasibility) | T5: +S ด้านความยั่งยืน (Sustainable Feasibility) | U5: +S ด้านความยั่งยืน (Sustainable Feasibility) | V5: +S ด้านความยั่งยืน (Sustainable Feasibility) | W5: ผลรวมทุกมิติ (All Pillars)
A6: คำถามทดสอบความเสี่ยงจริง (Stress-Test Question) | B6: Implementation (Build vs. Buy Burden): ระบบต้องพัฒนาขึ้นเองจากศูนย์ (Custom R&D) หรือสามารถประกอบขึ้นจากโมดูลสำเร็จรูป (COTS Assembly)? | C6: Access (Tech Stack & Ecosystem Permissions): สแตกเทคโนโลยีและสิทธิ์การเข้าถึงระบบ (Permissions & Ecosystem) มีความเปิดกว้างเพียงใดในการตรวจสอบ แก้ไข และพัฒนาต่อยอด? | D6: Supply (Component Procurement & Vendor Availability): ชิ้นส่วนและอุปกรณ์หลักมีห่วงโซ่อุปทานและความพร้อมในการจัดหา (Supply & Vendor Availability) จากผู้จำหน่ายในระดับใด? | E6: Base Performance (Technology Readiness Level - TRL): ระดับความพร้อมของเทคโนโลยี (TRL) ของระบบอยู่ในขั้นใดเมื่อเทียบกับสภาวะแวดล้อมการใช้งานจริงหน้างาน? | F6: Team Compatibility (Manpower & Skill Redundancy): ทักษะของสมาชิกในทีมมีความเข้ากันได้และการกระจายความเชี่ยวชาญสำรอง (Bus Factor & Redundancy) มากน้อยเพียงใด? | G6: ROI (Payback Period / Value Horizon): ระยะเวลาคืนทุนและกรอบเวลาการสร้างผลตอบแทนคุ้มค่า (Payback Horizon) ต่อระบบสาธารณะหรือผู้ใช้งานอยู่ในเกณฑ์ใด? | H6: Dependencies of Component (Vendor Lock-in & Service Autonomy): ระบบมีความเป็นอิสระจากการผูกขาดของผู้ผลิต (Vendor Lock-in) มากน้อยเพียงใด และสามารถซ่อมบำรุงด้วยเครื่องมือเปิดได้เองหรือไม่? | I6: Scrap Margin (Safety Allowance for Blown ICs & Iterations): โครงการมีการจัดสรรงบประมาณสำรองสำหรับชิ้นส่วนทดแทนกรณีเสียหาย (Scrap Margin) และการทดลองซ้ำมากน้อยเพียงใด? | J6: Felony and Civil Law (Regulatory & Public Safety Compliance): ระบบและการติดตั้งมีความสอดคล้องต่อข้อบังคับทางกฎหมายอาญา แพ่ง ระเบียบจราจร และการคุ้มครองข้อมูลส่วนบุคคล (PDPA / Public Safety) หรือไม่? | K6: IP and Licensing: ทรัพย์สินทางปัญญา ซอฟต์แวร์ไลบรารี และสิทธิบัตรที่นำมาใช้ มีความเปิดกว้างและปลอดภาระผูกพันทางการค้าหรือการละเมิดลิขสิทธิ์ (Licensing Freedom) มากน้อยเพียงใด? | L6: User — Implementation (Field Deployment / Setup Friction): ขั้นตอนการติดตั้ง ติดตั้งเครื่องมือ ปรับเทียบศูนย์ (Calibration) และเตรียมพร้อมใช้งานหน้างานจริงโดยผู้ปฏิบัติงาน มีความยุ่งยากหรือกินเวลาเพียงใด? | M6: User — Customer / Public Safety & Failsafes: ความปลอดภัยเชิงกลและไฟฟ้าต่อเจ้าหน้าที่ผู้ปฏิบัติงานและประชาชนในพื้นที่ (Intrinsic Safety & Failsafes) มีระบบป้องกันในระดับใด? | N6: User — Behavior & Workflow Disruption: ระบบสร้างความเปลี่ยนแปลงหรือรบกวนต่อขั้นตอนการทำงานปกติ (Standard Operating Procedure - SOP) ของผู้ใช้งานเดิมมากน้อยเพียงใด? | O6: Developer — Task Dependency (Critical Path Architecture): โครงสร้างสถาปัตยกรรมของระบบและการแบ่งส่วนงานระหว่างฮาร์ดแวร์ ซอฟต์แวร์ และกลไก มีการแยกส่วน (Decoupling) เพื่อให้พัฒนาคู่ขนานได้มากน้อยเพียงใด? | P6: Developer — Contribution Dependency (Bureaucratic & Lab Gatekeeping): การเข้าถึงเครื่องมือในห้องปฏิบัติการ การอนุมัติงบประมาณ และกระบวนการทางธุรการ (Lab Access & Purchasing Bureaucracy) มีอุปสรรคขัดขวางความคล่องตัวเพียงใด? | Q6: Developer — Task & Skill Compatibility: ความเข้ากันได้ระหว่างทักษะเดิมของทีมกับเทคโนโลยีสแตกของระบบ (Task & Skill Compatibility: 'Water and Oil' vs. 'Oil and Engine') อยู่ในระดับใด? | R6: Production Time (Engineering Design Maturity by Milestone): ความพร้อมของแบบวิศวกรรม (3D CAD, Schematics, PCB Gerbers, Firmware Architecture, BOM) อยู่ในระดับความสมบูรณ์ใดเทียบกับหมุดหมายการผลิตจริง? | S6: Shipping (Component Procurement Lead Time): ระยะเวลาในการจัดหาและขนส่งชิ้นส่วน อุปกรณ์ และเซนเซอร์ (Procurement Lead Time) อยู่ในกรอบเวลาที่ปลอดภัยต่อกำหนดส่งมอบงานหรือไม่? | T6: Real Public Impact vs. Academic Greenwashing (SDG 11.5 / 13.1): Is this genuinely reducing flood/heat losses for the public, or is it just fluff for a presentation slide? | U6: Environmental Footprint & E-Waste ("Do No Harm" — SDG 6.3 / 12.4): Will this hardware end up as toxic e-waste rotting at the bottom of a canal or washing down the river? | V6: Decision Transparency & Public Fairness (SDG 10.2 / 16.6): Can an officer or citizen verify why the system made its call, or is it an unaccountable black box? | W6: ประเมินคำถามทั้งสิ้น 21 ข้อ
A7: เหตุผลในการถาม & โหมดความล้มเหลวที่เฝ้าระวัง (Rationale) | B7: วัดภาระงานสร้างและการวิจัยพัฒนา (Build vs. Buy Burden) ยิ่งสร้างเองจากศูนย์มาก ยิ่งเสี่ยงต่อความล่าช้าและความล้มเหลว | C7: ตรวจสอบอุปสรรคด้านสิทธิ์การเข้าถึง (Access Barriers) เช่น NDA, Closed-source blobs, หรือข้อจำกัดด้านใบอนุญาตที่ขัดขวางการแก้บั๊ก | D7: ตรวจสอบความเสี่ยงด้านห่วงโซ่อุปทาน (Single-source, EOL, Overseas backlog) ที่อาจทำให้โครงการหยุดชะงักเมื่อชิ้นส่วนขาดตลาด | E7: ประเมินความเสถียรของเทคโนโลยีตามมาตรฐาน TRL จากระดับแล็บทดลอง (Lab model) ไปจนถึงระดับใช้งานจริงในสภาวะวิกฤต (Field-proven) | F7: ป้องกัน Single Point of Failure (SPOF) ด้านบุคคล หากมีสมาชิกคนใดคนหนึ่งไม่สามารถปฏิบัติงานได้ ระบบต้องยังสามารถพัฒนาและแก้ไขต่อได้ | G7: วัดความคุ้มค่าทางเศรษฐศาสตร์และการคืนทุนจากการลดความสูญเสีย ค่าแรง หรือค่าเชื้อเพลิง | H7: ตรวจสอบภาระค่าใช้จ่ายแฝงระยะยาว (Recurring Cloud/Licensing Fees) และการพึ่งพาผู้ผลิตรายเดียว | I7: ตรวจสอบงบสำรองสำหรับชิ้นส่วนเสียหาย (Scrap Budget Rule) ป้องกันงานสะดุดเมื่อเกิดชิปไหม้หรือฮาร์ดแวร์หัก | J7: ตรวจสอบความเสี่ยงทางกฎหมายสาธารณะ (พ.ร.บ. จราจร, PDPA, กฎหมายสิ่งแวดล้อม และระเบียบทางหลวง) | K7: ตรวจสอบข้อจำกัดด้านสิทธิ์ซอฟต์แวร์และฮาร์ดแวร์ ป้องกันการติดไวรัสไลเซนส์ (Copyleft GPLv3) หรือการละเมิดสิทธิบัตร | L7: ประเมินความสะดวกในการติดตั้งหน้างาน (Setup Friction) เพื่อป้องกันไม่ให้อุปกรณ์ถูกละเลยเนื่องจากการตั้งค่ายุ่งยาก | M7: ประเมินมาตรการความปลอดภัยและกลไกป้องกันอันตราย (Hazard Failsafes) เช่น สวิตช์ฉุกเฉิน E-stop, ฟิวส์, และการออกแบบป้องกันแรงดันสูง | N7: ประเมินแรงต้านทานจากผู้ใช้งาน (Workflow Friction) และความราบรื่นในการเชื่อมต่อเข้ากับระบบการทำงานเดิมของเจ้าหน้าที่ | O7: ตรวจสอบคอขวดบนสายงานวิกฤต (Critical Path Bottleneck) ป้องกันไม่ให้ทีมซอฟต์แวร์ต้องหยุดรอแผ่นวงจรพิมพ์หรือกลไกที่ยังไม่เสร็จ | P7: ประเมินอุปสรรคด้านการบริหารและเครื่องมือ (Institutional Gatekeeping) เช่น คิวรอเครื่องจักร การล็อกแล็บ หรือขั้นตอนเบิกจ่ายงบประมาณที่ล่าช้า | Q7: ตรวจสอบความสอดคล้องระหว่างทักษะที่ทีมมีอยู่จริงกับเทคโนโลยีที่เลือกใช้ เพื่อป้องกัน Learning Curve ที่สูงเกินไปจนงานล้มเหลว | R7: ประเมินความพร้อมของพิมพ์เขียวการผลิต (Design Maturity Package) ก่อนเริ่มสั่งผลิตจริง เพื่อป้องกันการรื้อแก้แบบกลางคัน | S7: ตรวจสอบห่วงโซ่อุปทาน (Supply Chain Lead Time) ชิ้นส่วนที่ต้องรอส่งจากต่างประเทศเกิน 3 สัปดาห์ถือเป็นความเสี่ยงต่อวิกฤตสัปดาห์สอบและกำหนดส่งมอบ | T7: Your team's 1 vs. 5 premise: "Pure buzzword bullshit to get a grade vs. Actually moves the needle on city infrastructure." | U7: Your team's 1 vs. 5 premise: "Dumping toxic e-waste into public canals vs. Zero-footprint hardware." | V7: Your team's 1 vs. 5 premise: "Black-box algorithm cutting services to poor areas vs. Open, verifiable math." | W7: สังเคราะห์จาก AI Agents Group 2
A8: เกณฑ์การให้คะแนน (Scoring Rubric Definition: ระดับ 1, 2, 3, 4, 5 ครบทุกระดับ) | B8: 1 — Build from Scratch: 100% custom R&D required (custom mechanism, custom PCB, raw algorithm derivation); no reference designs available. 2 — Heavy Customization: Core components exist, but requires extensive custom adaptation, structural machining, and custom wrapper code. 3 — Hybrid / COTS Integration: Standard COTS modules (e.g., standard dev board + breakout sensors) assembled with custom brackets and intermediate wiring. 4 — Modular COTS Assembly: Pre-engineered building blocks with standard mounting and standard communication buses (e.g., Din-rail modules, I2C/CAN shields); minimal custom fabrication. 5 — Commercial Off-the-Shelf (COTS): Buy and use directly out of the box (Plug-and-Play); zero mechanical or electrical fabrication required. | C8: 1 — Strictly Restricted: Proprietary stack under NDA, blocked enterprise firewalls, or unavailable developer licenses. 2 — Limited Access: Closed binary blobs or third-party proprietary software; black-box firmware with zero internal telemetry or source code. 3 — Request-Based Access: Standard educational/evaluation license or public APIs with strict rate limits; requires account verification or approval delays. 4 — Open Developer Access: Free public SDKs, full documentation, and open developer access, but cannot modify upstream core source code. 5 — Unrestricted Full-Stack Access: Fully open source (permissive license) and open hardware; team has root/admin rights to modify, inspect, and deploy as both user and developer. | D8: 1 — Sole-Source / Obsolete: Single overseas supplier, restricted export control, long backorder, or risk of end-of-life (EOL). 2 — Specialized Vendor: Only 1–2 niche industrial suppliers; requires formal corporate quote/PO process; no consumer retail channels. 3 — Moderate Availability: 2–3 regional distributors (e.g., DigiKey, Mouser, Element14); reliable stock but requires overseas shipping. 4 — Multi-Vendor Local Stock: Readily available from multiple domestic vendors; common industrial or maker components with reliable inventory. 5 — Commodity / Off-the-Shelf: Ubiquitous commodity item sold across multiple local electronics shops and online platforms (delivered in 1–2 days). | E8: 1 — Proof of Concept (TRL 3): Bench breadboard or mathematical model; verified only in simulated/controlled lab conditions. 2 — Functional Breadboard (TRL 4): Integrated components working together in lab; messy wiring, fragile, uncalibrated for harsh environments. 3 — Alpha Prototype (TRL 5–6): Enclosed prototype tested in a relevant simulated environment; occasional crashes, requires human supervisor. 4 — Beta / Field-Proven (TRL 7): Pre-production hardware operating reliably in the actual operating environment under real stress. 5 — Commercial Product (TRL 8–9): Fully certified, production-grade commercial product with documented MTBF and mass field reliability. | F8: 1 — Single Point of Failure (SPOF): Only 1 person has the niche skill (if they get sick, the subsystem halts 100%). 2 — Solo Lead with Minimal Backup: 1 person executes; 1 teammate understands basic concepts but cannot debug code or fix hardware alone. 3 — Primary + Secondary Pair: 1 primary developer and 1 competent secondary backup who can maintain, troubleshoot, and push updates. 4 — Broad Competence: 3+ teammates can actively design, assemble, and debug the subsystem with low ramp-up time. 5 — Full Team Redundancy: All team members are fully proficient; tasks can be swapped across anyone with zero friction or velocity loss. | G8: 1 — Long Payback ($\ge 10\text{ Years}$): High initial CapEx and low recurring savings; economically non-viable for rapid deployment. 2 — Slow Return ($6–9\text{ Years}$): Substantial capital investment with long break-even horizon; requires long-term institutional subsidization. 3 — Moderate Return ($3–5\text{ Years}$): Reasonable public infrastructure payback; offsets costs across multi-year operational cycles. 4 — Fast Return ($2–3\text{ Years}$): Strong operational cost reduction (fuel, labor, scrap); breaks even within normal equipment lifecycle. 5 — Immediate Payback ($\le 1–2\text{ Years}$): Rapid break-even; eliminates major recurring losses within the first operating season. | H8: 1 — Total Vendor Lock-in: Proprietary cloud backend, encrypted telemetry, and proprietary connectors; completely dependent on vendor survival. 2 — High Dependency: Hardware requires vendor-licensed diagnostic tools or annual subscription fees to maintain operation. 3 — Semi-Independent: Core hardware relies on proprietary firmware, but allows open API export and standard electrical interfaces. 4 — High Autonomy: Uses standard open communication protocols (e.g., Modbus, MQTT, CAN); parts can be serviced using generic tools. 5 — Complete Independence: 100% open architecture; hardware is interchangeable with generic substitutes; self-serviceable by any engineer. | I8: 1 — Zero Buffer (0%): Exactly 1x BOM purchased; any fried chip, cracked bracket, or wiring mistake kills the project. 2 — Fragile Buffer (20–30%): Spares only for passive components (resistors, connectors); no backup microcontrollers or expensive sensors. 3 — Moderate Buffer (50%): Spares for all critical passive parts and 1 spare for the primary controller board. 4 — High Buffer (80%): Spares for nearly every active component and sensor; can sustain multiple prototype burn-ins. 5 — Full Redundancy ($\ge 100\%$): Complete 2x BOM budget on hand; can build two complete working units simultaneously. | J8: 1 — Severe Violation / No Privilege: Direct breach of statutory law (e.g., unconsented public surveillance/PDPA, hazardous road blockage, RF jammer). 2 — High Legal Exposure: Ambiguous legal zone; high risk of civic complaints or traffic disruption; requires complex technical waivers. 3 — Conditional / Requires Permit: Allowed under explicit written approval, official agency MoU, or municipal permit (e.g., BMA/Highway dept permit). 4 — Low Legal Friction: Operates within standard public engineering exemptions; simple standard notification/safety compliance needed. 5 — 100% Compliant / Free Domain: Completely exempt from statutory licensing; zero public safety risk, zero personal data (Zero PII), fully unrestricted. | K8: 1 — Closed / Commercial Barrier: Proprietary commercial license; cannot compile, flash, or operate without paying expensive commercial seat licenses. 2 — Ambiguous / Gray IP: Unclear licensing terms or unlicensed GitHub repos; risk of copyright strike or IP dispute upon public demonstration. 3 — Restrictive Open Source (Copyleft): Permitted for educational use, but viral licenses (e.g., GPLv3) force your entire codebase to be made public if distributed. 4 — Permissive Open Source: Open source with minimal conditions (e.g., LGPL, CC-BY); allows proprietary wrapping with simple attribution. 5 — Completely Permissive / Public Domain: Permissive open source (MIT, Apache 2.0, BSD) or Public Domain; unrestricted freedom to commercialize, modify, and contribute. | L8: 1 — Laborious Recalibration: Requires multi-point manual physical zeroing, chemical calibration, or oscilloscope tuning before every run. 2 — Complex Setup: Requires trained technician 20–30 minutes to adjust potentiometers, align brackets, or enter configuration commands. 3 — Moderate Field Setup: Simple 5-minute calibration procedure (e.g., tare button or basic mobile app zeroing) performed by non-engineers. 4 — Minimal Setup: Fast clamp-on mounting with automated self-calibration on power-up; ready in $< 1\text{ minute}$. 5 — True Plug and Go: Pure plug-and-play; zero calibration required, zero buttons; power on and immediately operational. | M8: 1 — Critical Hazard: Failure can directly cause electrocution, fire, traffic crashes, chemical exposure, or confined-space asphyxiation. 2 — High Risk / Manual Oversight: High mechanical/electrical hazard requiring constant operator vigilance and full PPE. 3 — Moderate Safety: Protected by passive mechanical guards, fuses, and warning labels; requires basic safety precautions. 4 — High Safety & Interlocks: Active software limits, hardware thermal shutoffs, and reverse polarity protection; minimal hazard on failure. 5 — Inherently Safe & Redundant: Failsafe by physics (cannot store lethal energy); isolated, dual-rated enclosures, redundant E-stops, zero injury risk. | N8: 1 — Disruptive Overhaul: Forces operators to abandon existing SOPs, adds 5+ extra tedious forms/steps, and faces fierce institutional union/worker resistance. 2 — Significant Friction: Adds notable extra documentation or redundant verification steps; operators will actively look for ways to bypass it. 3 — Moderate Adaptation: Modifies daily routine slightly; requires 1–2 training workshops, but delivers clear convenience trade-offs. 4 — Low Friction: Integrates into existing tools (e.g., sends automated alerts to existing LINE/Telegram or ticketing dashboard); minimal change in habits. 5 — Transparent / Seamless Integration: Zero workflow disruption; runs invisibly in background and automates existing manual paperwork without operator intervention. | O8: 1 — Strictly Sequential (Linear): A depends on B depends on C; if the PCB fab is delayed, software and testing halt 100%. 2 — Bottlenecked Pipelines: Major subsystems are tightly coupled; frequent integration stalls waiting for hardware bench access. 3 — Semi-Decoupled: Hardware and software teams can work independently for 1–2 weeks using rough mockups before needing physical integration. 4 — Modular Parallelism: Clear API/interface boundaries; software builds against mock data/simulators while hardware is routed; integration takes $< 2\text{ days}$. 5 — Fully Parallel Architecture: Microservices/modular nodes with standard contracts; mechanical, electrical, and firmware develop, simulate, and unit-test completely in parallel. | P8: 1 — Heavy Gatekeeping: Blocked by supervisor approvals, locked lab cabinets, NDA signatures, purchasing bureaucracy, and restricted git branches. 2 — Moderate Bureaucracy: Requires departmental request forms, tool booking queues, and waiting 3–5 days for administrative sign-offs. 3 — Standard Campus Access: Workable access during university open hours; minor approval delays for equipment or lab keys. 4 — High Autonomy: Team has full repository write access, open 24/7 lab entry, and pre-approved discretionary debit cards/stipends for rapid purchases. 5 — Frictionless Contribution: Complete autonomy; decentralized cloud CI/CD, local prototyping tools at home/bench, zero administrative blockers. | Q8: 1 — Complete Mismatch ("Water and Oil"): Team has zero foundation in the stack (e.g., pure mechanical students forced to train deep neural nets in C++ from scratch). 2 — Steep Learning Curve: High theoretical knowledge, but zero production hands-on experience; debugging basic syntax/wiring stalls progress. 3 — Adjacent Competence: Strong mastery in related tools (e.g., proficient in Arduino/ESP32 migrating to STM32, or SolidWorks migrating to Fusion360); manageable 1-week curve. 4 — Proven Experience: Team has built similar subsystems in past semester coursework or competition robots; rapid ramp-up. 5 — Perfect Synergy ("Oil and Engine"): Complete domain mastery; team members have built this exact architecture multiple times with verified libraries and muscle memory. | R8: 1 — Concept Only (0% Design): Napkin sketches and verbal concepts; 0% CAD models, 0% schematics, 0% code written. 2 — Rough Drafts (25% Design): Preliminary block diagrams, hand-drawn schematics, unverified parts list, incomplete 3D bounding boxes. 3 — Intermediate Maturity (50% Design): Complete CAD assembly (untested clearances), schematic capture complete, draft firmware architecture mapped out. 4 — Pre-Production (80% Design): Fully detailed 3D CAD ready for 3D print/CNC, routed PCB Gerber files validated with DRC, pinouts locked down. 5 — Fully Engineered Design (100% Production Ready): Complete drawing package: BOM with part numbers, verified manufacturing Gerbers, 2D tolerance drawings, assembly SOP, and flashing scripts ready. | S8: 1 — Extreme Lead Time ($\ge 4\text{ Weeks}$): Custom overseas fabrication, customs clearance delays, or parts with long factory lead times (critical path hazard). 2 — High Lead Time ($3–4\text{ Weeks}$): Standard overseas shipping (e.g., standard AliExpress/international postal surface mail); vulnerable to logistics delays. 3 — Moderate Lead Time ($2\text{ Weeks}$): Express international courier (DHL, FedEx, JLCPCB express) or regional distributors (7–14 days). 4 — Short Lead Time ($1\text{ Week}$): Domestic couriers or express domestic stockists (3–5 business days). 5 — Immediate / Next-Day ($\le 1–2\text{ Days}$): Shelf stock available locally at retail shops or next-day domestic express delivery. | T8: 1 — Pure Buzzword / Academic Greenwashing: Claims to "save the city," but has zero real data, zero measurable effect, and solves a problem nobody in the municipality actually experiences. 2 — Superficial Correlation: Indirect impact; functions only as an isolated school demo with no realistic way to measure if it prevented damage or saved money. 3 — Localized Proof: Delivers a measurable, verified benefit (e.g., cuts response time by 10 minutes or drops pavement temp on a single test strip), but lacks a model to scale. 4 — District-Level Viability: Clear pathway to protect municipal infrastructure or reduce public losses across multiple roads/alleys during extreme weather. 5 — Systemic City Resilience: Backed by concrete empirical data showing significant reduction in public economic losses, vehicle damage, or human hazard during severe rain or heat. | U8: 1 — Toxic Canal Hazard: Cheap plastic enclosure cracks under UV, or unsealed LiPo batteries leak toxic chemicals and detach into the drainage network as marine litter. 2 — Fragile Disposable Tech: Short operational lifespan; sensors foul or corrode within 2–3 weeks and are left behind by crews because retrieving them is too annoying. 3 — Standard Field Footprint: Requires periodic battery replacement and creates standard electronic scrap, but utilizes basic tethering to prevent total hardware loss. 4 — Low-Impact Enclosure: Solar-trickle or long-life low-power architecture; uses recyclable casing and redundant physical tethers (e.g., dual stainless lanyards). 5 — Fully Circular & Zero Footprint: 100% fail-safe retrieval design; uses non-toxic, non-leaching materials, consumes minimal public water/energy, and leaves zero trace in the city. | V8: 1 — Opaque Black Box: Proprietary or unexplained threshold that cancels dispatch trucks or alters services with zero explanation, risking quiet abandonment of vulnerable neighborhoods. 2 — Ambiguous Logic: Decision rules are buried in messy heuristic code; field operators cannot explain to a citizen why an alert was triggered or suppressed. 3 — Documented Internal Rules: Logic is documented on paper for engineers, but has no public audit trail or clear appeal mechanism if the sensor misreads. 4 — Open Empirical Standards: Decisions are driven by transparent physical equations (e.g., verified dh/dt thresholds) applied equally across all city zones. 5 — 100% Auditable & Equitable: Full tamper-evident digital audit trail; open logic accessible to city officials and citizens, guaranteeing equal public protection regardless of district wealth. | W8: เกณฑ์รวม: >=80 ผ่านสูง, >=60 มีเงื่อนไข, <60 เสี่ยงสูง | หากมีข้อใดได้ 1 = VETOED ตกเกณฑ์ทันที
A9: คะแนนที่ได้รับ (ASSIGNED SCORE: 1, 2, 3, 4, 5 STRICT INTEGER) | B9: 3 | C9: 4 | D9: 3 | E9: 3 | F9: 2 | G9: 3 | H9: 4 | I9: 3 | J9: 4 | K9: 4 | L9: 3 | M9: 2 | N9: 4 | O9: 3 | P9: 2 | Q9: 2 | R9: 3 | S9: 3 | T9: 5 | U9: 4 | V9: 5 | W9: =IF(W10>0, (W11/W10)*20, 0) -> 66.334633
A10: ค่าน้ำหนัก (Weight %) | B10: 0.04 | C10: 0.04 | D10: 0.04 | E10: 0.04 | F10: 0.04 | G10: 0.0667 | H10: 0.0667 | I10: 0.0666 | J10: 0.075 | K10: 0.075 | L10: 0.0333 | M10: 0.0333 | N10: 0.0333 | O10: 0.0333 | P10: 0.0333 | Q10: 0.0334 | R10: 0.075 | S10: 0.075 | T10: 0.0333 | U10: 0.0333 | V10: 0.0334 | W10: =SUM(B10:V10) -> 0.9999
A11: คะแนนถ่วงน้ำหนัก (=Score * Weight) | B11: =B9*B10 -> 0.12 | C11: =C9*C10 -> 0.16 | D11: =D9*D10 -> 0.12 | E11: =E9*E10 -> 0.12 | F11: =F9*F10 -> 0.08 | G11: =G9*G10 -> 0.2001 | H11: =H9*H10 -> 0.2668 | I11: =I9*I10 -> 0.1998 | ... V11: =V9*V10 -> 0.167 | W11: =SUM(B11:V11) -> 3.3164
A12: คำอธิบาย & หลักฐานอ้างอิงจากไฟล์ Intake (Evidence Citation) | B12: อ้างอิง solution-4.md: ประกอบโมดูล LoRaWAN และเซนเซอร์ระดับน้ำ/ความเร็วการไหลเข้ากับกล่องกันน้ำ IP68 (Hybrid / COTS Integration) | C12: ใช้เครือข่าย LoRaWAN คลื่นความถี่สาธารณะ 920-925 MHz ตามประกาศ กสทช. ซอฟต์แวร์ฝั่งโหนดและเกตเวย์เป็นโอเพนซอร์ส (Open Developer Access) | D12: เซนเซอร์วัดระดับน้ำทนกรดและโมดูลสื่อสารระยะไกลต้องสั่งจากตัวแทนจำหน่ายเฉพาะทาง ใช้เวลาขนส่ง 2 สัปดาห์ (Moderate Availability) | E12: อ้างอิงโครงการโทรมาตรท่อระบายน้ำในจาการ์ตา (TRL 7) ส่วนโครงการทดลองของทีมอยู่ในระดับ Alpha Prototype (TRL 5-6) | F12: ต้องพึ่งพาผู้เชี่ยวชาญด้าน RF และเคมีวัสดุกันน้ำในท่อเป็นหลัก หากขาดหัวหน้าทีมงานอาจล่าช้า (Solo Lead with Minimal Backup) | G12: ช่วยลดความเสียหายจากน้ำท่วมขังใต้ดินและการอุดตันเรื้อรัง จุดคุ้มทุน 3-5 ปีในภาพรวมโครงสร้างพื้นฐานเมือง | H12: ใช้มาตรฐาน LoRaWAN เปิด สามารถเปลี่ยนยี่ห้อเกตเวย์และเซิร์ฟเวอร์เครือข่ายได้อิสระ (High Autonomy) | I12: เซนเซอร์วัดแรงดันน้ำทนกรดมีราคาสูง สำรองได้ประมาณ 50% ของงบประมาณ (Moderate Buffer) | J12: ต้องขออนุญาตติดตั้งอุปกรณ์ถาวรในท่อระบายน้ำของ กทม. และคลื่นวิทยุ LoRaWAN ต้องสอดคล้องกับข้อกำหนด กสทช. (Low Legal Friction) | K12: ใช้สแต็กซอฟต์แวร์โอเพนซอร์ส LoRaWAN และไลบรารีส่งข้อมูลมาตรฐาน MIT/Apache ปลอดปัญหาทรัพย์สินทางปัญญา | L12: การติดตั้งในท่อระบายน้ำต้องใช้เครื่องมือช่างและอุปกรณ์หย่อนสายเคเบิล ใช้เวลาประมาณ 10-15 นาทีต่อจุด | M12: การปฏิบัติงานในพื้นที่อับอากาศใต้ท่อระบายน้ำมีความเสี่ยงต่อก๊าซพิษสะสม ต้องปฏิบัติตามมาตรฐานความปลอดภัยอย่างเคร่งครัด | N12: เชื่อมต่อข้อมูลโทรมาตรเข้าสู่ศูนย์ควบคุมของสำนักระบายน้ำเดิมได้ผ่าน Web API ไม่รบกวนขั้นตอนการทำงานปกติ | O12: การทดสอบสัญญาณวิทยุใต้ฝาท่อต้องทำควบคู่กับฮาร์ดแวร์จริง มีจุดติดขัดรอการทดสอบสนามร่วมกัน | P12: การขออนุญาตลงพื้นที่ติดตั้งในท่อจริงของเมืองมีขั้นตอนทางราชการและต้องรอการอนุมัติ 3-5 วันทำการ | Q12: สมาชิกมีพื้นฐานด้าน IoT และระบบเครือข่าย แต่ต้องเรียนรู้เพิ่มเติมเรื่องการป้องกันการกัดกร่อนของสารเคมีและก๊าซในท่อ | R12: แบบจำลองกล่อง Enclosure และการเดินสายไฟอยู่ในระดับ 50% CAD Assembly กำลังปรับระยะสำหรับแบตเตอรี่ | S12: เซนเซอร์วัดระดับน้ำทนสารเคมีและโมดูลส่งสัญญาณระยะไกลต้องสั่งจากตัวแทนจำหน่าย ใช้ระยะเวลาจัดส่งประมาณ 2 สัปดาห์ | T12: ช่วยเตือนภัยน้ำท่วมใต้ดินล่วงหน้าและระบุจุดเสี่ยงท่อตันตลอด 24 ชม. เสริมโครงสร้างพื้นฐานเมืองที่ทนทานต่อสภาพภูมิอากาศ (SDG 11.5 / 13.1) | U12: ช่วยลดการอุดตันของท่อน้ำเสีย แต่เซนเซอร์ในสภาพแวดล้อมกัดกร่อนอาจมีอายุการใช้งานสั้น ต้องมีระบบรีไซเคิลขยะอิเล็กทรอนิกส์ (SDG 6.3 และ SDG 12.4 ได้ระดับ 4) | V12: แดชบอร์ดเมืองเปิดเผยข้อมูลการระบายน้ำอย่างโปร่งใส ช่วยให้ทุกชุมชนเข้าถึงข้อมูลความเสี่ยงน้ำท่วมอย่างเท่าเทียม (SDG 10.2 / 16.6) | W12: =IF(MIN(B9:V9)=1, "VETOED / ตกเกณฑ์ข้อบังคับวิกฤต (คะแนนระดับ 1)", IF(W9>=80, "ผ่านเกณฑ์ระดับสูง (HIGHLY VIABLE)", IF(W9>=60, "ผ่านแบบมีเงื่อนไข (CONDITIONALLY VIABLE)", "ความเสี่ยงสูง (HIGH RISK)"))) -> ผ่านแบบมีเงื่อนไข (CONDITIONALLY VIABLE)
A13: แผนลดขอบเขตงาน & มาตรการลดความเสี่ยง (De-scoping Action) | B13: เลือกใช้กล่อง Polycarbonate มาตรฐาน IP68 พร้อมเคลือบน้ำยา Conformal Coating ป้องกันไอระเหยกรด | C13: บันทึกขั้นตอนการคอนฟิกโมเด็ม LoRaWAN เพื่อให้เพื่อนในทีมสามารถช่วยตั้งค่าได้ | D13: สั่งซื้อโมดูล LoRaWAN และเซนเซอร์ตั้งแต่เริ่มสัปดาห์แรก | E13: ทดสอบการทะลุผ่านของสัญญาณวิทยุผ่านฝาท่อจำลองในห้องแล็บ | F13: ถ่ายทอดขั้นตอนการคอนฟิก LoRaWAN ให้สมาชิกคนอื่นสามารถตั้งค่าแทนได้ | G13: เลือกพื้นที่นำร่อง 1 จุดวิกฤตเพื่อพิสูจน์ความคุ้มค่าก่อนขยายผล | H13: ติดตั้ง Local Gateway ของทีมเพื่อลดค่าบริการเครือข่ายรายเดือน | I13: สำรองชุดเซนเซอร์และแผงควบคุมไว้ 1 ชุดเพื่อรองรับความเสียหาย | J13: ประสานงานกับอาจารย์ที่ปรึกษาทำหนังสือขออนุญาตติดตั้งอย่างเป็นทางการ | K13: ใช้ไลบรารี MicroPython และโอเพนซอร์สคอมมูนิตี้ | L13: ออกแบบขายึดแบบ Quick-clamp ไม่ต้องเจาะผนังท่อเพื่อลดเวลาติดตั้งหน้างาน | M13: กำหนดมาตรการความปลอดภัย ไม่อนุญาตให้มุดตัวลงท่อ ใช้เครื่องมือหย่อนติดตั้งจากปากท่อด้านบน | N13: ออกแบบแดชบอร์ดให้สรุปรายการจุดท่อที่ต้องล้างแบบเข้าใจง่ายในหน้าเดียว | O13: ทำแบบจำลองท่อคอนกรีตจำลองในสถาบันเพื่อทดสอบการทะลุผ่านของสัญญาณวิทยุ | P13: เตรียมเอกสารขออนุญาตล่วงหน้าตั้งแต่ต้นภาคการศึกษา | Q13: ปรึกษาผู้เชี่ยวชาญด้านวัสดุศาสตร์ในการเลือกใช้ซิลิโคนและวัสดุกันซึม | R13: สรุปแบบกล่อง Enclosure และสั่งพิมพ์ 3D ล่วงหน้าก่อนสัปดาห์ที่ 7 | S13: สั่งซื้อโมดูล LoRaWAN และเซนเซอร์ตั้งแต่เริ่มสัปดาห์ที่ 2 | T13: เชื่อมข้อมูลระดับน้ำเข้ากับระบบเตือนภัยสาธารณะของเทศบาล | U13: ใช้วัสดุเคลือบแผงวงจรที่เป็นมิตรต่อสิ่งแวดล้อมและรีไซเคิลได้ | V13: จัดทำ Open API ให้ภาคประชาสังคมและนักวิจัยนำข้อมูลไปใช้ประโยชน์ | W13: ปฏิบัติตามแผนลดขอบเขตงาน (De-scoping Advisory)
A15: ตารางสรุปคะแนนแยกตามมิติ TELOS+S (Pillar Score Breakdown)
A16: มิติการประเมิน (TELOS+S Pillar) | B16: สัดส่วนน้ำหนัก (Weight %) | C16: คะแนนเต็มมิติ (Max Points) | D16: คะแนนที่ได้รับจริง (Earned Points) | E16: คะแนนเฉลี่ย (Score 1-5) | F16: ระดับความพร้อม (Readiness Level)
A17: T : ด้านเทคโนโลยีและวิศวกรรม (Technical) | B17: 0.2 | C17: 20 | D17: =SUM(B11:F11)*20 -> 12 | E17: =IF(C17>0, (D17/C17)*5, 0) -> 3 | F17: =IF(D17>=16, "พร้อมระดับสูง (High)", IF(D17>=12, "ปานกลาง (Medium)", "เสี่ยงวิกฤต (Critical)")) -> ปานกลาง (Medium)
A18: E : ด้านเศรษฐศาสตร์และความคุ้มค่า (Economic) | B18: 0.2 | C18: 20 | D18: =SUM(G11:I11)*20 -> 13.334 | E18: =IF(C18>0, (D18/C18)*5, 0) -> 3.3335 | F18: =IF(D18>=16, "พร้อมระดับสูง (High)", IF(D18>=12, "ปานกลาง (Medium)", "เสี่ยงวิกฤต (Critical)")) -> ปานกลาง (Medium)
A19: L : ด้านกฎหมาย ระเบียบ และภาคประชาชน (Legal & Outreach) | B19: 0.15 | C19: 15 | D19: =SUM(J11:K11)*20 -> 12 | E19: =IF(C19>0, (D19/C19)*5, 0) -> 4 | F19: =IF(D19>=12, "พร้อมระดับสูง (High)", IF(D19>=9, "ปานกลาง (Medium)", "เสี่ยงวิกฤต (Critical)")) -> พร้อมระดับสูง (High)
A20: O : ด้านการปฏิบัติการและหน้างาน (Operational) | B20: 0.2 | C20: 20 | D20: =SUM(L11:Q11)*20 -> 10.66 | E20: =IF(C20>0, (D20/C20)*5, 0) -> 2.665 | F20: =IF(D20>=16, "พร้อมระดับสูง (High)", IF(D20>=12, "ปานกลาง (Medium)", "เสี่ยงวิกฤต (Critical)")) -> เสี่ยงวิกฤต (Critical)
A21: S : ด้านแผนงานและเวลาส่งมอบ (Schedule) | B21: 0.15 | C21: 15 | D21: =SUM(R11:S11)*20 -> 9 | E21: =IF(C21>0, (D21/C21)*5, 0) -> 3 | F21: =IF(D21>=12, "พร้อมระดับสูง (High)", IF(D21>=9, "ปานกลาง (Medium)", "เสี่ยงวิกฤต (Critical)")) -> ปานกลาง (Medium)
A22: +S : ด้านความยั่งยืนและสิ่งแวดล้อม (Sustainability / SDG) | B22: 0.1 | C22: 10 | D22: =SUM(T11:V11)*20 -> 9.334 | E22: =IF(C22>0, (D22/C22)*5, 0) -> 4.667 | F22: =IF(D22>=8, "พร้อมระดับสูง (High)", IF(D22>=6, "ปานกลาง (Medium)", "เสี่ยงวิกฤต (Critical)")) -> พร้อมระดับสูง (High)
A23: คะแนนรวมทุกมิติ (Total Feasibility Score) | B23: =SUM(B17:B22) -> 1 | C23: =SUM(C17:C22) -> 100 | D23: =SUM(D17:D22) -> 66.328 | E23: =IF(C23>0, (D23/C23)*5, 0) -> 3.3164 | F23: =IF(D23>=80, "ผ่านเกณฑ์ระดับสูง (HIGHLY VIABLE)", IF(D23>=60, "ผ่านแบบมีเงื่อนไข (CONDITIONALLY VIABLE)", "ความเสี่ยงสูง (HIGH RISK)")) -> ผ่านแบบมีเงื่อนไข (CONDITIONALLY VIABLE)
A25: เมทริกซ์ประเมินความเข้ากันได้กับองค์ความรู้ด้านวิศวกรรมหุ่นยนต์ (Robotics Knowledge Compatibility)
A26: * หมายเหตุ: การประเมินส่วนนี้วัดศักยภาพในการประยุกต์ใช้องค์ความรู้ด้านวิศวกรรมหุ่นยนต์ (Perception, Control, Actuation, Mechatronics) เต็ม 10 คะแนน | เป็นเอกเทศ ไม่นับรวมในคะแนน TELOS 100 คะแนน
A27: มิติการประเมิน (Robotics Dimension) | B27: คะแนนศักยภาพ (/10) | C27: แกน Perception & Sensing (การรับรู้) | D27: แกน Control & Algorithms (การควบคุม) | E27: แกน Actuation & Mechanisms (กลไก) | F27: บทวิเคราะห์เชิงวิศวกรรมหุ่นยนต์ (FIBO Alignment Rationale)
A28: ศักยภาพการประยุกต์ใช้องค์ความรู้หุ่นยนต์และระบบอัตโนมัติ | B28: 6.5 | C28: โครงข่ายเซนเซอร์แบบกระจายตัว (Distributed Telemetry Sensing): เซนเซอร์วัดระดับน้ำแบบความดันใต้น้ำ (Hydrostatic Pressure Sensor), เซนเซอร์ตรวจวัดความเร็วน้ำด้วยคลื่นดอปเปลอร์ (Doppler Flow Velocity), และเซนเซอร์ก๊าซพิษ (H2S/CH4) | D28: การควบคุมและติดตามสภาวะแบบกระจายศูนย์ (Supervisory Control and Data Acquisition - SCADA): เครือข่าย LoRaWAN แบบไร้สาย, อัลกอริทึมวิเคราะห์แนวโน้มการไหลใต้ดิน (Predictive Routing Model), และระบบตรวจจับความผิดปกติ (Anomaly Detection) | E28: ไม่มีระบบการทำงานเชิงกลของหุ่นยนต์ (Zero Active Robotics Mechanics) เน้นความทนทานของเคสป้องกันการกัดกร่อน (IP68 Chemical-resistant Enclosure) | F28: มีความเข้ากันได้ในแกน Distributed Sensor Network, การสื่อสารทางไกล และการประมวลผลข้อมูลโทรมาตร แต่ขาดแกนกลไกและการเคลื่อนที่ของหุ่นยนต์ คะแนนจึงอยู่ที่ 6.5

Sheet Solution-5
A1: เมทริกซ์ประเมินความเป็นไปได้เชิงระบบ TELOS+S: UHI Latent Heat Precision Road Cooling (Micro-dosing 0.2-0.4 mm Evaporative Spraying)
A2: ระบบคะแนนจำนวนเต็มเด็ดขาด: 1, 2, 3, 4, 5 เท่านั้น (ไม่มีจุดทศนิยม / ไม่มี 0.5) | โครงสร้างแบบ Transposed แนวนอน
A4: รหัสคำถาม (Question Code) | B4: T-01 | C4: T-02 | D4: T-03 | E4: T-04 | F4: T-05 | G4: E-01 | H4: E-02 | I4: E-03 | J4: L-01 | K4: L-02 | L4: O-01 | M4: O-02 | N4: O-03 | O4: O-04 | P4: O-05 | Q4: O-06 | R4: S-01 | S4: S-02 | T4: SDG-01 | U4: SDG-02 | V4: SDG-03 | W4: สรุปภาพรวม (SUMMARY)
A5: มิติการประเมิน (TELOS+S Pillar) | B5: ด้านเทคโนโลยีและวิศวกรรม (Technical Feasibility) | C5: ด้านเทคโนโลยีและวิศวกรรม (Technical Feasibility) | D5: ด้านเทคโนโลยีและวิศวกรรม (Technical Feasibility) | E5: ด้านเทคโนโลยีและวิศวกรรม (Technical Feasibility) | F5: ด้านเทคโนโลยีและวิศวกรรม (Technical Feasibility) | G5: ด้านเศรษฐศาสตร์ (Economic Feasibility) | H5: ด้านเศรษฐศาสตร์ (Economic Feasibility) | I5: ด้านเศรษฐศาสตร์ (Economic Feasibility) | J5: ด้านกฎหมายและสถาบัน (Legal & Institutional Feasibility) | K5: ด้านกฎหมายและสถาบัน (Legal & Institutional Feasibility) | L5: ด้านการปฏิบัติการ (Operational Feasibility) | M5: ด้านการปฏิบัติการ (Operational Feasibility) | N5: ด้านการปฏิบัติการ (Operational Feasibility) | O5: ด้านการปฏิบัติการ (Operational Feasibility) | P5: ด้านการปฏิบัติการ (Operational Feasibility) | Q5: ด้านการปฏิบัติการ (Operational Feasibility) | R5: ด้านแผนงานและเวลา (Schedule Feasibility) | S5: ด้านแผนงานและเวลา (Schedule Feasibility) | T5: +S ด้านความยั่งยืน (Sustainable Feasibility) | U5: +S ด้านความยั่งยืน (Sustainable Feasibility) | V5: +S ด้านความยั่งยืน (Sustainable Feasibility) | W5: ผลรวมทุกมิติ (All Pillars)
A6: คำถามทดสอบความเสี่ยงจริง (Stress-Test Question) | B6: Implementation (Build vs. Buy Burden): ระบบต้องพัฒนาขึ้นเองจากศูนย์ (Custom R&D) หรือสามารถประกอบขึ้นจากโมดูลสำเร็จรูป (COTS Assembly)? | C6: Access (Tech Stack & Ecosystem Permissions): สแตกเทคโนโลยีและสิทธิ์การเข้าถึงระบบ (Permissions & Ecosystem) มีความเปิดกว้างเพียงใดในการตรวจสอบ แก้ไข และพัฒนาต่อยอด? | D6: Supply (Component Procurement & Vendor Availability): ชิ้นส่วนและอุปกรณ์หลักมีห่วงโซ่อุปทานและความพร้อมในการจัดหา (Supply & Vendor Availability) จากผู้จำหน่ายในระดับใด? | E6: Base Performance (Technology Readiness Level - TRL): ระดับความพร้อมของเทคโนโลยี (TRL) ของระบบอยู่ในขั้นใดเมื่อเทียบกับสภาวะแวดล้อมการใช้งานจริงหน้างาน? | F6: Team Compatibility (Manpower & Skill Redundancy): ทักษะของสมาชิกในทีมมีความเข้ากันได้และการกระจายความเชี่ยวชาญสำรอง (Bus Factor & Redundancy) มากน้อยเพียงใด? | G6: ROI (Payback Period / Value Horizon): ระยะเวลาคืนทุนและกรอบเวลาการสร้างผลตอบแทนคุ้มค่า (Payback Horizon) ต่อระบบสาธารณะหรือผู้ใช้งานอยู่ในเกณฑ์ใด? | H6: Dependencies of Component (Vendor Lock-in & Service Autonomy): ระบบมีความเป็นอิสระจากการผูกขาดของผู้ผลิต (Vendor Lock-in) มากน้อยเพียงใด และสามารถซ่อมบำรุงด้วยเครื่องมือเปิดได้เองหรือไม่? | I6: Scrap Margin (Safety Allowance for Blown ICs & Iterations): โครงการมีการจัดสรรงบประมาณสำรองสำหรับชิ้นส่วนทดแทนกรณีเสียหาย (Scrap Margin) และการทดลองซ้ำมากน้อยเพียงใด? | J6: Felony and Civil Law (Regulatory & Public Safety Compliance): ระบบและการติดตั้งมีความสอดคล้องต่อข้อบังคับทางกฎหมายอาญา แพ่ง ระเบียบจราจร และการคุ้มครองข้อมูลส่วนบุคคล (PDPA / Public Safety) หรือไม่? | K6: IP and Licensing: ทรัพย์สินทางปัญญา ซอฟต์แวร์ไลบรารี และสิทธิบัตรที่นำมาใช้ มีความเปิดกว้างและปลอดภาระผูกพันทางการค้าหรือการละเมิดลิขสิทธิ์ (Licensing Freedom) มากน้อยเพียงใด? | L6: User — Implementation (Field Deployment / Setup Friction): ขั้นตอนการติดตั้ง ติดตั้งเครื่องมือ ปรับเทียบศูนย์ (Calibration) และเตรียมพร้อมใช้งานหน้างานจริงโดยผู้ปฏิบัติงาน มีความยุ่งยากหรือกินเวลาเพียงใด? | M6: User — Customer / Public Safety & Failsafes: ความปลอดภัยเชิงกลและไฟฟ้าต่อเจ้าหน้าที่ผู้ปฏิบัติงานและประชาชนในพื้นที่ (Intrinsic Safety & Failsafes) มีระบบป้องกันในระดับใด? | N6: User — Behavior & Workflow Disruption: ระบบสร้างความเปลี่ยนแปลงหรือรบกวนต่อขั้นตอนการทำงานปกติ (Standard Operating Procedure - SOP) ของผู้ใช้งานเดิมมากน้อยเพียงใด? | O6: Developer — Task Dependency (Critical Path Architecture): โครงสร้างสถาปัตยกรรมของระบบและการแบ่งส่วนงานระหว่างฮาร์ดแวร์ ซอฟต์แวร์ และกลไก มีการแยกส่วน (Decoupling) เพื่อให้พัฒนาคู่ขนานได้มากน้อยเพียงใด? | P6: Developer — Contribution Dependency (Bureaucratic & Lab Gatekeeping): การเข้าถึงเครื่องมือในห้องปฏิบัติการ การอนุมัติงบประมาณ และกระบวนการทางธุรการ (Lab Access & Purchasing Bureaucracy) มีอุปสรรคขัดขวางความคล่องตัวเพียงใด? | Q6: Developer — Task & Skill Compatibility: ความเข้ากันได้ระหว่างทักษะเดิมของทีมกับเทคโนโลยีสแตกของระบบ (Task & Skill Compatibility: 'Water and Oil' vs. 'Oil and Engine') อยู่ในระดับใด? | R6: Production Time (Engineering Design Maturity by Milestone): ความพร้อมของแบบวิศวกรรม (3D CAD, Schematics, PCB Gerbers, Firmware Architecture, BOM) อยู่ในระดับความสมบูรณ์ใดเทียบกับหมุดหมายการผลิตจริง? | S6: Shipping (Component Procurement Lead Time): ระยะเวลาในการจัดหาและขนส่งชิ้นส่วน อุปกรณ์ และเซนเซอร์ (Procurement Lead Time) อยู่ในกรอบเวลาที่ปลอดภัยต่อกำหนดส่งมอบงานหรือไม่? | T6: Real Public Impact vs. Academic Greenwashing (SDG 11.5 / 13.1): Is this genuinely reducing flood/heat losses for the public, or is it just fluff for a presentation slide? | U6: Environmental Footprint & E-Waste ("Do No Harm" — SDG 6.3 / 12.4): Will this hardware end up as toxic e-waste rotting at the bottom of a canal or washing down the river? | V6: Decision Transparency & Public Fairness (SDG 10.2 / 16.6): Can an officer or citizen verify why the system made its call, or is it an unaccountable black box? | W6: ประเมินคำถามทั้งสิ้น 21 ข้อ
A7: เหตุผลในการถาม & โหมดความล้มเหลวที่เฝ้าระวัง (Rationale) | B7: วัดภาระงานสร้างและการวิจัยพัฒนา (Build vs. Buy Burden) ยิ่งสร้างเองจากศูนย์มาก ยิ่งเสี่ยงต่อความล่าช้าและความล้มเหลว | C7: ตรวจสอบอุปสรรคด้านสิทธิ์การเข้าถึง (Access Barriers) เช่น NDA, Closed-source blobs, หรือข้อจำกัดด้านใบอนุญาตที่ขัดขวางการแก้บั๊ก | D7: ตรวจสอบความเสี่ยงด้านห่วงโซ่อุปทาน (Single-source, EOL, Overseas backlog) ที่อาจทำให้โครงการหยุดชะงักเมื่อชิ้นส่วนขาดตลาด | E7: ประเมินความเสถียรของเทคโนโลยีตามมาตรฐาน TRL จากระดับแล็บทดลอง (Lab model) ไปจนถึงระดับใช้งานจริงในสภาวะวิกฤต (Field-proven) | F7: ป้องกัน Single Point of Failure (SPOF) ด้านบุคคล หากมีสมาชิกคนใดคนหนึ่งไม่สามารถปฏิบัติงานได้ ระบบต้องยังสามารถพัฒนาและแก้ไขต่อได้ | G7: วัดความคุ้มค่าทางเศรษฐศาสตร์และการคืนทุนจากการลดความสูญเสีย ค่าแรง หรือค่าเชื้อเพลิง | H7: ตรวจสอบภาระค่าใช้จ่ายแฝงระยะยาว (Recurring Cloud/Licensing Fees) และการพึ่งพาผู้ผลิตรายเดียว | I7: ตรวจสอบงบสำรองสำหรับชิ้นส่วนเสียหาย (Scrap Budget Rule) ป้องกันงานสะดุดเมื่อเกิดชิปไหม้หรือฮาร์ดแวร์หัก | J7: ตรวจสอบความเสี่ยงทางกฎหมายสาธารณะ (พ.ร.บ. จราจร, PDPA, กฎหมายสิ่งแวดล้อม และระเบียบทางหลวง) | K7: ตรวจสอบข้อจำกัดด้านสิทธิ์ซอฟต์แวร์และฮาร์ดแวร์ ป้องกันการติดไวรัสไลเซนส์ (Copyleft GPLv3) หรือการละเมิดสิทธิบัตร | L7: ประเมินความสะดวกในการติดตั้งหน้างาน (Setup Friction) เพื่อป้องกันไม่ให้อุปกรณ์ถูกละเลยเนื่องจากการตั้งค่ายุ่งยาก | M7: ประเมินมาตรการความปลอดภัยและกลไกป้องกันอันตราย (Hazard Failsafes) เช่น สวิตช์ฉุกเฉิน E-stop, ฟิวส์, และการออกแบบป้องกันแรงดันสูง | N7: ประเมินแรงต้านทานจากผู้ใช้งาน (Workflow Friction) และความราบรื่นในการเชื่อมต่อเข้ากับระบบการทำงานเดิมของเจ้าหน้าที่ | O7: ตรวจสอบคอขวดบนสายงานวิกฤต (Critical Path Bottleneck) ป้องกันไม่ให้ทีมซอฟต์แวร์ต้องหยุดรอแผ่นวงจรพิมพ์หรือกลไกที่ยังไม่เสร็จ | P7: ประเมินอุปสรรคด้านการบริหารและเครื่องมือ (Institutional Gatekeeping) เช่น คิวรอเครื่องจักร การล็อกแล็บ หรือขั้นตอนเบิกจ่ายงบประมาณที่ล่าช้า | Q7: ตรวจสอบความสอดคล้องระหว่างทักษะที่ทีมมีอยู่จริงกับเทคโนโลยีที่เลือกใช้ เพื่อป้องกัน Learning Curve ที่สูงเกินไปจนงานล้มเหลว | R7: ประเมินความพร้อมของพิมพ์เขียวการผลิต (Design Maturity Package) ก่อนเริ่มสั่งผลิตจริง เพื่อป้องกันการรื้อแก้แบบกลางคัน | S7: ตรวจสอบห่วงโซ่อุปทาน (Supply Chain Lead Time) ชิ้นส่วนที่ต้องรอส่งจากต่างประเทศเกิน 3 สัปดาห์ถือเป็นความเสี่ยงต่อวิกฤตสัปดาห์สอบและกำหนดส่งมอบ | T7: Your team's 1 vs. 5 premise: "Pure buzzword bullshit to get a grade vs. Actually moves the needle on city infrastructure." | U7: Your team's 1 vs. 5 premise: "Dumping toxic e-waste into public canals vs. Zero-footprint hardware." | V7: Your team's 1 vs. 5 premise: "Black-box algorithm cutting services to poor areas vs. Open, verifiable math." | W7: สังเคราะห์จาก AI Agents Group 2
A8: เกณฑ์การให้คะแนน (Scoring Rubric Definition: ระดับ 1, 2, 3, 4, 5 ครบทุกระดับ) | B8: 1 — Build from Scratch: 100% custom R&D required (custom mechanism, custom PCB, raw algorithm derivation); no reference designs available. 2 — Heavy Customization: Core components exist, but requires extensive custom adaptation, structural machining, and custom wrapper code. 3 — Hybrid / COTS Integration: Standard COTS modules (e.g., standard dev board + breakout sensors) assembled with custom brackets and intermediate wiring. 4 — Modular COTS Assembly: Pre-engineered building blocks with standard mounting and standard communication buses (e.g., Din-rail modules, I2C/CAN shields); minimal custom fabrication. 5 — Commercial Off-the-Shelf (COTS): Buy and use directly out of the box (Plug-and-Play); zero mechanical or electrical fabrication required. | C8: 1 — Strictly Restricted: Proprietary stack under NDA, blocked enterprise firewalls, or unavailable developer licenses. 2 — Limited Access: Closed binary blobs or third-party proprietary software; black-box firmware with zero internal telemetry or source code. 3 — Request-Based Access: Standard educational/evaluation license or public APIs with strict rate limits; requires account verification or approval delays. 4 — Open Developer Access: Free public SDKs, full documentation, and open developer access, but cannot modify upstream core source code. 5 — Unrestricted Full-Stack Access: Fully open source (permissive license) and open hardware; team has root/admin rights to modify, inspect, and deploy as both user and developer. | D8: 1 — Sole-Source / Obsolete: Single overseas supplier, restricted export control, long backorder, or risk of end-of-life (EOL). 2 — Specialized Vendor: Only 1–2 niche industrial suppliers; requires formal corporate quote/PO process; no consumer retail channels. 3 — Moderate Availability: 2–3 regional distributors (e.g., DigiKey, Mouser, Element14); reliable stock but requires overseas shipping. 4 — Multi-Vendor Local Stock: Readily available from multiple domestic vendors; common industrial or maker components with reliable inventory. 5 — Commodity / Off-the-Shelf: Ubiquitous commodity item sold across multiple local electronics shops and online platforms (delivered in 1–2 days). | E8: 1 — Proof of Concept (TRL 3): Bench breadboard or mathematical model; verified only in simulated/controlled lab conditions. 2 — Functional Breadboard (TRL 4): Integrated components working together in lab; messy wiring, fragile, uncalibrated for harsh environments. 3 — Alpha Prototype (TRL 5–6): Enclosed prototype tested in a relevant simulated environment; occasional crashes, requires human supervisor. 4 — Beta / Field-Proven (TRL 7): Pre-production hardware operating reliably in the actual operating environment under real stress. 5 — Commercial Product (TRL 8–9): Fully certified, production-grade commercial product with documented MTBF and mass field reliability. | F8: 1 — Single Point of Failure (SPOF): Only 1 person has the niche skill (if they get sick, the subsystem halts 100%). 2 — Solo Lead with Minimal Backup: 1 person executes; 1 teammate understands basic concepts but cannot debug code or fix hardware alone. 3 — Primary + Secondary Pair: 1 primary developer and 1 competent secondary backup who can maintain, troubleshoot, and push updates. 4 — Broad Competence: 3+ teammates can actively design, assemble, and debug the subsystem with low ramp-up time. 5 — Full Team Redundancy: All team members are fully proficient; tasks can be swapped across anyone with zero friction or velocity loss. | G8: 1 — Long Payback ($\ge 10\text{ Years}$): High initial CapEx and low recurring savings; economically non-viable for rapid deployment. 2 — Slow Return ($6–9\text{ Years}$): Substantial capital investment with long break-even horizon; requires long-term institutional subsidization. 3 — Moderate Return ($3–5\text{ Years}$): Reasonable public infrastructure payback; offsets costs across multi-year operational cycles. 4 — Fast Return ($2–3\text{ Years}$): Strong operational cost reduction (fuel, labor, scrap); breaks even within normal equipment lifecycle. 5 — Immediate Payback ($\le 1–2\text{ Years}$): Rapid break-even; eliminates major recurring losses within the first operating season. | H8: 1 — Total Vendor Lock-in: Proprietary cloud backend, encrypted telemetry, and proprietary connectors; completely dependent on vendor survival. 2 — High Dependency: Hardware requires vendor-licensed diagnostic tools or annual subscription fees to maintain operation. 3 — Semi-Independent: Core hardware relies on proprietary firmware, but allows open API export and standard electrical interfaces. 4 — High Autonomy: Uses standard open communication protocols (e.g., Modbus, MQTT, CAN); parts can be serviced using generic tools. 5 — Complete Independence: 100% open architecture; hardware is interchangeable with generic substitutes; self-serviceable by any engineer. | I8: 1 — Zero Buffer (0%): Exactly 1x BOM purchased; any fried chip, cracked bracket, or wiring mistake kills the project. 2 — Fragile Buffer (20–30%): Spares only for passive components (resistors, connectors); no backup microcontrollers or expensive sensors. 3 — Moderate Buffer (50%): Spares for all critical passive parts and 1 spare for the primary controller board. 4 — High Buffer (80%): Spares for nearly every active component and sensor; can sustain multiple prototype burn-ins. 5 — Full Redundancy ($\ge 100\%$): Complete 2x BOM budget on hand; can build two complete working units simultaneously. | J8: 1 — Severe Violation / No Privilege: Direct breach of statutory law (e.g., unconsented public surveillance/PDPA, hazardous road blockage, RF jammer). 2 — High Legal Exposure: Ambiguous legal zone; high risk of civic complaints or traffic disruption; requires complex technical waivers. 3 — Conditional / Requires Permit: Allowed under explicit written approval, official agency MoU, or municipal permit (e.g., BMA/Highway dept permit). 4 — Low Legal Friction: Operates within standard public engineering exemptions; simple standard notification/safety compliance needed. 5 — 100% Compliant / Free Domain: Completely exempt from statutory licensing; zero public safety risk, zero personal data (Zero PII), fully unrestricted. | K8: 1 — Closed / Commercial Barrier: Proprietary commercial license; cannot compile, flash, or operate without paying expensive commercial seat licenses. 2 — Ambiguous / Gray IP: Unclear licensing terms or unlicensed GitHub repos; risk of copyright strike or IP dispute upon public demonstration. 3 — Restrictive Open Source (Copyleft): Permitted for educational use, but viral licenses (e.g., GPLv3) force your entire codebase to be made public if distributed. 4 — Permissive Open Source: Open source with minimal conditions (e.g., LGPL, CC-BY); allows proprietary wrapping with simple attribution. 5 — Completely Permissive / Public Domain: Permissive open source (MIT, Apache 2.0, BSD) or Public Domain; unrestricted freedom to commercialize, modify, and contribute. | L8: 1 — Laborious Recalibration: Requires multi-point manual physical zeroing, chemical calibration, or oscilloscope tuning before every run. 2 — Complex Setup: Requires trained technician 20–30 minutes to adjust potentiometers, align brackets, or enter configuration commands. 3 — Moderate Field Setup: Simple 5-minute calibration procedure (e.g., tare button or basic mobile app zeroing) performed by non-engineers. 4 — Minimal Setup: Fast clamp-on mounting with automated self-calibration on power-up; ready in $< 1\text{ minute}$. 5 — True Plug and Go: Pure plug-and-play; zero calibration required, zero buttons; power on and immediately operational. | M8: 1 — Critical Hazard: Failure can directly cause electrocution, fire, traffic crashes, chemical exposure, or confined-space asphyxiation. 2 — High Risk / Manual Oversight: High mechanical/electrical hazard requiring constant operator vigilance and full PPE. 3 — Moderate Safety: Protected by passive mechanical guards, fuses, and warning labels; requires basic safety precautions. 4 — High Safety & Interlocks: Active software limits, hardware thermal shutoffs, and reverse polarity protection; minimal hazard on failure. 5 — Inherently Safe & Redundant: Failsafe by physics (cannot store lethal energy); isolated, dual-rated enclosures, redundant E-stops, zero injury risk. | N8: 1 — Disruptive Overhaul: Forces operators to abandon existing SOPs, adds 5+ extra tedious forms/steps, and faces fierce institutional union/worker resistance. 2 — Significant Friction: Adds notable extra documentation or redundant verification steps; operators will actively look for ways to bypass it. 3 — Moderate Adaptation: Modifies daily routine slightly; requires 1–2 training workshops, but delivers clear convenience trade-offs. 4 — Low Friction: Integrates into existing tools (e.g., sends automated alerts to existing LINE/Telegram or ticketing dashboard); minimal change in habits. 5 — Transparent / Seamless Integration: Zero workflow disruption; runs invisibly in background and automates existing manual paperwork without operator intervention. | O8: 1 — Strictly Sequential (Linear): A depends on B depends on C; if the PCB fab is delayed, software and testing halt 100%. 2 — Bottlenecked Pipelines: Major subsystems are tightly coupled; frequent integration stalls waiting for hardware bench access. 3 — Semi-Decoupled: Hardware and software teams can work independently for 1–2 weeks using rough mockups before needing physical integration. 4 — Modular Parallelism: Clear API/interface boundaries; software builds against mock data/simulators while hardware is routed; integration takes $< 2\text{ days}$. 5 — Fully Parallel Architecture: Microservices/modular nodes with standard contracts; mechanical, electrical, and firmware develop, simulate, and unit-test completely in parallel. | P8: 1 — Heavy Gatekeeping: Blocked by supervisor approvals, locked lab cabinets, NDA signatures, purchasing bureaucracy, and restricted git branches. 2 — Moderate Bureaucracy: Requires departmental request forms, tool booking queues, and waiting 3–5 days for administrative sign-offs. 3 — Standard Campus Access: Workable access during university open hours; minor approval delays for equipment or lab keys. 4 — High Autonomy: Team has full repository write access, open 24/7 lab entry, and pre-approved discretionary debit cards/stipends for rapid purchases. 5 — Frictionless Contribution: Complete autonomy; decentralized cloud CI/CD, local prototyping tools at home/bench, zero administrative blockers. | Q8: 1 — Complete Mismatch ("Water and Oil"): Team has zero foundation in the stack (e.g., pure mechanical students forced to train deep neural nets in C++ from scratch). 2 — Steep Learning Curve: High theoretical knowledge, but zero production hands-on experience; debugging basic syntax/wiring stalls progress. 3 — Adjacent Competence: Strong mastery in related tools (e.g., proficient in Arduino/ESP32 migrating to STM32, or SolidWorks migrating to Fusion360); manageable 1-week curve. 4 — Proven Experience: Team has built similar subsystems in past semester coursework or competition robots; rapid ramp-up. 5 — Perfect Synergy ("Oil and Engine"): Complete domain mastery; team members have built this exact architecture multiple times with verified libraries and muscle memory. | R8: 1 — Concept Only (0% Design): Napkin sketches and verbal concepts; 0% CAD models, 0% schematics, 0% code written. 2 — Rough Drafts (25% Design): Preliminary block diagrams, hand-drawn schematics, unverified parts list, incomplete 3D bounding boxes. 3 — Intermediate Maturity (50% Design): Complete CAD assembly (untested clearances), schematic capture complete, draft firmware architecture mapped out. 4 — Pre-Production (80% Design): Fully detailed 3D CAD ready for 3D print/CNC, routed PCB Gerber files validated with DRC, pinouts locked down. 5 — Fully Engineered Design (100% Production Ready): Complete drawing package: BOM with part numbers, verified manufacturing Gerbers, 2D tolerance drawings, assembly SOP, and flashing scripts ready. | S8: 1 — Extreme Lead Time ($\ge 4\text{ Weeks}$): Custom overseas fabrication, customs clearance delays, or parts with long factory lead times (critical path hazard). 2 — High Lead Time ($3–4\text{ Weeks}$): Standard overseas shipping (e.g., standard AliExpress/international postal surface mail); vulnerable to logistics delays. 3 — Moderate Lead Time ($2\text{ Weeks}$): Express international courier (DHL, FedEx, JLCPCB express) or regional distributors (7–14 days). 4 — Short Lead Time ($1\text{ Week}$): Domestic couriers or express domestic stockists (3–5 business days). 5 — Immediate / Next-Day ($\le 1–2\text{ Days}$): Shelf stock available locally at retail shops or next-day domestic express delivery. | T8: 1 — Pure Buzzword / Academic Greenwashing: Claims to "save the city," but has zero real data, zero measurable effect, and solves a problem nobody in the municipality actually experiences. 2 — Superficial Correlation: Indirect impact; functions only as an isolated school demo with no realistic way to measure if it prevented damage or saved money. 3 — Localized Proof: Delivers a measurable, verified benefit (e.g., cuts response time by 10 minutes or drops pavement temp on a single test strip), but lacks a model to scale. 4 — District-Level Viability: Clear pathway to protect municipal infrastructure or reduce public losses across multiple roads/alleys during extreme weather. 5 — Systemic City Resilience: Backed by concrete empirical data showing significant reduction in public economic losses, vehicle damage, or human hazard during severe rain or heat. | U8: 1 — Toxic Canal Hazard: Cheap plastic enclosure cracks under UV, or unsealed LiPo batteries leak toxic chemicals and detach into the drainage network as marine litter. 2 — Fragile Disposable Tech: Short operational lifespan; sensors foul or corrode within 2–3 weeks and are left behind by crews because retrieving them is too annoying. 3 — Standard Field Footprint: Requires periodic battery replacement and creates standard electronic scrap, but utilizes basic tethering to prevent total hardware loss. 4 — Low-Impact Enclosure: Solar-trickle or long-life low-power architecture; uses recyclable casing and redundant physical tethers (e.g., dual stainless lanyards). 5 — Fully Circular & Zero Footprint: 100% fail-safe retrieval design; uses non-toxic, non-leaching materials, consumes minimal public water/energy, and leaves zero trace in the city. | V8: 1 — Opaque Black Box: Proprietary or unexplained threshold that cancels dispatch trucks or alters services with zero explanation, risking quiet abandonment of vulnerable neighborhoods. 2 — Ambiguous Logic: Decision rules are buried in messy heuristic code; field operators cannot explain to a citizen why an alert was triggered or suppressed. 3 — Documented Internal Rules: Logic is documented on paper for engineers, but has no public audit trail or clear appeal mechanism if the sensor misreads. 4 — Open Empirical Standards: Decisions are driven by transparent physical equations (e.g., verified dh/dt thresholds) applied equally across all city zones. 5 — 100% Auditable & Equitable: Full tamper-evident digital audit trail; open logic accessible to city officials and citizens, guaranteeing equal public protection regardless of district wealth. | W8: เกณฑ์รวม: >=80 ผ่านสูง, >=60 มีเงื่อนไข, <60 เสี่ยงสูง | หากมีข้อใดได้ 1 = VETOED ตกเกณฑ์ทันที
A9: คะแนนที่ได้รับ (ASSIGNED SCORE: 1, 2, 3, 4, 5 STRICT INTEGER) | B9: 2 | C9: 5 | D9: 4 | E9: 3 | F9: 3 | G9: 3 | H9: 4 | I9: 3 | J9: 2 | K9: 5 | L9: 2 | M9: 2 | N9: 4 | O9: 2 | P9: 2 | Q9: 4 | R9: 3 | S9: 4 | T9: 5 | U9: 4 | V9: 5 | W9: =IF(W10>0, (W11/W10)*20, 0) -> 67.938794
A10: ค่าน้ำหนัก (Weight %) | B10: 0.04 | C10: 0.04 | D10: 0.04 | E10: 0.04 | F10: 0.04 | G10: 0.0667 | H10: 0.0667 | I10: 0.0666 | J10: 0.075 | K10: 0.075 | L10: 0.0333 | M10: 0.0333 | N10: 0.0333 | O10: 0.0333 | P10: 0.0333 | Q10: 0.0334 | R10: 0.075 | S10: 0.075 | T10: 0.0333 | U10: 0.0333 | V10: 0.0334 | W10: =SUM(B10:V10) -> 0.9999
A11: คะแนนถ่วงน้ำหนัก (=Score * Weight) | B11: =B9*B10 -> 0.08 | C11: =C9*C10 -> 0.2 | D11: =D9*D10 -> 0.16 | E11: =E9*E10 -> 0.12 | F11: =F9*F10 -> 0.12 | G11: =G9*G10 -> 0.2001 | H11: =H9*H10 -> 0.2668 | I11: =I9*I10 -> 0.1998 | ... V11: =V9*V10 -> 0.167 | W11: =SUM(B11:V11) -> 3.3966
A12: คำอธิบาย & หลักฐานอ้างอิงจากไฟล์ Intake (Evidence Citation) | B12: อ้างอิง solution-5_uhi_latent_heat.md: ต้องออกแบบโครงสร้างขายึดรับแรงสั่นสะเทือนบนรถ ติดตั้งระบบปั๊มแรงดันและท่อไฮดรอลิกส์สั่งทำพิเศษ (Heavy Customization) | C12: ระบบใช้ไมโครคอนโทรลเลอร์ Arduino/ESP32 ควบคุมวาล์วและปั๊มด้วยโค้ดโอเพนซอร์ส ทีมมีสิทธิ์ในการปรับแต่งและเข้าถึงอย่างอิสระ 100% (Unrestricted Full-Stack Access) | D12: ปั๊มแรงดันไดอะแฟรม หัวพ่นหมอกสแตนเลส ท่อแรงดันสูง และวาล์วโซลินอยด์มีสต็อกจำหน่ายในร้านอุปกรณ์เกษตรและอุตสาหกรรมในไทย (Multi-Vendor Local Stock) | E12: หลักการพ่นละอองลดความร้อนผิวถนนมีการศึกษาในญี่ปุ่น/จีน (TRL 6-7) เวอร์ชันของทีมเป็น Alpha Prototype บนรถทดสอบในวิทยาเขต (TRL 5-6) | F12: สมาชิก 2 คน (Fifa ด้านกลไกไฮดรอลิกส์ และ Due ด้านระบบควบคุมไฟฟ้าปั๊ม) เป็นแกนหลักในการสร้างชุดพ่นหมอก (Primary + Secondary Pair) | G12: ลดอุณหภูมิผิวทางเท้าและลดความเครียดทางความร้อนของประชาชน จุดคุ้มทุน 3-5 ปีในมิติด้านสิ่งแวดล้อมและสุขภาพเมือง | H12: ปั๊มน้ำ วาล์วโซลินอยด์ และหัวพ่นหมอกเป็นอะไหล่มาตรฐานอุตสาหกรรม/การเกษตร หาซื้อเปลี่ยนทดแทนได้ง่าย | I12: อุปกรณ์ปั๊มแรงดันสูงและชุดหัวฉีดสแตนเลสมีราคาสูง สามารถสำรองอะไหล่ได้ประมาณ 50% ของงบประมาณ | J12: การพ่นละอองน้ำบนถนนหลวงมีข้อบังคับ พ.ร.บ. จราจรทางบกเรื่องความปลอดภัยผิวทางลื่น เสี่ยงต่อการเกิดอุบัติเหตุ ต้องขอข้อยกเว้นและมีมาตรการความปลอดภัยเข้มงวด | K12: ใช้หลักการทางอุณหพลศาสตร์และสมการความร้อนแฝง (Latent Heat of Vaporization) เปิดเผย ปลอดปัญหาทรัพย์สินทางปัญญา | L12: การเตรียมระบบก่อนออกวิ่งต้องติดตั้งโครงบูม เติมน้ำ ตรวจสอบแรงดันปั๊ม และล้างไส้กรอง ใช้เวลาประมาณ 15-20 นาที | M12: ปฏิบัติงานบนยานพาหนะเคลื่อนที่ร่วมกับการจราจรจริง เสี่ยงต่อการเฉี่ยวชนและละอองน้ำบดบังทัศนวิสัย ต้องมีป้ายไฟเตือนและระบบตัดน้ำฉุกเฉิน E-stop | N12: ปรับติดตั้งเข้ากับรถบริการเดิมของเทศบาลหรือรถรดน้ำต้นไม้ เจ้าหน้าที่ขับขี่รถตามเส้นทางปกติโดยมีระบบพ่นน้ำอัตโนมัติ | O12: การพัฒนาระบบควบคุมต้องพึ่งพารถต้นแบบจริงเพื่อทดสอบแรงสั่นสะเทือนและการกระจายตัวของละอองน้ำ ซอฟต์แวร์จึงผูกติดกับฮาร์ดแวร์สูง | P12: การขอใช้ยานพาหนะและสนามทดสอบของมหาวิทยาลัยต้องผ่านกระบวนการขออนุมัติและรอคิว 3-5 วันทำการ | Q12: สมาชิกมีความเชี่ยวชาญด้านกลไก (Fifa), ระบบควบคุมไฟฟ้า (Due) และการวัดอุณหภูมิ (JK) สอดคล้องกับงานที่ถนัดเดิม ('Oil and Engine') | R12: แบบ 3D CAD ของโครงสร้างยึดรถและผังระบบท่อน้ำอยู่ในระดับ 50% Design กำลังคำนวณ Stress Analysis ของขายึด | S12: ปั๊มแรงดันสูง 12V/24V และหัวพ่นหมอกสแตนเลสมีจำหน่ายในประเทศ จัดส่งถึงภายใน 3-5 วันทำการ | T12: ลดอุณหภูมิเกาะความร้อนเมือง (Urban Heat Island) โดยตรง 3-7°C ช่วยลดความเสี่ยง Heatstroke ของคนเดินเท้า เสริมการปรับตัวต่อสภาพภูมิอากาศสุดขั้ว (SDG 11.5 / 13.1) | U12: ระบบพ่นละอองละเอียด Micro-dosing ประหยัดน้ำกว่าการฉีดล้างถนนทั่วไปถึง 80% มีระบบกรองน้ำรีไซเคิล (SDG 6.4 และ SDG 12.4 ได้ระดับ 4) | V12: ช่วยลดความร้อนให้แก่ประชาชนกลุ่มเปราะบาง คนรอรถเมล์ และผู้มีรายได้น้อยที่ต้องเดินสัญจรกลางแจ้ง สร้างความเท่าเทียมในเมือง (SDG 10.2 / 11.7) | W12: =IF(MIN(B9:V9)=1, "VETOED / ตกเกณฑ์ข้อบังคับวิกฤต (คะแนนระดับ 1)", IF(W9>=80, "ผ่านเกณฑ์ระดับสูง (HIGHLY VIABLE)", IF(W9>=60, "ผ่านแบบมีเงื่อนไข (CONDITIONALLY VIABLE)", "ความเสี่ยงสูง (HIGH RISK)"))) -> ผ่านแบบมีเงื่อนไข (CONDITIONALLY VIABLE)
A13: แผนลดขอบเขตงาน & มาตรการลดความเสี่ยง (De-scoping Action) | B13: ใช้ท่อและข้อต่อสวมเร็วแบบ Quick-fitting แรงดันสูงสำเร็จรูปเพื่อลดการเชื่อมกลึง | C13: เขียนอัลกอริทึมควบคุมรอบการพ่นด้วยไลบรารีโอเพนซอร์สบน Arduino/ESP32 | D13: เลือกใช้หัวพ่นหมอกขนาดเกลียวมาตรฐาน 3/16 นิ้วที่หาซื้อได้ทั่วไป | E13: ทดสอบแรงดันปั๊มบนแท่นทดสอบจำลองก่อนติดตั้งบนรถจริง | F13: ทำแผนผังระบบท่อและวงจรควบคุมไฟฟ้าให้สมาชิกทุกคนเข้าใจตำแหน่งวาล์วฉุกเฉิน | G13: จำกัดขอบเขตการทดสอบเฉพาะถนนภายในวิทยาเขตเพื่อควบคุมค่าใช้จ่าย | H13: เลือกใช้หัวพ่นหมอกขนาดเกลียวมาตรฐาน 3/16 นิ้วที่หาซื้อได้ทั่วไป | I13: จัดซื้อหัวพ่นหมอกสำรอง 5 หัว และโอริงสำรอง 1 ชุด | J13: ทำหนังสือขออนุญาตใช้ถนนภายในมหาวิทยาลัยในการทดสอบวิ่ง โดยกำหนดความเร็วไม่เกิน 20 กม./ชม. | K13: เขียนอัลกอริทึมควบคุมรอบการพ่นด้วยไลบรารีโอเพนซอร์สบน Arduino/ESP32 | L13: ติดตั้งข้อต่อสวมเร็วสำหรับเติมน้ำและมีเกจวัดแรงดันแบบเห็นได้ชัดเจน | M13: ติดตั้งไฟกะพริบเตือนสีเหลืองด้านหลังรถ และมีปุ่ม E-stop ตัดไฟปั๊มน้ำในห้องโดยสาร | N13: ติดตั้งสวิตช์เปิด-ปิดระบบในตำแหน่งที่คนขับเอื้อมถึงง่าย | O13: สร้างชุดแท่นทดสอบหัวพ่นหมอกขนาดเล็กบนโต๊ะแล็บเพื่อทดสอบวงจรควบคุมล่วงหน้า | P13: ทำหนังสือขออนุญาตใช้รถกระบะและพื้นที่ทดสอบกับภาควิชาล่วงหน้า | Q13: จัดฝึกอบรมความปลอดภัยด้านระบบแรงดันสูงภายในทีม | R13: เร่งทดสอบการประกอบโครงบูมเข้ากับท้ายรถให้เสร็จก่อนสัปดาห์ที่ 8 | S13: สั่งซื้อปั๊มแรงดันและอุปกรณ์ระบบน้ำจากร้านค้าในไทยทันทีที่อนุมัติแบบ | T13: ติดตั้งเซนเซอร์วัดอุณหภูมิผิวถนนเปรียบเทียบก่อน-หลังฉีดพ่นเพื่อทำรายงานผลลัพธ์เชิงวิทยาศาสตร์ | U13: ติดตั้งระบบกรองตะกรันเพื่อยืดอายุการใช้งานของหัวพ่นและประหยัดน้ำ | V13: จัดเส้นทางวิ่งพ่นละอองน้ำเน้นพื้นที่ป้ายรถเมล์และทางเท้าที่มีประชาชนหนาแน่น | W13: ปฏิบัติตามแผนลดขอบเขตงาน (De-scoping Advisory)
A15: ตารางสรุปคะแนนแยกตามมิติ TELOS+S (Pillar Score Breakdown)
A16: มิติการประเมิน (TELOS+S Pillar) | B16: สัดส่วนน้ำหนัก (Weight %) | C16: คะแนนเต็มมิติ (Max Points) | D16: คะแนนที่ได้รับจริง (Earned Points) | E16: คะแนนเฉลี่ย (Score 1-5) | F16: ระดับความพร้อม (Readiness Level)
A17: T : ด้านเทคโนโลยีและวิศวกรรม (Technical) | B17: 0.2 | C17: 20 | D17: =SUM(B11:F11)*20 -> 13.6 | E17: =IF(C17>0, (D17/C17)*5, 0) -> 3.4 | F17: =IF(D17>=16, "พร้อมระดับสูง (High)", IF(D17>=12, "ปานกลาง (Medium)", "เสี่ยงวิกฤต (Critical)")) -> ปานกลาง (Medium)
A18: E : ด้านเศรษฐศาสตร์และความคุ้มค่า (Economic) | B18: 0.2 | C18: 20 | D18: =SUM(G11:I11)*20 -> 13.334 | E18: =IF(C18>0, (D18/C18)*5, 0) -> 3.3335 | F18: =IF(D18>=16, "พร้อมระดับสูง (High)", IF(D18>=12, "ปานกลาง (Medium)", "เสี่ยงวิกฤต (Critical)")) -> ปานกลาง (Medium)
A19: L : ด้านกฎหมาย ระเบียบ และภาคประชาชน (Legal & Outreach) | B19: 0.15 | C19: 15 | D19: =SUM(J11:K11)*20 -> 10.5 | E19: =IF(C19>0, (D19/C19)*5, 0) -> 3.5 | F19: =IF(D19>=12, "พร้อมระดับสูง (High)", IF(D19>=9, "ปานกลาง (Medium)", "เสี่ยงวิกฤต (Critical)")) -> ปานกลาง (Medium)
A20: O : ด้านการปฏิบัติการและหน้างาน (Operational) | B20: 0.2 | C20: 20 | D20: =SUM(L11:Q11)*20 -> 10.664 | E20: =IF(C20>0, (D20/C20)*5, 0) -> 2.666 | F20: =IF(D20>=16, "พร้อมระดับสูง (High)", IF(D20>=12, "ปานกลาง (Medium)", "เสี่ยงวิกฤต (Critical)")) -> เสี่ยงวิกฤต (Critical)
A21: S : ด้านแผนงานและเวลาส่งมอบ (Schedule) | B21: 0.15 | C21: 15 | D21: =SUM(R11:S11)*20 -> 10.5 | E21: =IF(C21>0, (D21/C21)*5, 0) -> 3.5 | F21: =IF(D21>=12, "พร้อมระดับสูง (High)", IF(D21>=9, "ปานกลาง (Medium)", "เสี่ยงวิกฤต (Critical)")) -> ปานกลาง (Medium)
A22: +S : ด้านความยั่งยืนและสิ่งแวดล้อม (Sustainability / SDG) | B22: 0.1 | C22: 10 | D22: =SUM(T11:V11)*20 -> 9.334 | E22: =IF(C22>0, (D22/C22)*5, 0) -> 4.667 | F22: =IF(D22>=8, "พร้อมระดับสูง (High)", IF(D22>=6, "ปานกลาง (Medium)", "เสี่ยงวิกฤต (Critical)")) -> พร้อมระดับสูง (High)
A23: คะแนนรวมทุกมิติ (Total Feasibility Score) | B23: =SUM(B17:B22) -> 1 | C23: =SUM(C17:C22) -> 100 | D23: =SUM(D17:D22) -> 67.932 | E23: =IF(C23>0, (D23/C23)*5, 0) -> 3.3966 | F23: =IF(D23>=80, "ผ่านเกณฑ์ระดับสูง (HIGHLY VIABLE)", IF(D23>=60, "ผ่านแบบมีเงื่อนไข (CONDITIONALLY VIABLE)", "ความเสี่ยงสูง (HIGH RISK)")) -> ผ่านแบบมีเงื่อนไข (CONDITIONALLY VIABLE)
A25: เมทริกซ์ประเมินความเข้ากันได้กับองค์ความรู้ด้านวิศวกรรมหุ่นยนต์ (Robotics Knowledge Compatibility)
A26: * หมายเหตุ: การประเมินส่วนนี้วัดศักยภาพในการประยุกต์ใช้องค์ความรู้ด้านวิศวกรรมหุ่นยนต์ (Perception, Control, Actuation, Mechatronics) เต็ม 10 คะแนน | เป็นเอกเทศ ไม่นับรวมในคะแนน TELOS 100 คะแนน
A27: มิติการประเมิน (Robotics Dimension) | B27: คะแนนศักยภาพ (/10) | C27: แกน Perception & Sensing (การรับรู้) | D27: แกน Control & Algorithms (การควบคุม) | E27: แกน Actuation & Mechanisms (กลไก) | F27: บทวิเคราะห์เชิงวิศวกรรมหุ่นยนต์ (FIBO Alignment Rationale)
A28: ศักยภาพการประยุกต์ใช้องค์ความรู้หุ่นยนต์และระบบอัตโนมัติ | B28: 9 | C28: ระบบวัดอุณหภูมิพื้นผิวถนนแบบไม่สัมผัส (Infrared Pyrometer / Thermal Camera), เซนเซอร์วัดอุณหภูมิอากาศ, ความชื้นสัมพัทธ์ และเซนเซอร์วัดความเร็วลม (Ultrasonic Anemometer) | D28: ระบบควบคุมอุณหพลศาสตร์วงปิด (Closed-loop Thermodynamic Control): คำนวณอัตราการระเหยตามสมการ Penman-Monteith, การควบคุมความดันและรอบการพ่นแบบ PWM, และการประเมินสภาวะถนนลื่น (Surface Slip Detection) | E28: ระบบกลไกและการฉีดพ่นขั้นสูง: โครงบูมปรับมุมองศาด้วยเซอร์โว/กระบอกสูบไฮดรอลิกส์, ปั๊มแรงดันสูง (High-Pressure Diaphragm Pump), วาล์วโซลินอยด์ควบคุมแรงดัน และหัวพ่นหมอกแบบป้องกันการหยด (Anti-drip Misting Nozzles) | F28: มีความเข้ากันได้อย่างสมบูรณ์แบบสูงสุดกับหลักสูตรวิศวกรรมหุ่นยนต์และระบบอัตโนมัติ (FIBO) ครบทั้ง 3 เสาหลัก: Perception (Thermal Imaging), Control (Thermodynamic Closed-loop Control) และ Actuation/Mechatronics (Vehicle-mounted High-pressure Hydraulics & Mechanics) ได้คะแนน 9.0
